Workbook

Sheet attack-vectors-knowledge-base
A1: ID | B1: Scope | C1: Vector | D1: Category | E1: Kill_chain_phase | F1: Severity_default | G1: Description | H1: Impact | I1: Test_approach | J1: Remediation | K1: Detection_note | L1: OWASP_Top10_2025 | M1: OWASP_API_2023 | N1: WSTG | O1: ASVS_5.0 | P1: MITRE_ATTACK | Q1: CWE | R1: PayloadsAllTheThings | S1: OSCP_plus | T1: CISSP_domain | U1: Evidence | V1: CVSS_score | W1: CVSS_vector | X1: Affected_versions | Y1: Fixed_in | Z1: CISA_KEV | AA1: Exploit_public | AB1: Related_IDs | AC1: Other_mapping | AD1: References | AE1: Last_updated
A2: AV-WEB-01 | B2: Web application | C2: Broken access control / IDOR | D2: Authorization | E2: Privilege escalation | F2: High | G2: Object-referenties zonder server-side autorisatiecheck laten toegang tot data van andere gebruikers toe. | H2: Ongeautoriseerde toegang tot of manipulatie van andermans records. | I2: Wissel object-identifiers en rollen om en controleer of autorisatie server-side wordt afgedwongen (zie WSTG-ATHZ). | J2: Dwing autorisatie centraal af per object en per functie; gebruik indirecte referenties. | K2: Log en alarmeer op toegang tot objecten buiten het bereik van de gebruiker. | L2: A01:2025 | M2: API1:2023 | N2: WSTG-ATHZ-04 | O2: V8 | P2: T1078 | Q2: CWE-639, CWE-284 | R2: Insecure Direct Object References | S2: Web attacks | T2: D5 | AB2: AV-API-01 | AD2: https://owasp.org/www-project-web-security-testing-guide/latest/4-Web_Application_Security_Testing/05-Authorization_Testing/04-Testing_for_Insecure_Direct_Object_References | AE2: 2026-10-09
A3: AV-WEB-02 | B3: Web application | C3: Vertical privilege escalation | D3: Authorization | E3: Privilege escalation | F3: High | G3: Een lager geprivilegieerde gebruiker bereikt functies of data die voor hogere rollen bedoeld zijn. | H3: Overname van admin-functionaliteit of gevoelige acties. | I3: Benader admin-endpoints met een gebruikersaccount en controleer rol-enforcement (WSTG-ATHZ). | J3: Deny-by-default, rolcontrole op elke functie, geen vertrouwen op verborgen UI. | K3: Alarmeer op admin-acties door niet-admin-accounts. | L3: A01:2025 | M3: API5:2023 | N3: WSTG-ATHZ-02, WSTG-ATHZ-03 | O3: V8 | P3: T1068, T1078 | Q3: CWE-269 | R3: Privilege Escalation | S3: Web attacks | T3: D5 | AB3: AV-API-05, CVE-2025-29927, CVE-2023-22515 | AE3: 2026-10-09
A4: AV-WEB-03 | B4: Web application | C4: SQL injection | D4: Injection | E4: Execution | F4: High | G4: Onvertrouwde invoer wordt als SQL geinterpreteerd, waardoor queries manipuleerbaar zijn. | H4: Uitlezen, wijzigen of verwijderen van database-inhoud; soms code-uitvoering. | I4: Toets invoervelden op injectie via afwijkend gedrag en foutmeldingen; bevestig met review op parameterized queries (WSTG-INPV). | J4: Parameterized queries / prepared statements; least-privilege DB-accounts. | K4: WAF- en DB-anomaliedetectie op ongebruikelijke querypatronen. | L4: A05:2025 | N4: WSTG-INPV-05 | O4: V1, V2 | P4: T1190 | Q4: CWE-89 | R4: SQL Injection | S4: Web attacks | T4: D8 | AB4: AV-WEB-36, CVE-2023-34362, CVE-2026-9082, CVE-2026-72898 | AE4: 2026-10-09
A5: AV-WEB-04 | B5: Web application | C5: Command injection | D5: Injection | E5: Execution | F5: Critical | G5: Invoer bereikt een OS-command-interpreter en laat uitvoering van systeemcommando's toe. | H5: Uitvoering van commando's op de host, potentieel volledige compromittering. | I5: Identificeer functies die OS-commando's aanroepen en controleer of invoer wordt afgeschermd (WSTG-INPV). | J5: Vermijd shell-aanroepen; gebruik veilige API's en strikte allowlists. | K5: Monitor op onverwachte child-processen van webprocessen. | L5: A05:2025 | N5: WSTG-INPV-12 | O5: V1 | P5: T1190, T1059 | Q5: CWE-78 | R5: Command Injection | S5: Web attacks | T5: D8 | AB5: AV-HOST-02, CVE-2024-4577, CVE-2014-6271, CVE-2024-3400 | AE5: 2026-10-09
A6: AV-WEB-05 | B6: Web application | C6: Reflected XSS | D6: Injection / client-side | E6: Execution | F6: Medium | G6: Onge-encodeerde invoer wordt direct in de respons weerspiegeld en in de browser uitgevoerd. | H6: Uitvoering van script in de context van het slachtoffer; sessiediefstal, phishing. | I6: Controleer of gereflecteerde invoer context-correct wordt ge-encodeerd (WSTG-CLNT). | J6: Output-encoding per context; Content Security Policy als extra laag. | K6: CSP-report-endpoints en afwijkende URL-parameters loggen. | L6: A05:2025 | N6: WSTG-INPV-01 | O6: V1, V3 | P6: T1059.007, T1539 | Q6: CWE-79 | R6: XSS Injection | S6: Web attacks | T6: D8 | AB6: AV-WEB-41, AV-WEB-42, AV-WEB-19 | AE6: 2026-10-09
A7: AV-WEB-06 | B7: Web application | C7: Stored XSS | D7: Injection / client-side | E7: Execution | F7: High | G7: Kwaadaardige invoer wordt opgeslagen en later ongeencodeerd aan andere gebruikers getoond. | H7: Breed bereik; script draait bij elke bezoeker van de getroffen pagina. | I7: Plaats gemarkeerde invoer en controleer encoding bij weergave elders (WSTG-CLNT). | J7: Output-encoding en input-sanitisatie; CSP. | K7: Content-integriteit en CSP-violations monitoren. | L7: A05:2025 | N7: WSTG-INPV-02 | O7: V1, V3 | P7: T1059.007, T1539 | Q7: CWE-79 | R7: XSS Injection | S7: Web attacks | T7: D8 | AB7: AV-WEB-41, AV-WEB-05 | AE7: 2026-10-09
A8: AV-WEB-07 | B8: Web application | C8: Server-side request forgery (SSRF) | D8: Access control | E8: Discovery | F8: High | G8: De server wordt aangezet tot het benaderen van interne of onbedoelde bestemmingen. | H8: Toegang tot interne services, metadata-endpoints en netwerkverkenning. | I8: Controleer of gebruikersgestuurde URL's server-side worden gevalideerd tegen een allowlist (WSTG-INPV). | J8: Allowlist voor bestemmingen; blokkeer interne ranges en metadata-IP's. | K8: Egress-filtering en alarmering op interne calls vanuit app-servers. | L8: A01:2025 | N8: WSTG-INPV-19 | O8: V4 | P8: T1190 | Q8: CWE-918 | R8: Server Side Request Forgery | S8: Web attacks | T8: D8 | AB8: AV-API-07, AV-CLD-05, CVE-2021-26855, CVE-2026-64849 | AE8: 2026-10-09
A9: AV-WEB-08 | B9: Web application | C9: XML external entity (XXE) | D9: Injection | E9: Execution | F9: High | G9: Een XML-parser verwerkt externe entiteiten en laat bestands- of netwerktoegang toe. | H9: Uitlezen van lokale bestanden, SSRF en denial-of-service. | I9: Controleer of XML-parsers externe entiteiten en DTD's uitschakelen (WSTG-INPV). | J9: Schakel DTD/externe-entiteitverwerking uit in de parser. | K9: Alarmeer op uitgaande calls vanuit XML-verwerkende componenten. | L9: A05:2025 | N9: WSTG-INPV-07 | O9: V1 | P9: T1190 | Q9: CWE-611 | R9: XXE Injection | S9: Web attacks | T9: D8 | AB9: AV-WEB-31 | AE9: 2026-10-09
A10: AV-WEB-09 | B10: Web application | C10: Insecure deserialization | D10: Integrity | E10: Execution | F10: High | G10: Onvertrouwde geserialiseerde data wordt verwerkt zonder integriteitscontrole. | H10: Objectinjectie tot en met remote code execution. | I10: Identificeer deserialisatiepunten en controleer op integriteits-/typecontrole (WSTG-INPV). | J10: Vermijd native deserialisatie van onvertrouwde data; gebruik signed formaten. | K10: Monitor op deserialisatiefouten en onverwachte objecttypes. | L10: A08:2025 | N10: WSTG-INPV (geen specifieke test) | O10: V1 | P10: T1190 | Q10: CWE-502 | R10: Insecure Deserialization | S10: Web attacks | T10: D8 | AB10: CVE-2025-53770, CVE-2025-55182, CVE-2023-46604, CVE-2019-18935, CVE-2025-59287 | AE10: 2026-10-09
A11: AV-WEB-10 | B11: Web application | C11: Unrestricted file upload | D11: File handling | E11: Execution | F11: High | G11: Uploads worden onvoldoende gevalideerd op type, inhoud en opslaglocatie. | H11: Plaatsing van uitvoerbare bestanden; mogelijk code-uitvoering. | I11: Controleer server-side validatie van type/inhoud en of de opslag buiten webroot ligt (WSTG-BUSL/INPV). | J11: Valideer inhoud, hernoem bestanden, sla buiten webroot op, blokkeer uitvoering. | K11: Monitor uploadmappen op uitvoerbare bestanden. | L11: A05:2025 | N11: WSTG-BUSL-08, WSTG-BUSL-09 | O11: V5 | P11: T1190, T1505.003 | Q11: CWE-434 | R11: Upload Insecure Files | S11: Web attacks | T11: D8 | AB11: CVE-2025-31324, CVE-2020-14008, CVE-2021-21972 | AE11: 2026-10-09
A12: AV-WEB-11 | B12: Web application | C12: Path traversal / LFI / RFI | D12: Access control | E12: Discovery | F12: High | G12: Padmanipulatie geeft toegang tot bestanden buiten de bedoelde directory. | H12: Uitlezen van gevoelige bestanden; soms inclusie en uitvoering. | I12: Controleer of bestandspaden server-side worden genormaliseerd en beperkt (WSTG-ATHZ). | J12: Canonicaliseer paden, gebruik allowlists, mijd gebruikersinvoer in paden. | K12: Alarmeer op traversal-patronen in bestandsverzoeken. | L12: A01:2025 | N12: WSTG-ATHZ-01 | O12: V5 | P12: T1190, T1083 | Q12: CWE-22, CWE-98 | R12: Directory Traversal / File Inclusion | S12: Web attacks | T12: D8 | AB12: CVE-2021-41773, CVE-2021-43798, CVE-2018-13379, CVE-2019-19781 | AE12: 2026-10-09
A13: AV-WEB-12 | B13: Web application | C13: Authentication weaknesses | D13: Authentication | E13: Credential access | F13: High | G13: Zwakke inlogmechanismen laten brute force, credential stuffing of omzeiling toe. | H13: Accountovername en ongeautoriseerde toegang. | I13: Controleer lockout, rate-limiting, MFA en resetflows (WSTG-ATHN). | J13: Sterke MFA, rate-limiting, veilige resetflows, credential-screening. | K13: Alarmeer op login-anomalieen en spikes in mislukte logins. | L13: A07:2025 | M13: API2:2023 | N13: WSTG-ATHN-03, WSTG-ATHN-07, WSTG-ATHN-09 | O13: V6 | P13: T1110, T1078 | Q13: CWE-307, CWE-521 | R13: Account Takeover | S13: Web attacks | T13: D5 | AB13: AV-WEB-43, AV-WEB-44, AV-WEB-45, AV-WEB-46, AV-API-02 | AE13: 2026-10-09
A14: AV-WEB-13 | B14: Web application | C14: Session management flaws | D14: Session | E14: Credential access | F14: Medium | G14: Zwakke sessietokens, fixation of ontbrekende invalidatie ondermijnen sessieveiligheid. | H14: Sessiekaping en persistente ongeautoriseerde toegang. | I14: Controleer tokenentropie, rotatie bij login, en logout-/timeout-invalidatie (WSTG-SESS). | J14: Veilige cookie-attributen, rotatie na auth, correcte invalidatie. | K14: Detecteer gelijktijdig gebruik van sessies vanaf meerdere locaties. | L14: A07:2025 | N14: WSTG-SESS-01, WSTG-SESS-03, WSTG-SESS-06, WSTG-SESS-07 | O14: V7 | P14: T1539, T1550.004 | Q14: CWE-384, CWE-613 | R14: Session Management | S14: Web attacks | T14: D5 | AB14: AV-WEB-47, AV-WEB-53, CVE-2023-4966 | AE14: 2026-10-09
A15: AV-WEB-14 | B15: Web application | C15: JWT / token weaknesses | D15: Session / tokens | E15: Credential access | F15: High | G15: Onjuiste validatie van self-contained tokens (bv. alg-verwarring, zwakke sleutels). | H15: Vervalsing van identiteit en rechten. | I15: Controleer handtekeningvalidatie, algorithm-allowlist en claimverificatie (WSTG-SESS). | J15: Valideer handtekening en alg strikt; korte levensduur; sterke sleutels. | K15: Alarmeer op tokens met onverwachte alg of issuer. | L15: A07:2025 | N15: WSTG-SESS-10 | O15: V9 | P15: T1606 | Q15: CWE-347 | R15: JSON Web Token | S15: Web attacks | T15: D5 | AB15: AV-WEB-30, CVE-2026-5430 | AE15: 2026-10-09
A16: AV-WEB-15 | B16: Web application | C16: Cross-site request forgery (CSRF) | D16: Client-side | E16: Execution | F16: Medium | G16: Een geauthenticeerde gebruiker voert onbewust een statuswijzigend verzoek uit. | H16: Ongewenste acties namens het slachtoffer. | I16: Controleer anti-CSRF-tokens en SameSite-cookiebeleid op statuswijzigende endpoints (WSTG-SESS). | J16: Anti-CSRF-tokens, SameSite-cookies, herauthenticatie voor gevoelige acties. | K16: Detecteer statuswijzigingen zonder verwachte token/oorsprong. | L16: A01:2025 | N16: WSTG-SESS-05 | O16: V3 | Q16: CWE-352 | R16: CSRF Injection | S16: Web attacks | T16: D8 | AB16: AV-WEB-33, AV-WEB-47 | AE16: 2026-10-09
A17: AV-WEB-16 | B17: Web application | C17: Server-side template injection (SSTI) | D17: Injection | E17: Execution | F17: High | G17: Invoer wordt door een template-engine geevalueerd in plaats van als data behandeld. | H17: Template-evaluatie tot en met code-uitvoering. | I17: Controleer of gebruikersinvoer buiten de template-context blijft (WSTG-INPV). | J17: Behandel invoer als data; gebruik logic-less templates; sandbox. | K17: Monitor template-fouten en onverwachte evaluaties. | L17: A05:2025 | N17: WSTG-INPV-18 | O17: V1 | P17: T1190 | Q17: CWE-1336 | R17: Server Side Template Injection | S17: Web attacks | T17: D8 | AB17: AV-WEB-39, CVE-2023-22527, CVE-2026-75650 | AE17: 2026-10-09
A18: AV-WEB-17 | B18: Web application | C18: Open redirect | D18: Input validation | E18: Initial access | F18: Low | G18: Ongevalideerde redirect-parameters sturen gebruikers naar externe bestemmingen. | H18: Phishing en omzeiling van oorsprongvertrouwen. | I18: Controleer of redirect-doelen tegen een allowlist worden gevalideerd (WSTG-CLNT). | J18: Allowlist van redirect-doelen; vermijd gebruikersgestuurde URL's. | K18: Log redirects naar externe domeinen. | L18: A01:2025 | N18: WSTG-CLNT-04 | O18: V2 | P18: T1566.002 | Q18: CWE-601 | R18: Open Redirect | S18: Web attacks | T18: D8 | AB18: AV-WEB-30 | AE18: 2026-10-09
A19: AV-WEB-18 | B19: Web application | C19: Security misconfiguration | D19: Configuration | E19: Reconnaissance | F19: Medium | G19: Default-instellingen, onnodige features of blootgestelde beheerinterfaces. | H19: Uiteenlopend, van informatielekkage tot directe compromittering. | I19: Controleer hardening, default-credentials en blootgestelde interfaces (WSTG-CONF). | J19: Hardening-baselines, verwijder defaults, minimaliseer features. | K19: Config-drift-detectie en periodieke hardening-scans. | L19: A02:2025 | N19: WSTG-CONF-02, WSTG-CONF-05 | O19: V13 | P19: T1592 | Q19: CWE-16, CWE-1188 | R19: Methodology and Resources | S19: Enumeration | T19: D3 | AB19: AV-WEB-48, AV-WEB-49, AV-EXT-07 | AE19: 2026-10-09
A20: AV-WEB-19 | B20: Web application | C20: Missing security headers | D20: Configuration | E20: Reconnaissance | F20: Low | G20: Ontbrekende headers (CSP, HSTS, X-Frame-Options) verzwakken browserverdediging. | H20: Grotere kans op XSS, clickjacking en downgrade. | I20: Controleer aanwezigheid en correctheid van beveiligingsheaders (WSTG-CONF). | J20: Stel CSP, HSTS, X-Content-Type-Options en frame-ancestors in. | K20: Periodieke header-scans in CI. | L20: A02:2025 | N20: WSTG-CONF-07, WSTG-CONF-12 | O20: V3 | Q20: CWE-693 | R20: Methodology and Resources | S20: Enumeration | T20: D3 | AB20: AV-WEB-27, AV-WEB-47 | AE20: 2026-10-09
A21: AV-WEB-20 | B21: Web application | C21: Cryptographic failures / weak TLS | D21: Cryptography | E21: Credential access | F21: Medium | G21: Zwakke algoritmes, verouderde TLS of slecht sleutelbeheer. | H21: Blootstelling of manipulatie van gevoelige data in transit of at rest. | I21: Controleer TLS-config, algoritmekeuze en sleutelbeheer (WSTG-CRYP). | J21: Moderne TLS, sterke suites, correct sleutelbeheer en crypto-agility. | K21: Monitor op verouderde protocolversies en cipher-downgrades. | L21: A04:2025 | N21: WSTG-CRYP-01, WSTG-CRYP-04 | O21: V11, V12 | P21: T1557, T1040 | Q21: CWE-327 | R21: Methodology and Resources | S21: Enumeration | T21: D3 | AB21: AV-NET-18, CVE-2014-0160 | AE21: 2026-10-09
A22: AV-WEB-21 | B22: Web application | C22: Sensitive data exposure | D22: Data protection | E22: Collection | F22: Medium | G22: Gevoelige gegevens worden onvoldoende beschermd of onnodig blootgesteld. | H22: Datalek en privacyschending. | I22: Controleer dataclassificatie, versleuteling en minimalisatie in responses (WSTG-ATHZ/CONF). | J22: Classificeer data, versleutel at rest/in transit, minimaliseer velden. | K22: DLP en monitoring op ongebruikelijke data-egress. | L22: A04:2025 | N22: WSTG-CRYP-03, WSTG-INFO-05 | O22: V14 | P22: T1005, T1213 | Q22: CWE-200 | R22: Methodology and Resources | S22: Enumeration | T22: D2 | AB22: AV-WEB-48, AV-WEB-53 | AE22: 2026-10-09
A23: AV-WEB-22 | B23: Web application | C23: Business logic flaws | D23: Business logic | E23: Execution | F23: Medium | G23: Legitieme functionaliteit wordt op onbedoelde wijze misbruikt (bv. workflow-bypass, race conditions). | H23: Fraude, omzeiling van limieten en integriteitsschade. | I23: Modelleer bedoelde workflows en toets afwijkende volgordes en gelijktijdigheid (WSTG-BUSL). | J23: Server-side afdwinging van workflow, atomaire operaties, limieten. | K23: Alarmeer op onmogelijke of te snelle workflow-transities. | L23: A06:2025 | N23: WSTG-BUSL-01, WSTG-BUSL-06 | O23: V2 | Q23: CWE-840 | R23: Methodology and Resources | S23: Web attacks | T23: D8 | AB23: AV-WEB-34, AV-API-06 | AE23: 2026-10-09
A24: AV-WEB-23 | B24: Web application | C24: Vulnerable & outdated components | D24: Supply chain | E24: Initial access | F24: High | G24: Verouderde libraries of frameworks met bekende kwetsbaarheden. | H24: Exploitatie van bekende CVE's in afhankelijkheden. | I24: Inventariseer afhankelijkheden en vergelijk versies met bekende adviezen (WSTG-CONF). | J24: SBOM, dependency-scanning, tijdig patchen. | K24: Continu SCA en versiemonitoring in de pipeline. | L24: A03:2025 | N24: WSTG-INFO-02, WSTG-INFO-08 | O24: V15 | P24: T1190 | Q24: CWE-1104 | R24: Methodology and Resources | S24: Enumeration | T24: D8 | AB24: CVE-2021-44228, CVE-2022-22965, CVE-2017-5638, AV-CLD-19, AV-NET-21 | AE24: 2026-10-09
A25: AV-WEB-24 | B25: Web application | C25: Improper error handling | D25: Error handling | E25: Reconnaissance | F25: Low | G25: Verbose fouten lekken details of de applicatie faalt open in plaats van dicht. | H25: Informatielekkage en omzeiling van controles bij uitzonderingen. | I25: Forceer foutcondities en beoordeel lekkage en fail-open-gedrag (WSTG-ERRH). | J25: Generieke foutpagina's, fail-closed-ontwerp, gestructureerde logging. | K25: Monitor op stacktraces in responses. | L25: A10:2025 | N25: WSTG-ERRH-01, WSTG-ERRH-02 | O25: V16 | Q25: CWE-209 | R25: Methodology and Resources | S25: Web attacks | T25: D8 | AB25: AV-WEB-48 | AE25: 2026-10-09
A26: AV-WEB-25 | B26: Web application | C26: HTTP request smuggling / desync | D26: Injection | E26: Execution | F26: High | G26: Front-end (proxy/load balancer) en back-end interpreteren Content-Length/Transfer-Encoding (of HTTP/2-downgrade) verschillend, waardoor een aanvaller een tweede verzoek in de verbinding kan smokkelen. | H26: Omzeiling van front-end security controls, kaping van verzoeken van andere gebruikers, cache poisoning en soms accountovername. | I26: Toets CL.TE-, TE.CL- en H2.CL-desync met timing-based probes op de front-end; bevestig alleen met niet-destructieve payloads en per RoE (WSTG-INPV-15). | J26: Gebruik end-to-end HTTP/2 of normaliseer ambigue verzoeken op de front-end; weiger verzoeken met zowel CL als TE; sluit back-endverbindingen na elke request; patch proxy/webserver. | K26: Alarmeer op 400/timeout-pieken en op verzoeken met conflicterende CL/TE-headers op de edge. | L26: A06:2025 | N26: WSTG-INPV-15 | O26: V4, V13 | P26: T1190 | Q26: CWE-444 | R26: Request Smuggling | S26: Web attacks | T26: D8 | AD26: https://portswigger.net/web-security/request-smuggling | AE26: 2026-10-09
A27: AV-WEB-26 | B27: Web application | C27: CORS misconfiguration | D27: Configuration | E27: Collection | F27: Medium | G27: Access-Control-Allow-Origin reflecteert willekeurige of null-origins (vaak gecombineerd met Allow-Credentials: true), waardoor een kwaadaardige site geauthenticeerde responses kan uitlezen. | H27: Cross-origin diefstal van gevoelige data en CSRF-achtige acties namens het slachtoffer. | I27: Stuur verzoeken met afwijkende Origin-headers (willekeurig, null, subdomein-varianten) en controleer ACAO/ACAC in de respons (WSTG-CLNT-07). | J27: Strikte allowlist van origins; nooit reflectie van de Origin-header met credentials; geen wildcard op geauthenticeerde endpoints. | K27: Log en review Origin-headers op geauthenticeerde endpoints; periodieke header-scan in CI. | L27: A01:2025 | M27: API8:2023 | N27: WSTG-CLNT-07 | O27: V3 | Q27: CWE-942 | R27: CORS Misconfiguration | S27: Web attacks | T27: D8 | AD27: https://portswigger.net/web-security/cors | AE27: 2026-10-09
A28: AV-WEB-27 | B28: Web application | C28: Clickjacking / UI redressing | D28: Client-side | E28: Execution | F28: Low | G28: Pagina's met statuswijzigende functionaliteit kunnen in een (onzichtbaar) frame van een aanvallersdomein worden geladen door ontbrekende frame-ancestors/X-Frame-Options. | H28: Gebruiker voert onbedoeld acties uit (bv. instellingen wijzigen, transacties bevestigen). | I28: Controleer CSP frame-ancestors en X-Frame-Options op gevoelige pagina's en maak een framing-PoC (WSTG-CLNT-09). | J28: Content-Security-Policy: frame-ancestors 'none' of een allowlist; X-Frame-Options als fallback; herauthenticatie voor gevoelige acties. | K28: Header-scan in CI; CSP-violation-rapportage. | L28: A02:2025 | N28: WSTG-CLNT-09 | O28: V3 | Q28: CWE-1021 | R28: Clickjacking | S28: Web attacks | T28: D8 | AB28: AV-WEB-19 | AD28: https://cheatsheetseries.owasp.org/cheatsheets/Clickjacking_Defense_Cheat_Sheet.html | AE28: 2026-10-09
A29: AV-WEB-28 | B29: Web application | C29: Subdomain takeover (dangling DNS) | D29: Configuration | E29: Initial access | F29: Medium | G29: Een CNAME/A-record verwijst naar een niet-meer-geclaimde externe dienst (cloud storage, SaaS, CDN), waardoor een aanvaller de bestemming kan claimen en content onder het vertrouwde domein kan serveren. | H29: Phishing onder het eigen domein, cookie-diefstal voor parent-domain cookies, omzeiling van CSP/CORS-vertrouwen. | I29: Enumereer subdomeinen en controleer DNS-records op verwijzingen naar niet-geclaimde diensten (fingerprints per provider) (WSTG-CONF-10). | J29: Verwijder verweesde DNS-records bij decommissioning; inventariseer DNS periodiek; claim resources voordat DNS wordt aangemaakt. | K29: Periodieke DNS-inventaris en monitoring op CNAME's naar externe diensten zonder actieve resource. | L29: A02:2025 | N29: WSTG-CONF-10 | O29: V13 | P29: T1584.001 | Q29: CWE-284 | R29: Methodology and Resources - Subdomains Enumeration | S29: Enumeration | T29: D4 | AB29: AV-EXT-04 | AD29: https://github.com/EdOverflow/can-i-take-over-xyz | AE29: 2026-10-09
A30: AV-WEB-29 | B30: Web application | C30: Host header injection / password reset poisoning | D30: Injection | E30: Credential access | F30: Medium | G30: De applicatie gebruikt de Host- of X-Forwarded-Host-header om absolute URL's te bouwen (bv. in wachtwoordresetmails), waardoor een aanvaller links naar een eigen domein kan injecteren. | H30: Diefstal van reset-tokens en accountovername; cache poisoning en SSRF-achtige routing. | I30: Manipuleer Host/X-Forwarded-Host en controleer of gegenereerde links, redirects of cache-keys de waarde overnemen (WSTG-INPV-17). | J30: Gebruik een geconfigureerde canonieke hostname; valideer Host tegen een allowlist; negeer X-Forwarded-Host tenzij van een vertrouwde proxy. | K30: Alarmeer op verzoeken met onbekende Host-waarden op de edge. | L30: A05:2025 | N30: WSTG-INPV-17 | O30: V2, V4 | P30: T1566.002 | Q30: CWE-644, CWE-20 | R30: Methodology and Resources | S30: Web attacks | T30: D8 | AB30: AV-WEB-45 | AD30: https://portswigger.net/web-security/host-header | AE30: 2026-10-09
A31: AV-WEB-30 | B31: Web application | C31: OAuth 2.0 / OIDC misconfiguration | D31: Authentication | E31: Credential access | F31: High | G31: Zwakke redirect_uri-validatie, ontbrekende state/PKCE, implicit flow of te ruime scopes maken diefstal van authorization codes of access tokens mogelijk. | H31: Accountovername via tokendiefstal of login-CSRF; toegang tot API's namens het slachtoffer. | I31: Toets redirect_uri-varianten (pad/subdomein/open redirect), ontbreken van state/nonce/PKCE, token-leakage via Referer en scope-escalatie (WSTG-ATHZ-05). | J31: Exacte redirect_uri-matching, authorization code flow met PKCE, state/nonce verplicht, korte tokenlevensduur, scope-minimalisatie. | K31: Alarmeer op authorization-verzoeken met afwijkende redirect_uri of ongebruikelijke client/scopes. | L31: A07:2025 | M31: API2:2023 | N31: WSTG-ATHZ-05 | O31: V10 | P31: T1528, T1550.001 | Q31: CWE-601, CWE-287 | R31: OAuth Misconfiguration | S31: Web attacks | T31: D5 | AB31: AV-WEB-17, AV-CLD-10 | AD31: https://portswigger.net/web-security/oauth | AE31: 2026-10-09
A32: AV-WEB-31 | B32: Web application | C32: SAML / SSO implementation flaws | D32: Authentication | E32: Credential access | F32: High | G32: Onjuiste validatie van SAML-responses (signature wrapping, ontbrekende/zwakke signature-check, XXE in assertions, ontbrekende audience/recipient-check) laat identiteitsvervalsing toe. | H32: Impersonatie van willekeurige gebruikers inclusief beheerders bij de service provider. | I32: Manipuleer SAML-responses (verwijder/vervang signature, XSW, attribuutwijziging, replay) en controleer of de SP de assertion afwijst. | J32: Gebruik een onderhouden SAML-library, valideer signature op de assertion en response, controleer audience/recipient/NotOnOrAfter, schakel DTD-verwerking uit. | K32: Alarmeer op SAML-responses met signature-fouten of afwijkende issuer/audience. | L32: A07:2025 | N32: WSTG-ATHN-04 | O32: V6, V9 | P32: T1606.002 | Q32: CWE-347, CWE-287 | R32: SAML Injection | S32: Web attacks | T32: D5 | AB32: CVE-2022-47966 | AD32: https://cheatsheetseries.owasp.org/cheatsheets/SAML_Security_Cheat_Sheet.html | AE32: 2026-10-09
A33: AV-WEB-32 | B33: Web application | C33: GraphQL-specific weaknesses | D33: Configuration | E33: Discovery | F33: Medium | G33: Introspection in productie, ontbrekende autorisatie per resolver, batching/aliasing zonder limieten en diepe queries maken informatielekkage, brute force en DoS mogelijk. | H33: Blootstelling van schema en data, omzeiling van rate limiting, resource-uitputting. | I33: Controleer introspection, per-field autorisatie, query depth/complexity-limieten en batching-misbruik (WSTG-APIT-01). | J33: Introspection uit in productie, autorisatie in de resolver-laag, depth/complexity/cost-limieten, limiteer batching en aliasing. | K33: Monitor op introspection-queries en ongebruikelijk complexe/grote queries. | L33: A01:2025 | M33: API4:2023, API8:2023 | N33: WSTG-APIT-01 | O33: V4 | Q33: CWE-200, CWE-770 | R33: GraphQL Injection | S33: Web attacks | T33: D8 | AB33: AV-API-04 | AD33: https://cheatsheetseries.owasp.org/cheatsheets/GraphQL_Cheat_Sheet.html | AE33: 2026-10-09
A34: AV-WEB-33 | B34: Web application | C34: WebSocket weaknesses (CSWSH, missing auth) | D34: Session | E34: Execution | F34: Medium | G34: WebSocket-handshakes zonder Origin-validatie of zonder (her)authenticatie laten cross-site WebSocket hijacking en ongeautoriseerde berichten toe; berichten worden vaak niet gevalideerd. | H34: Lezen en versturen van berichten namens het slachtoffer; injectie via onbeschermde berichtverwerking. | I34: Test de handshake met een vreemde Origin en zonder sessiecookie; fuzz berichtinhoud op injectie (WSTG-CLNT-10). | J34: Valideer Origin, gebruik tokens in de handshake, pas dezelfde autorisatie en inputvalidatie toe als op HTTP-endpoints, gebruik wss://. | K34: Log handshakes met onbekende Origin; monitor berichtvolume per sessie. | L34: A01:2025 | N34: WSTG-CLNT-10 | O34: V3, V4 | Q34: CWE-1385, CWE-346 | R34: Web Sockets | S34: Web attacks | T34: D8 | AB34: AV-WEB-15 | AD34: https://portswigger.net/web-security/websockets | AE34: 2026-10-09
A35: AV-WEB-34 | B35: Web application | C35: Race conditions / TOCTOU | D35: Business logic | E35: Execution | F35: Medium | G35: Gelijktijdige verzoeken op niet-atomaire operaties (vouchers, saldo, limieten, OTP-pogingen, registratie) laten limieten overschrijden of controles omzeilen. | H35: Financiele fraude, dubbele uitbetaling, omzeiling van rate limits en eenmalige acties. | I35: Verstuur parallelle verzoeken (single-packet/last-byte-sync) op limit-gebonden functies en vergelijk de eindtoestand met de verwachte limiet (WSTG-BUSL-05). | J35: Atomaire database-operaties/locks, idempotency keys, server-side state-machine, unieke constraints. | K35: Alarmeer op meerdere geslaagde transacties binnen milliseconden voor dezelfde entiteit. | L35: A06:2025 | M35: API6:2023 | N35: WSTG-BUSL-05 | O35: V2 | Q35: CWE-362, CWE-367 | R35: Race Condition | S35: Web attacks | T35: D8 | AB35: AV-WEB-22 | AD35: https://portswigger.net/web-security/race-conditions | AE35: 2026-10-09
A36: AV-WEB-35 | B36: Web application | C36: Web cache poisoning / cache deception | D36: Configuration | E36: Execution | F36: Medium | G36: Unkeyed input (headers, parameters, path-normalisatie) beinvloedt gecachte responses, of gevoelige persoonlijke responses worden onder een statisch ogend pad gecached. | H36: Verspreiding van XSS/redirects naar alle bezoekers, of blootstelling van persoonlijke data via de cache. | I36: Identificeer cache-gedrag (headers, keys) en toets unkeyed inputs en path-confusion (/account/x.css) op cachebaarheid. | J36: Cache alleen expliciet statische content, normaliseer pad/parameters consistent op CDN en origin, zet Cache-Control: no-store op persoonlijke responses. | K36: Monitor cache-hit-ratio's en afwijkende cache-keys; alarmeer op gecachte responses met Set-Cookie. | L36: A06:2025 | N36: WSTG-CONF-13 | O36: V3, V13 | Q36: CWE-444, CWE-524 | R36: Web Cache Deception | S36: Web attacks | T36: D8 | AB36: AV-WEB-25 | AD36: https://portswigger.net/web-security/web-cache-poisoning | AE36: 2026-10-09
A37: AV-WEB-36 | B37: Web application | C37: NoSQL injection | D37: Injection | E37: Execution | F37: High | G37: Invoer wordt ongefilterd in NoSQL-queries (MongoDB-operators zoals $ne/$regex/$where, JSON-objecten) opgenomen. | H37: Authenticatie-omzeiling, uitlezen van collecties, soms server-side JavaScript-uitvoering. | I37: Injecteer operator-objecten en JSON-typeverandering in parameters/bodies en observeer gedragsafwijkingen (WSTG-INPV-05). | J37: Strikte schema-/typevalidatie, verbied operator-keys in invoer, gebruik parameterized query-builders, schakel server-side JS uit. | K37: Alarmeer op query-operators in request-bodies en op afwijkende query-patronen in de database. | L37: A05:2025 | N37: WSTG-INPV-05 | O37: V1 | P37: T1190 | Q37: CWE-943 | R37: NoSQL Injection | S37: Web attacks | T37: D8 | AB37: AV-WEB-03 | AD37: https://cheatsheetseries.owasp.org/cheatsheets/Injection_Prevention_Cheat_Sheet.html | AE37: 2026-10-09
A38: AV-WEB-37 | B38: Web application | C38: LDAP / XPath injection | D38: Injection | E38: Execution | F38: High | G38: Invoer wordt zonder escaping in LDAP-filters of XPath-expressies opgenomen (bv. loginformulieren tegen AD of XML-datastores). | H38: Authenticatie-omzeiling, enumeratie van directory-objecten en uitlezen van XML-data. | I38: Injecteer filter-metatekens (*, (, ), |, &) en XPath-booleans en controleer op afwijkende resultaten (WSTG-INPV-06, WSTG-INPV-09). | J38: Escape per context met een library, gebruik allowlists voor invoer, bind met least-privilege service-accounts. | K38: Alarmeer op LDAP-queries met ongebruikelijke filters vanuit de applicatie. | L38: A05:2025 | N38: WSTG-INPV-06, WSTG-INPV-09 | O38: V1 | P38: T1190 | Q38: CWE-90, CWE-643 | R38: LDAP Injection | S38: Web attacks | T38: D8 | AD38: https://cheatsheetseries.owasp.org/cheatsheets/LDAP_Injection_Prevention_Cheat_Sheet.html | AE38: 2026-10-09
A39: AV-WEB-38 | B39: Web application | C39: CRLF / HTTP header / e-mail header injection | D39: Injection | E39: Execution | F39: Medium | G39: Regeleinden in invoer worden niet gefilterd bij het opbouwen van HTTP-headers, logregels of e-mailheaders (SMTP). | H39: Response splitting, cookie-injectie, log-vervuiling, spam/phishing via de eigen mailserver. | I39: Injecteer %0d%0a in parameters die in headers, redirects of mailvelden belanden en controleer de uitvoer (WSTG-INPV-15, WSTG-INPV-10). | J39: Strip of encodeer CR/LF, gebruik framework-API's voor headers en mail, valideer e-mailvelden strikt. | K39: Monitor op onverwachte extra headers of afwijkende mailvolumes vanaf de applicatie. | L39: A05:2025 | N39: WSTG-INPV-15, WSTG-INPV-10 | O39: V1 | Q39: CWE-113, CWE-93 | R39: CRLF Injection | S39: Web attacks | T39: D8 | AD39: https://owasp.org/www-community/vulnerabilities/CRLF_Injection | AE39: 2026-10-09
A40: AV-WEB-39 | B40: Web application | C40: Code injection (eval) / expression language injection | D40: Injection | E40: Execution | F40: Critical | G40: Invoer wordt door een interpreter of expression language geevalueerd (eval(), OGNL, SpEL, EL, Jinja-expressies buiten templates). | H40: Directe code-uitvoering op de server; volledige compromittering. | I40: Injecteer rekenkundige en taalspecifieke expressies in verdachte parameters en controleer of ze worden geevalueerd (WSTG-INPV-11). | J40: Vermijd dynamische evaluatie van invoer; gebruik veilige parsers; sandbox en least privilege. | K40: Monitor op onverwachte child-processen en op expressie-syntax in requests. | L40: A05:2025 | N40: WSTG-INPV-11 | O40: V1 | P40: T1190, T1059 | Q40: CWE-94, CWE-917 | R40: Methodology and Resources | S40: Web attacks | T40: D8 | AB40: AV-WEB-16, CVE-2022-26134, CVE-2017-5638 | AD40: https://owasp.org/www-community/attacks/Code_Injection | AE40: 2026-10-09
A41: AV-WEB-40 | B41: Web application | C41: Prototype pollution | D41: Injection | E41: Execution | F41: Medium | G41: Onveilige merge/clone van gebruikersinvoer in JavaScript (client- of server-side) laat __proto__/constructor-properties zetten die alle objecten beinvloeden. | H41: Client-side XSS via gadgets, server-side logica-omzeiling tot en met RCE in Node.js. | I41: Injecteer __proto__[x]=y via query/JSON en controleer of properties op lege objecten verschijnen; zoek naar gadgets (WSTG-CLNT-01). | J41: Gebruik Object.create(null)/Map, freeze prototypes, valideer keys, update kwetsbare libraries. | K41: SCA op bekende kwetsbare libraries; alarmeer op __proto__/constructor in request-bodies. | L41: A05:2025 | N41: WSTG-CLNT-01 | O41: V1, V15 | Q41: CWE-1321 | R41: Prototype Pollution | S41: Web attacks | T41: D8 | AB41: AV-WEB-23 | AD41: https://portswigger.net/web-security/prototype-pollution | AE41: 2026-10-09
A42: AV-WEB-41 | B42: Web application | C42: DOM-based XSS | D42: Injection / client-side | E42: Execution | F42: Medium | G42: Client-side JavaScript schrijft onvertrouwde bronnen (location, postMessage, storage) via gevaarlijke sinks (innerHTML, eval, document.write) naar de DOM. | H42: Scriptuitvoering in de browser van het slachtoffer zonder server-side reflectie; vaak onzichtbaar voor WAF. | I42: Analyseer sources en sinks in de client-side code (DOM Invader/handmatig) en bevestig met een PoC-payload (WSTG-CLNT-01). | J42: Gebruik veilige DOM-API's (textContent), sanitize met DOMPurify, Trusted Types en een strikte CSP. | K42: CSP-violation-rapportage; client-side telemetry op fouten. | L42: A05:2025 | N42: WSTG-CLNT-01 | O42: V1, V3 | P42: T1059.007 | Q42: CWE-79 | R42: XSS Injection | S42: Web attacks | T42: D8 | AB42: AV-WEB-05, AV-WEB-06 | AD42: https://cheatsheetseries.owasp.org/cheatsheets/DOM_based_XSS_Prevention_Cheat_Sheet.html | AE42: 2026-10-09
A43: AV-WEB-42 | B43: Web application | C43: HTML injection / content spoofing | D43: Injection / client-side | E43: Execution | F43: Low | G43: Invoer wordt als HTML gerenderd zonder scriptuitvoering mogelijk te maken (bv. door CSP of filtering), maar laat wel vervalste content, formulieren en links toe. | H43: Phishing binnen de vertrouwde site, defacement, diefstal van invoer via geinjecteerde formulieren. | I43: Injecteer onschuldige HTML-elementen (h1, a, form) en controleer de rendering (WSTG-CLNT-03). | J43: Context-correcte output-encoding; sanitize HTML met een allowlist wanneer rich text nodig is. | K43: Content-integriteitsmonitoring op gebruikersgegenereerde pagina's. | L43: A05:2025 | N43: WSTG-CLNT-03 | O43: V1 | Q43: CWE-80 | R43: XSS Injection | S43: Web attacks | T43: D8 | AB43: AV-WEB-05 | AD43: https://owasp.org/www-project-web-security-testing-guide/latest/4-Web_Application_Security_Testing/11-Client-side_Testing/03-Testing_for_HTML_Injection | AE43: 2026-10-09
A44: AV-WEB-43 | B44: Web application | C44: Username / account enumeration | D44: Authentication | E44: Reconnaissance | F44: Low | G44: Login-, registratie- of resetfuncties reageren verschillend (bericht, statuscode, timing) voor bestaande en niet-bestaande accounts. | H44: Opbouw van geldige gebruikerslijsten voor password spraying en phishing. | I44: Vergelijk responses en responstijden voor bekende en onbekende gebruikersnamen op alle auth-gerelateerde endpoints (WSTG-IDNT-04). | J44: Generieke foutmeldingen, constante responstijden, rate limiting en CAPTCHA op enumeratiegevoelige functies. | K44: Alarmeer op veel verschillende gebruikersnamen vanaf een bron binnen korte tijd. | L44: A07:2025 | M44: API2:2023 | N44: WSTG-IDNT-04 | O44: V6 | P44: T1589.002, T1087 | Q44: CWE-204, CWE-203 | R44: Account Takeover | S44: Enumeration | T44: D5 | AB44: AV-NET-06, AV-WEB-12 | AD44: https://owasp.org/www-project-web-security-testing-guide/latest/4-Web_Application_Security_Testing/03-Identity_Management_Testing/04-Testing_for_Account_Enumeration_and_Guessable_User_Account | AE44: 2026-10-09
A45: AV-WEB-44 | B45: Web application | C45: Weak password policy | D45: Authentication | E45: Credential access | F45: Medium | G45: Korte of simpele wachtwoorden worden geaccepteerd, geen screening tegen gelekte wachtwoorden, geen beperking op hergebruik. | H45: Succesvolle brute force, spraying en credential stuffing. | I45: Probeer zwakke wachtwoorden bij registratie/wijziging en controleer lengte-, complexiteits- en breach-checks (WSTG-ATHN-07). | J45: Minimaal 12-14 tekens, screening tegen breach-lijsten (NIST SP 800-63B), geen geforceerde periodieke rotatie zonder aanleiding, MFA. | K45: Periodieke audit van wachtwoordhashes (offline, met toestemming) en monitoring van spraying. | L45: A07:2025 | N45: WSTG-ATHN-07 | O45: V6 | P45: T1110 | Q45: CWE-521 | R45: Account Takeover | S45: Password attacks | T45: D5 | AB45: AV-AD-19, AV-WEB-12 | AC45: NIST SP 800-63B | AD45: https://cheatsheetseries.owasp.org/cheatsheets/Authentication_Cheat_Sheet.html | AE45: 2026-10-09
A46: AV-WEB-45 | B46: Web application | C46: Insecure password reset / recovery flow | D46: Authentication | E46: Credential access | F46: High | G46: Reset-tokens zijn voorspelbaar, niet gebonden aan de gebruiker, niet verlopend, lekken via Referer/Host-header of worden niet geinvalideerd na gebruik; beveiligingsvragen zijn raadbaar. | H46: Accountovername zonder kennis van het huidige wachtwoord. | I46: Analyseer token-entropie en -levensduur, hergebruik, binding aan account, Host-header-poisoning en logica van de flow (WSTG-ATHN-09). | J46: Cryptografisch willekeurige, kortlevende eenmalige tokens gebonden aan het account; invalidatie na gebruik; notificatie; geen beveiligingsvragen. | K46: Alarmeer op veel resetaanvragen per account of bron. | L46: A07:2025 | N46: WSTG-ATHN-09 | O46: V6 | P46: T1098 | Q46: CWE-640 | R46: Account Takeover | S46: Web attacks | T46: D5 | AB46: AV-WEB-29, CVE-2023-7028 | AD46: https://cheatsheetseries.owasp.org/cheatsheets/Forgot_Password_Cheat_Sheet.html | AE46: 2026-10-09
A47: AV-WEB-46 | B47: Web application | C47: MFA bypass / weak MFA implementation | D47: Authentication | E47: Credential access | F47: High | G47: OTP-codes zijn te raden (geen rate limiting), de MFA-stap kan worden overgeslagen (direct naar post-auth endpoints), response-manipulatie keurt goed, of MFA ontbreekt op alternatieve kanalen (API, legacy). | H47: Omzeiling van de tweede factor en accountovername met alleen een wachtwoord. | I47: Toets brute force op OTP, stap-overslaan, response-tampering, herbruikbare codes en MFA-dekking van alle inlogkanalen (WSTG-ATHN-11). | J47: Server-side state-machine voor de auth-flow, rate limiting en lockout op OTP, eenmalige codes, MFA op alle kanalen, phishing-resistente MFA (FIDO2) waar mogelijk. | K47: Alarmeer op veel OTP-pogingen en op sessies die de MFA-stap niet doorlopen. | L47: A07:2025 | M47: API2:2023 | N47: WSTG-ATHN-11 | O47: V6 | P47: T1621, T1111 | Q47: CWE-287, CWE-307 | R47: Account Takeover | S47: Web attacks | T47: D5 | AB47: AV-SE-06, AV-SE-07, AV-CLD-09 | AD47: https://cheatsheetseries.owasp.org/cheatsheets/Multifactor_Authentication_Cheat_Sheet.html | AE47: 2026-10-09
A48: AV-WEB-47 | B48: Web application | C48: Insecure cookie attributes | D48: Session | E48: Credential access | F48: Low | G48: Sessiecookies missen Secure, HttpOnly of SameSite, hebben een te ruim Domain/Path of een te lange levensduur. | H48: Grotere impact van XSS en netwerkonderschepping; CSRF-risico; sessiediefstal. | I48: Inspecteer Set-Cookie-headers van alle sessie- en auth-cookies op attributen en scope (WSTG-SESS-02). | J48: Secure; HttpOnly; SameSite=Lax/Strict; __Host-prefix; minimale levensduur en scope. | K48: Header-scan in CI. | L48: A02:2025 | N48: WSTG-SESS-02 | O48: V7 | P48: T1539 | Q48: CWE-1004, CWE-614, CWE-1275 | R48: Session Management | S48: Web attacks | T48: D5 | AB48: AV-WEB-13 | AD48: https://cheatsheetseries.owasp.org/cheatsheets/Session_Management_Cheat_Sheet.html | AE48: 2026-10-09
A49: AV-WEB-48 | B49: Web application | C49: Information disclosure (source maps, backups, .git, directory listing, banners) | D49: Configuration | E49: Reconnaissance | F49: Low | G49: Blootgestelde .git/.svn-mappen, backup- en configbestanden, source maps, directory listing, Swagger/actuator-endpoints en gedetailleerde versiebanners lekken implementatiedetails of secrets. | H49: Versnelde exploitatie, lekkage van credentials/API-keys, broncode-analyse door aanvallers. | I49: Fuzz op bekende paden (.git/HEAD, .env, *.bak, /actuator, /swagger), controleer listing en banners (WSTG-INFO-02, WSTG-CONF-04, WSTG-CONF-05). | J49: Verwijder/blokkeer ontwikkelartefacten en backups uit de webroot, schakel listing uit, minimaliseer banners, bescherm management-endpoints. | K49: Alarmeer op verzoeken naar .git/.env/backup-patronen; periodieke content-discovery-scan. | L49: A02:2025 | M49: API9:2023 | N49: WSTG-INFO-02, WSTG-CONF-04, WSTG-CONF-05 | O49: V13, V14 | P49: T1592, T1552.001 | Q49: CWE-538, CWE-548, CWE-200 | R49: Insecure Source Code Management | S49: Enumeration | T49: D8 | AB49: AV-WEB-18, AV-WEB-24 | AD49: https://owasp.org/www-project-web-security-testing-guide/latest/4-Web_Application_Security_Testing/02-Configuration_and_Deployment_Management_Testing/04-Review_Old_Backup_and_Unreferenced_Files_for_Sensitive_Information | AE49: 2026-10-09
A50: AV-WEB-49 | B50: Web application | C50: Dangerous HTTP methods / verb tampering | D50: Configuration | E50: Execution | F50: Medium | G50: PUT/DELETE/TRACE/WebDAV zijn ingeschakeld of autorisatie wordt alleen op specifieke methods afgedwongen, waardoor een andere method de controle omzeilt. | H50: Uploaden/verwijderen van bestanden, omzeiling van autorisatie, cross-site tracing. | I50: Enumereer toegestane methods (OPTIONS) en herhaal geautoriseerde verzoeken met alternatieve methods/overrides (WSTG-CONF-06, WSTG-INPV-03). | J50: Beperk methods tot wat nodig is, dwing autorisatie method-onafhankelijk af, schakel TRACE/WebDAV uit, blokkeer X-HTTP-Method-Override. | K50: Alarmeer op ongebruikelijke methods naar applicatie-endpoints. | L50: A02:2025 | N50: WSTG-CONF-06, WSTG-INPV-03 | O50: V13 | P50: T1190 | Q50: CWE-650, CWE-749 | R50: Methodology and Resources | S50: Web attacks | T50: D8 | AB50: AV-WEB-02, CVE-2025-24813 | AD50: https://owasp.org/www-project-web-security-testing-guide/latest/4-Web_Application_Security_Testing/02-Configuration_and_Deployment_Management_Testing/06-Test_HTTP_Methods | AE50: 2026-10-09
A51: AV-WEB-50 | B51: Web application | C51: Insufficient logging & alerting (application) | D51: Detection | E51: Defense evasion | F51: Medium | G51: Security-relevante gebeurtenissen (logins, mislukte autorisatie, inputvalidatiefouten, admin-acties) worden niet, onvolledig of zonder context gelogd en er zijn geen alerts. | H51: Aanvallen en misbruik blijven onopgemerkt; forensisch onderzoek is beperkt. | I51: Voer tijdens de test herkenbare acties uit (mislukte logins, IDOR-pogingen, injectie) en verifieer met de klant of deze in logging en alerting zichtbaar zijn. | J51: Log auth-, autorisatie- en validatiegebeurtenissen gestructureerd met correlatie-id's, centraliseer in SIEM, definieer alerts en bewaartermijnen; geen gevoelige data in logs. | K51: Meet dekking door purple-team-stijl verificatie van testacties in het SIEM. | L51: A09:2025 | N51: WSTG-CONF (geen specifieke test) | O51: V16 | P51: T1562.008 | Q51: CWE-778, CWE-223 | R51: Methodology and Resources | T51: D7 | AB51: AV-CLD-08 | AD51: https://cheatsheetseries.owasp.org/cheatsheets/Logging_Cheat_Sheet.html | AE51: 2026-10-09
A52: AV-WEB-51 | B52: Web application | C52: Missing integrity controls (SRI, unsigned updates, third-party scripts) | D52: Integrity | E52: Initial access | F52: Medium | G52: Externe scripts/CSS worden geladen zonder Subresource Integrity, auto-update- of plugin-mechanismen verifieren geen handtekeningen, en CI/CD-artefacten worden niet gesigneerd. | H52: Supply-chain-compromittering via CDN/third-party (bv. Magecart-achtige skimming) of via gemanipuleerde updates. | I52: Inventariseer externe resources en controleer SRI-hashes, CSP en signature-verificatie van update-/pluginmechanismen. | J52: SRI en strikte CSP voor externe resources, self-hosting van kritieke scripts, ondertekende updates/artefacten en verificatie bij installatie. | K52: Monitor wijzigingen in third-party scripts; CSP-rapportage op onbekende script-bronnen. | L52: A08:2025, A03:2025 | N52: WSTG-CLNT-06 | O52: V3, V15 | P52: T1195.001, T1195.002 | Q52: CWE-353, CWE-494, CWE-829 | R52: Methodology and Resources | T52: D8 | AB52: AV-WEB-23, AV-CLD-19 | AD52: https://cheatsheetseries.owasp.org/cheatsheets/Third_Party_Javascript_Management_Cheat_Sheet.html | AE52: 2026-10-09
A53: AV-WEB-52 | B53: Web application | C53: postMessage / JSONP / cross-origin messaging weaknesses | D53: Client-side | E53: Collection | F53: Medium | G53: window.postMessage-listeners valideren de origin niet of verwerken data onveilig; JSONP-endpoints of cross-site script inclusion lekken gegevens aan derden. | H53: Cross-origin lekkage van tokens/data en DOM-XSS via berichtverwerking. | I53: Inventariseer message-listeners en JSONP-endpoints in de client-code en toets origin-validatie en sink-gebruik (WSTG-CLNT-11, WSTG-CLNT-13). | J53: Valideer event.origin tegen een allowlist, behandel berichtdata als onvertrouwd, vervang JSONP door CORS met allowlist. | K53: Client-side telemetry; code review in CI op onveilige listeners. | L53: A01:2025 | N53: WSTG-CLNT-11, WSTG-CLNT-13 | O53: V3 | Q53: CWE-346, CWE-79 | R53: XSS Injection | S53: Web attacks | T53: D8 | AB53: AV-WEB-26, AV-WEB-41 | AD53: https://portswigger.net/web-security/dom-based/controlling-the-web-message-source | AE53: 2026-10-09
A54: AV-WEB-53 | B54: Web application | C54: Sensitive data in client-side storage | D54: Data protection | E54: Credential access | F54: Medium | G54: Access/refresh tokens, PII of secrets worden in localStorage/sessionStorage/IndexedDB bewaard, waardoor elke XSS ze kan uitlezen en ze persistent op het apparaat achterblijven. | H54: Tokendiefstal en accountovername bij XSS of lokale toegang. | I54: Inspecteer browser storage na inloggen en beoordeel de gevoeligheid en levensduur van opgeslagen waarden (WSTG-CLNT-12). | J54: Bewaar sessietokens in HttpOnly-cookies (met SameSite), minimaliseer client-side opslag, korte tokenlevensduur en refresh-rotatie. | K54: Niet server-side detecteerbaar; audit tijdens code review. | L54: A04:2025 | N54: WSTG-CLNT-12 | O54: V7, V14 | P54: T1539, T1528 | Q54: CWE-922, CWE-312 | R54: Methodology and Resources | S54: Web attacks | T54: D2 | AB54: AV-WEB-14, AV-WEB-47 | AD54: https://cheatsheetseries.owasp.org/cheatsheets/HTML5_Security_Cheat_Sheet.html | AE54: 2026-10-09
A55: AV-API-01 | B55: API | C55: Broken object level authorization (BOLA) | D55: Authorization | E55: Privilege escalation | F55: High | G55: Endpoints met object-id's zonder autorisatiecheck geven toegang tot andermans objecten. | H55: Ongeautoriseerde toegang tot data van andere gebruikers. | I55: Wissel object-id's tussen accounts en controleer server-side autorisatie (WSTG-ATHZ). | J55: Autorisatiecheck op elk object per request; onvoorspelbare id's. | K55: Alarmeer op toegang tot object-id's buiten het bereik van de token. | L55: A01:2025 | M55: API1:2023 | N55: WSTG-ATHZ-04 | O55: V8 | P55: T1078 | Q55: CWE-639 | R55: Insecure Direct Object References | S55: Web attacks | T55: D5 | AB55: AV-WEB-01 | AE55: 2026-10-09
A56: AV-API-02 | B56: API | C56: Broken authentication | D56: Authentication | E56: Credential access | F56: High | G56: Zwakke of onjuist geimplementeerde authenticatie op API-endpoints. | H56: Tokencompromittering en impersonatie. | I56: Controleer token-uitgifte, -validatie en endpoint-dekking (WSTG-ATHN). | J56: Sterke authenticatie, correcte tokenvalidatie, MFA waar passend. | K56: Monitor op authenticatie-anomalieen en tokenmisbruik. | L56: A07:2025 | M56: API2:2023 | N56: WSTG-ATHN-04, WSTG-ATHN-10 | O56: V6 | P56: T1078 | Q56: CWE-287 | R56: Account Takeover | S56: Web attacks | T56: D5 | AB56: AV-WEB-12, AV-WEB-14, AV-API-12 | AE56: 2026-10-09
A57: AV-API-03 | B57: API | C57: Broken object property level authorization | D57: Authorization | E57: Collection | F57: Medium | G57: Onvoldoende autorisatie op property-niveau (excessive data exposure / mass assignment). | H57: Uitlezen of overschrijven van niet-toegestane velden. | I57: Controleer of respons- en request-velden per rol worden beperkt (WSTG-ATHZ). | J57: Expliciete allowlist van velden bij lezen en schrijven. | K57: Monitor op schrijfacties naar gevoelige properties. | L57: A01:2025 | M57: API3:2023 | N57: WSTG-INPV-20 | O57: V8 | Q57: CWE-915 | R57: Mass Assignment | S57: Web attacks | T57: D5 | AB57: AV-API-11 | AE57: 2026-10-09
A58: AV-API-04 | B58: API | C58: Unrestricted resource consumption | D58: Availability | E58: Impact | F58: Medium | G58: Ontbrekende limieten op verzoeken of resources. | H58: Denial-of-service en verhoogde kosten. | I58: Controleer rate-limiting, paginering en resourcequota (WSTG-BUSL). | J58: Rate-limiting, quota, payload- en time-out-limieten. | K58: Alarmeer op verbruikspieken per client/token. | L58: A06:2025 | M58: API4:2023 | N58: WSTG-BUSL-05 | O58: V2 | P58: T1499 | Q58: CWE-770 | R58: Methodology and Resources | S58: Web attacks | T58: D8 | AB58: AV-WEB-32, AV-AI-06 | AE58: 2026-10-09
A59: AV-API-05 | B59: API | C59: Broken function level authorization | D59: Authorization | E59: Privilege escalation | F59: High | G59: Functies zonder rolcontrole zijn bereikbaar voor lagere rollen. | H59: Toegang tot administratieve of bevoorrechte functies. | I59: Benader functies met verschillende rollen en controleer enforcement (WSTG-ATHZ). | J59: Deny-by-default per functie; centrale autorisatielaag. | K59: Alarmeer op bevoorrechte functie-aanroepen door lage rollen. | L59: A01:2025 | M59: API5:2023 | N59: WSTG-ATHZ-02, WSTG-ATHZ-03 | O59: V8 | Q59: CWE-285 | R59: Privilege Escalation | S59: Web attacks | T59: D5 | AB59: AV-WEB-02 | AE59: 2026-10-09
A60: AV-API-06 | B60: API | C60: Unrestricted access to sensitive business flows | D60: Business logic | E60: Impact | F60: Medium | G60: Gevoelige bedrijfsflows zonder misbruikbescherming (bv. bulk-aankoop, spam). | H60: Geautomatiseerd misbruik met bedrijfsschade. | I60: Identificeer gevoelige flows en toets anti-automatiseringsmaatregelen (WSTG-BUSL). | J60: Detecteer automatisering, voeg frictie toe, limiteer flows. | K60: Gedragsanalyse op flow-gebruik. | L60: A06:2025 | M60: API6:2023 | N60: WSTG-BUSL-07 | O60: V2 | Q60: CWE-840 | R60: Methodology and Resources | S60: Web attacks | T60: D8 | AB60: AV-WEB-22, AV-WEB-34 | AE60: 2026-10-09
A61: AV-API-07 | B61: API | C61: Server-side request forgery (API) | D61: Access control | E61: Discovery | F61: High | G61: API haalt op basis van gebruikersinvoer onbedoelde bestemmingen op. | H61: Interne netwerktoegang en metadata-diefstal. | I61: Controleer validatie van gebruikersgestuurde URL's server-side (WSTG-INPV). | J61: Allowlist bestemmingen; blokkeer interne ranges. | K61: Egress-filtering en alarmering op interne calls. | L61: A01:2025 | M61: API7:2023 | N61: WSTG-INPV-19 | O61: V4 | P61: T1190 | Q61: CWE-918 | R61: Server Side Request Forgery | S61: Web attacks | T61: D8 | AB61: AV-WEB-07, AV-CLD-05 | AE61: 2026-10-09
A62: AV-API-08 | B62: API | C62: Security misconfiguration (API) | D62: Configuration | E62: Reconnaissance | F62: Medium | G62: Onveilige defaults, CORS-fouten of ontbrekende hardening op API-niveau. | H62: Uiteenlopende blootstelling en toegang. | I62: Controleer CORS, methods, headers en foutafhandeling (WSTG-CONF). | J62: Hardening-baseline, strak CORS-beleid, minimaliseer methods. | K62: Config-scans en CORS-monitoring. | L62: A02:2025 | M62: API8:2023 | N62: WSTG-CONF-02, WSTG-CLNT-07 | O62: V13 | Q62: CWE-16 | R62: Methodology and Resources | S62: Enumeration | T62: D3 | AB62: AV-WEB-26, AV-WEB-18 | AE62: 2026-10-09
A63: AV-API-09 | B63: API | C63: Improper inventory management | D63: Configuration | E63: Reconnaissance | F63: Medium | G63: Onbekende, verouderde of ongedocumenteerde API-versies en -endpoints. | H63: Aanvalsoppervlak via shadow/legacy-endpoints. | I63: Inventariseer versies, hosts en endpoints en vergelijk met documentatie (WSTG-CONF). | J63: Actuele API-inventaris, deprecatiebeleid, retirement. | K63: Monitor verkeer naar niet-geinventariseerde endpoints. | L63: A02:2025 | M63: API9:2023 | N63: WSTG-INFO-04, WSTG-CONF-05 | O63: V13 | Q63: CWE-1059 | R63: Methodology and Resources | S63: Enumeration | T63: D8 | AB63: AV-EXT-01, AV-EXT-07 | AE63: 2026-10-09
A64: AV-API-10 | B64: API | C64: Unsafe consumption of APIs | D64: Integrity | E64: Execution | F64: Medium | G64: Data van derde-partij-API's wordt te vertrouwd verwerkt. | H64: Compromittering via upstream-services. | I64: Controleer validatie en isolatie van externe API-responses (WSTG-INPV). | J64: Valideer externe data, gebruik time-outs en isolatie. | K64: Monitor afwijkend gedrag van integraties. | L64: A08:2025 | M64: API10:2023 | N64: WSTG-INPV (geen specifieke test) | O64: V4 | P64: T1195 | Q64: CWE-1104 | R64: Methodology and Resources | S64: Web attacks | T64: D8 | AB64: AV-CLD-19 | AE64: 2026-10-09
A65: AV-API-11 | B65: API | C65: Missing input schema validation (type juggling, JSON injection, HPP) | D65: Input validation | E65: Execution | F65: Medium | G65: De API valideert request-bodies niet tegen een strikt schema: onverwachte types (array i.p.v. string), extra velden, dubbele parameters of genest JSON worden geaccepteerd en doorgegeven aan back-endlogica. | H65: Logica-omzeiling (bv. prijs/rol), injectie in downstream-systemen, crashes (DoS). | I65: Verander types, voeg onverwachte velden toe, dupliceer parameters en vergelijk server-side gedrag met de OpenAPI-specificatie (WSTG-INPV-04). | J65: Strikte schema-validatie (OpenAPI/JSON Schema) met additionalProperties: false, canonicalisatie van parameters, typesterke deserialisatie. | K65: Alarmeer op schema-validatiefouten en afwijkende request-structuren. | L65: A05:2025 | M65: API3:2023, API8:2023 | N65: WSTG-INPV-04 | O65: V2, V4 | Q65: CWE-20, CWE-235 | R65: HTTP Parameter Pollution | S65: Web attacks | T65: D8 | AB65: AV-API-03 | AD65: https://cheatsheetseries.owasp.org/cheatsheets/REST_Security_Cheat_Sheet.html | AE65: 2026-10-09
A66: AV-API-12 | B66: API | C66: Insufficient authentication on internal / machine-to-machine APIs | D66: Authentication | E66: Lateral movement | F66: High | G66: Interne of service-to-service API's vertrouwen op netwerklocatie, statische gedeelde API-keys of ontbrekende mTLS, waardoor elke host in het segment (of een gelekte key) volledige toegang heeft. | H66: Laterale beweging en data-toegang vanuit een gecompromitteerde component of via een gelekte key. | I66: Benader interne API's vanaf een andere host/pod zonder credentials of met gelekte keys; controleer key-rotatie, scoping en mTLS. | J66: mTLS of kortlevende workload-identiteiten (SPIFFE/OIDC), per-client scopes, key-rotatie, netwerkbeleid als extra laag. | K66: Alarmeer op API-calls vanaf onverwachte workloads/IP's en op gebruik van verlopen keys. | L66: A07:2025 | M66: API2:2023 | N66: WSTG-ATHN-10 | O66: V4, V6 | P66: T1078, T1552 | Q66: CWE-306, CWE-798 | R66: API Key Leaks | T66: D5 | AB66: AV-CLD-02, AV-NET-15 | AD66: https://cheatsheetseries.owasp.org/cheatsheets/Microservices_Security_Cheat_Sheet.html | AE66: 2026-10-09
A67: AV-NET-01 | B67: Internal network | C67: Network enumeration & host discovery | D67: Reconnaissance | E67: Reconnaissance | F67: Info | G67: Ontdekken van hosts, poorten en services binnen de scope. | H67: Bouwt de kaart van het aanvalsoppervlak. | I67: Voer scoped host- en servicediscovery uit conform de rules of engagement. | J67: Netwerksegmentatie en minimalisatie van blootgestelde services. | K67: IDS/NDR-detectie op scanpatronen. | P67: T1046, T1595, T1018 | R67: Network Discovery | S67: Enumeration | T67: D4 | AB67: AV-EXT-01, AV-AD-22 | AE67: 2026-10-09
A68: AV-NET-02 | B68: Internal network | C68: LLMNR/NBT-NS/mDNS poisoning & ADIDNS wildcard abuse | D68: Adversary-in-the-middle | E68: Credential access | F68: High | G68: Misbruik van fallback-naamresolutie (LLMNR, NBT-NS, mDNS) om verkeer om te leiden en NetNTLM-hashes op te vangen; als die protocollen uitstaan kan een geauthenticeerde gebruiker vaak alsnog een wildcard-record in AD-integrated DNS aanmaken met hetzelfde effect. | H68: Onderschepping van authenticatiemateriaal. | I68: Stel vast of legacy-naamresolutieprotocollen actief zijn in het segment. | J68: Schakel LLMNR/NBT-NS/mDNS uit via GPO; segmenteer; dwing veilige resolutie af; blokkeer aanmaak van wildcard-DNS-records (ADIDNS) door gewone gebruikers en dwing SMB/LDAP signing af zodat relay niet lukt. | K68: Alarmeer op onverwachte responder-activiteit. | P68: T1557.001 | R68: Active Directory Attack | S68: Active Directory | T68: D4 | AB68: AV-NET-03, AV-NET-10, AV-AD-18, AV-NET-08, CVE-2025-24054 | AE68: 2026-10-09
A69: AV-NET-03 | B69: Internal network | C69: NTLM relay | D69: Adversary-in-the-middle | E69: Lateral movement | F69: High | G69: Doorsturen van onderschepte authenticatie naar hosts zonder signing. | H69: Authenticatie als slachtoffer op andere systemen. | I69: Controleer of SMB/LDAP-signing wordt afgedwongen op doelsystemen. | J69: Dwing signing af, schakel legacy uit, segmenteer. | K69: Detecteer authenticaties met afwijkende bron/keten. | P69: T1557 | R69: Active Directory Attack | S69: Active Directory | T69: D4 | AB69: AV-NET-08, AV-AD-14, AV-AD-17, AV-NET-10, CVE-2019-1040, CVE-2025-33073, CVE-2024-21410 | AE69: 2026-10-09
A70: AV-NET-04 | B70: Internal network | C70: Service/version exploitation (unpatched) | D70: Exploitation | E70: Initial access | F70: High | G70: Bekende kwetsbaarheden in ongepatchte netwerkservices. | H70: Toegang tot of controle over de host. | I70: Identificeer versies en vergelijk met bekende adviezen binnen scope. | J70: Patchmanagement, minimaliseer blootgestelde services. | K70: Vulnerability-scanning en exploit-signature-detectie. | L70: A03:2025 | P70: T1190, T1210 | Q70: CWE-1104 | R70: Methodology and Resources | S70: Enumeration | T70: D4 | AB70: AV-NET-21, CVE-2017-0144, CVE-2019-0708, CVE-2020-0796, CVE-2025-59287, CVE-2026-33824 | AE70: 2026-10-09
A71: AV-NET-05 | B71: Internal network | C71: Default / weak credentials | D71: Credential access | E71: Initial access | F71: High | G71: Vendor-defaults of zwakke wachtwoorden op services en apparaten. | H71: Directe toegang tot systemen. | I71: Controleer op default- en zwakke credentials binnen scope. | J71: Verwijder defaults, sterk wachtwoordbeleid, MFA. | K71: Alarmeer op logins met default-accounts. | P71: T1078, T1110 | Q71: CWE-521 | R71: Methodology and Resources | S71: Enumeration | T71: D5 | AB71: AV-NET-12, AV-NET-14, AV-NET-19, AV-WEB-44 | AE71: 2026-10-09
A72: AV-NET-06 | B72: Internal network | C72: Password spraying | D72: Credential access | E72: Credential access | F72: High | G72: Een klein aantal veelgebruikte wachtwoorden tegen veel accounts. | H72: Accountcompromittering zonder lockout te triggeren. | I72: Controleer lockout-, throttling- en detectiebeleid (binnen RoE). | J72: MFA, slim lockout-beleid, detectie van spray-patronen. | K72: Alarmeer op veel accounts met enkele mislukte pogingen. | P72: T1110.003 | Q72: CWE-307 | R72: Password Spraying | S72: Active Directory | T72: D5 | AB72: AV-WEB-43, AV-AD-19, AV-EXT-06, AV-CLD-09 | AE72: 2026-10-09
A73: AV-NET-07 | B73: Internal network | C73: Cleartext protocol interception | D73: Sniffing | E73: Credential access | F73: Medium | G73: Onversleutelde protocollen laten meelezen van credentials toe. | H73: Onderschepping van gevoelige gegevens. | I73: Inventariseer onversleuteld verkeer binnen scope. | J73: Dwing versleuteling af; verwijder legacy-protocollen. | K73: NDR-detectie op cleartext-credentialverkeer. | L73: A04:2025 | O73: V12 | P73: T1040 | Q73: CWE-319 | R73: Network Sniffing | S73: Enumeration | T73: D4 | AB73: AV-NET-11, AV-NET-18, AV-WEB-20 | AE73: 2026-10-09
A74: AV-NET-08 | B74: Internal network | C74: SMB signing disabled | D74: Configuration | E74: Lateral movement | F74: Medium | G74: Ontbrekende SMB-signing maakt relay- en MitM-aanvallen mogelijk. | H74: Faciliteert NTLM-relay en verkeersmanipulatie. | I74: Controleer of SMB-signing vereist is op hosts binnen scope. | J74: Vereis SMB-signing domainbreed. | K74: Inventariseer hosts zonder verplichte signing. | L74: A02:2025 | P74: T1557 | Q74: CWE-16 | R74: Active Directory Attack | S74: Active Directory | T74: D4 | AB74: AV-NET-03, AV-AD-14, AV-AD-17, CVE-2025-33073 | AE74: 2026-10-09
A75: AV-NET-09 | B75: Internal network | C75: SNMP misconfiguration | D75: Configuration | E75: Discovery | F75: Medium | G75: Zwakke community strings of blootgestelde SNMP-informatie. | H75: Informatielekkage en soms configuratiewijziging. | I75: Controleer op default community strings en blootstelling (binnen scope). | J75: SNMPv3 met authenticatie, beperk toegang. | K75: Monitor SNMP-verkeer van onverwachte bronnen. | L75: A02:2025 | P75: T1602 | Q75: CWE-16 | R75: Methodology and Resources | S75: Enumeration | T75: D4 | AB75: AV-NET-12, CVE-2025-20352 | AE75: 2026-10-09
A76: AV-NET-10 | B76: Internal network | C76: IPv6 / DHCPv6 spoofing (mitm6) & WPAD abuse | D76: Adversary-in-the-middle | E76: Credential access | F76: High | G76: Windows-hosts vragen standaard DHCPv6 aan; een aanvaller op het segment deelt zichzelf uit als DNS-server en vangt via WPAD/DNS-spoofing authenticatie op die naar LDAP(S)/SMB gerelayed kan worden. | H76: NTLM-relay naar LDAP (computeraccount aanmaken, RBCD) tot en met domeincompromittering. | I76: Stel vast of IPv6 actief maar onbeheerd is en of clients DHCPv6/WPAD gebruiken; voer alleen passieve of expliciet goedgekeurde actieve tests uit (RoE). | J76: Beheer IPv6 (RA Guard, DHCPv6 Guard) of schakel het bewust uit op clients, schakel WPAD uit, dwing LDAP signing/channel binding en SMB signing af. | K76: Alarmeer op onverwachte DHCPv6/RA-bronnen en WPAD-aanvragen naar onbekende hosts. | P76: T1557.003, T1557.001 | Q76: CWE-290 | R76: Active Directory Attack - mitm6 | S76: Active Directory | T76: D4 | AB76: AV-NET-02, AV-NET-03, AV-AD-17 | AD76: https://blog.fox-it.com/2018/01/11/mitm6-compromising-ipv4-networks-via-ipv6/ | AE76: 2026-10-09
A77: AV-NET-11 | B77: Internal network | C77: ARP spoofing / layer-2 attacks | D77: Adversary-in-the-middle | E77: Credential access | F77: Medium | G77: Ontbrekende Dynamic ARP Inspection, DHCP snooping en port security laten ARP-cache-poisoning, DHCP-spoofing en VLAN-hopping toe op toegangsswitches. | H77: Onderschepping en manipulatie van verkeer binnen het segment; downgrade naar cleartext. | I77: Beoordeel switchconfiguratie (DAI, DHCP snooping, port security, native VLAN) en voer alleen beperkte, goedgekeurde PoC's uit. | J77: DAI, DHCP snooping, port security, 802.1X, geen ongebruikte poorten in productie-VLAN's, versleuteling van gevoelig verkeer. | K77: Alarmeer op ARP-anomalieen (dubbele MAC/IP-koppelingen) via NDR/switch-logging. | P77: T1557.002 | Q77: CWE-290 | R77: Network Sniffing | S77: Enumeration | T77: D4 | AB77: AV-NET-07, AV-NET-20 | AD77: https://attack.mitre.org/techniques/T1557/002/ | AE77: 2026-10-09
A78: AV-NET-12 | B78: Internal network | C78: Exposed management interfaces (IPMI/BMC, iLO, iDRAC, web admin) | D78: Configuration | E78: Privilege escalation | F78: High | G78: Out-of-band-beheerinterfaces en webconsoles van servers, switches, storage en hypervisors zijn vanuit gebruikers-VLAN's bereikbaar, vaak met default credentials, verouderde firmware of IPMI 2.0 (RAKP-hashlekkage, cipher 0). | H78: Volledige controle over hardware (console, virtual media, power) buiten het OS om; persistente toegang. | I78: Inventariseer beheerinterfaces per segment, controleer bereikbaarheid vanuit niet-beheerzones, default credentials, IPMI-versie/cipher-suites en firmwareversie. | J78: Isoleer beheer in een apart OOB-VLAN met jump hosts en MFA, verwijder defaults, schakel IPMI-over-LAN uit waar mogelijk, firmware-updates. | K78: Alarmeer op logins op beheerinterfaces vanaf niet-beheernetwerken. | P78: T1021, T1078.001, T1110 | Q78: CWE-1188, CWE-284 | R78: Insecure Management Interface | S78: Enumeration | T78: D4 | AB78: CVE-2013-4786, AV-NET-05, AV-NET-15 | AD78: https://www.rapid7.com/blog/post/2013/07/02/a-penetration-testers-guide-to-ipmi/ | AE78: 2026-10-09
A79: AV-NET-13 | B79: Internal network | C79: Insecure network shares (anonymous / overly permissive SMB & NFS) | D79: Access control | E79: Collection | F79: High | G79: Fileshares zijn leesbaar (of schrijfbaar) voor Everyone/Authenticated Users of anonieme gebruikers; NFS-exports zonder root_squash of met no_root_squash; shares bevatten configs, scripts, backups en wachtwoorden. | H79: Datalek, credential-vondst (vaak de snelste route naar domain admin), plaatsing van kwaadaardige bestanden (LNK/SCF voor hash-capture). | I79: Enumereer shares en exports als anonieme en als laaggeprivilegieerde gebruiker, scan bestandsinhoud op credentials en gevoelige data (binnen scope). | J79: Least-privilege share- en NTFS-rechten, verwijder anonieme toegang, root_squash en host-restricties op NFS, opschonen van credentials in bestanden, DLP/classificatie. | K79: Alarmeer op grootschalige share-enumeratie en massale bestandsreads door een enkele gebruiker. | P79: T1135, T1039, T1552.001 | Q79: CWE-732, CWE-284 | R79: Methodology and Resources - Network Discovery | S79: Enumeration | T79: D2 | AB79: AV-AD-26, AV-HOST-04 | AD79: https://attack.mitre.org/techniques/T1135/ | AE79: 2026-10-09
A80: AV-NET-14 | B80: Internal network | C80: Exposed databases & unauthenticated services (Redis, MongoDB, Elasticsearch, MSSQL) | D80: Configuration | E80: Initial access | F80: High | G80: Databases, caches en message brokers luisteren op alle interfaces zonder authenticatie of met zwakke/default credentials (bv. sa, postgres, redis zonder requirepass, Elasticsearch zonder security). | H80: Datalek en vaak code-uitvoering op de host (xp_cmdshell, Redis module/config-write, MongoDB scripting). | I80: Scan op databaseservices, test anonieme toegang en default credentials, beoordeel versie en netwerkblootstelling. | J80: Bind op localhost/beheerinterfaces, authenticatie en TLS verplicht, firewall per bron, least-privilege accounts, patchbeleid. | K80: Alarmeer op verbindingen naar databases vanaf niet-applicatiehosts. | L80: A02:2025 | P80: T1190, T1078.001, T1213 | Q80: CWE-306, CWE-1188 | R80: Methodology and Resources | S80: Enumeration | T80: D4 | AB80: CVE-2025-49844, CVE-2025-14847, AV-NET-05 | AD80: https://attack.mitre.org/techniques/T1190/ | AE80: 2026-10-09
A81: AV-NET-15 | B81: Internal network | C81: Insufficient network segmentation (flat network) | D81: Architecture | E81: Lateral movement | F81: High | G81: Werkplekken, servers, OT/IoT, beheer en gasten delen (routeerbare) segmenten zonder filtering, waardoor een gecompromitteerd endpoint direct kritieke systemen bereikt. | H81: Snelle laterale beweging en ransomware-verspreiding; blast radius van een enkel incident is het hele netwerk. | I81: Test bereikbaarheid van kritieke systemen (DC's, databases, backup, OT, beheer) vanuit representatieve segmenten; beoordeel firewallregels en VLAN-ontwerp. | J81: Zonering (gebruikers, servers, beheer, OT, DMZ, gasten) met default-deny tussen zones, microsegmentatie voor kritieke assets, host-firewalls. | K81: NDR/flow-monitoring op oost-west-verkeer tussen zones; alarmeer op SMB/RDP tussen werkplekken. | P81: T1021, T1570, T1210 | Q81: CWE-923 | R81: Network Pivoting Techniques | S81: Tunneling | T81: D4 | AB81: AV-NET-12, AV-NET-17, AV-WIFI-07 | AC81: CIS Controls v8: 12.2 | AD81: https://www.cisecurity.org/controls/v8 | AE81: 2026-10-09
A82: AV-NET-16 | B82: Internal network | C82: Insufficient egress filtering (C2 / exfiltration possible) | D82: Architecture | E82: Command and control | F82: Medium | G82: Uitgaand verkeer vanaf werkplekken en servers is niet beperkt tot noodzakelijke bestemmingen/protocollen (direct internet, DNS naar externe resolvers, onbeperkt 443), waardoor C2-kanalen en data-exfiltratie onopgemerkt blijven. | H82: Vrije command-and-control en exfiltratie; DNS/ICMP-tunneling mogelijk. | I82: Test vanuit representatieve segmenten welke poorten/protocollen naar internet open staan (incl. DNS-tunneling en directe IP-verbindingen) en of een proxy verplicht is. | J82: Default-deny egress met proxy/allowlisting, interne DNS-resolvers afdwingen, TLS-inspectie waar passend, geen directe internettoegang voor servers. | K82: Alarmeer op lange/regelmatige verbindingen naar onbekende bestemmingen, DNS-anomalieen en grote uitgaande volumes. | P82: T1071, T1572, T1090, T1048 | Q82: CWE-923 | R82: Network Pivoting Techniques | S82: Tunneling | T82: D4 | AB82: AV-NET-15 | AD82: https://attack.mitre.org/techniques/T1572/ | AE82: 2026-10-09
A83: AV-NET-17 | B83: Internal network | C83: Exposed remote access services (RDP/VNC/SSH) with weak configuration | D83: Configuration | E83: Lateral movement | F83: Medium | G83: RDP zonder NLA, VNC zonder of met zwak wachtwoord, SSH met wachtwoordauthenticatie/root-login, en remote access tools (AnyDesk, TeamViewer, ScreenConnect) breed beschikbaar binnen het netwerk. | H83: Brute force en credential-hergebruik voor laterale beweging; shadow-IT remote access als persistentiekanaal. | I83: Inventariseer remote-access-services per segment, controleer NLA, encryptie, authenticatiemethoden en lockout. | J83: NLA en MFA op RDP, SSH met keys en zonder root-login, VNC alleen via tunnel, allowlisting van remote-access-tools, jump hosts. | K83: Alarmeer op RDP/SSH-logins tussen werkplekken en op installatie van onbekende remote-access-software. | P83: T1021.001, T1021.004, T1219, T1110 | Q83: CWE-287, CWE-306 | R83: Methodology and Resources | S83: Password attacks | T83: D4 | AB83: CVE-2019-0708, CVE-2024-1709, AV-NET-05 | AD83: https://attack.mitre.org/techniques/T1021/001/ | AE83: 2026-10-09
A84: AV-NET-18 | B84: Internal network | C84: Legacy protocols enabled (SMBv1, Telnet/FTP, TLS 1.0/1.1, SSLv3) | D84: Configuration | E84: Initial access | F84: Medium | G84: Verouderde protocollen en versies zijn nog actief op servers, printers en appliances, met bekende kwetsbaarheden (EternalBlue op SMBv1), cleartext-authenticatie of zwakke cryptografie. | H84: Exploitatie van bekende kwetsbaarheden, onderschepping van credentials, downgrade-aanvallen. | I84: Scan op SMBv1, Telnet, FTP, oude TLS-versies en cipher suites; koppel aan bekende CVE's binnen scope. | J84: Schakel SMBv1 uit (GPO), vervang Telnet/FTP door SSH/SFTP, TLS 1.2+ met moderne suites, vervang of isoleer apparaten die dit niet ondersteunen. | K84: Periodieke protocolscans; alarmeer op SMBv1-negotiatie en cleartext-logins in NDR. | L84: A02:2025, A04:2025 | P84: T1210, T1040 | Q84: CWE-1104, CWE-327, CWE-319 | R84: Methodology and Resources | S84: Enumeration | T84: D4 | AB84: CVE-2017-0144, AV-NET-07, AV-AD-18 | AD84: https://learn.microsoft.com/en-us/windows-server/storage/file-server/troubleshoot/detect-enable-and-disable-smbv1-v2-v3 | AE84: 2026-10-09
A85: AV-NET-19 | B85: Internal network | C85: Printer / MFP abuse (LDAP pass-back, stored credentials, PJL) | D85: Configuration | E85: Credential access | F85: Medium | G85: Multifunctionals met default admin-wachtwoord bevatten LDAP/SMB-scan-to-folder-credentials; door het LDAP-adres te wijzigen (pass-back) worden die credentials in cleartext naar de aanvaller gestuurd; PJL/PostScript geeft toegang tot het bestandssysteem en opgeslagen scans. | H85: Verkrijgen van (vaak geprivilegieerde) domeincredentials en gevoelige documenten. | I85: Inventariseer printers, controleer default credentials en de aanwezigheid van opgeslagen LDAP/SMB-accounts; voer pass-back alleen uit binnen RoE. | J85: Unieke admin-wachtwoorden, least-privilege scan-accounts (geen domain admin), LDAPS met certificaatvalidatie, printers in apart VLAN, firmware-updates. | K85: Alarmeer op LDAP-binds van printeraccounts naar niet-DC-hosts. | P85: T1557, T1552, T1078.001 | Q85: CWE-1188, CWE-522 | R85: Methodology and Resources | S85: Enumeration | T85: D4 | AB85: AV-NET-05, AV-NET-12 | AD85: http://hacking-printers.net/wiki/index.php/Main_Page | AE85: 2026-10-09
A86: AV-NET-20 | B86: Internal network | C86: No network access control (802.1X / NAC) on wired or wireless | D86: Configuration | E86: Initial access | F86: Medium | G86: Elke fysiek aangesloten of draadloos verbonden apparaat krijgt een adres in een productie-VLAN; geen 802.1X, MAB-only met MAC-spoofing mogelijk, of NAC alleen in monitoring-mode. | H86: Rogue devices (drop boxes, implants) en meegebrachte laptops krijgen direct toegang tot het interne netwerk. | I86: Sluit een onbekend apparaat aan op toegangspoorten (vergaderzalen, printers, VoIP) en bepaal verkregen toegang; test MAC-spoofing van toegestane apparaten (RoE). | J86: 802.1X met certificaten (EAP-TLS), MAB alleen met profiling en beperkt VLAN, poortlockdown van ongebruikte poorten, VoIP/printer-VLAN's gescheiden. | K86: NAC-alerts op nieuwe MAC-adressen en profiling-mismatch. | P86: T1200, T1557 | Q86: CWE-306 | R86: Methodology and Resources | T86: D4 | AB86: AV-PHY-03, AV-PHY-08, AV-WIFI-05 | AD86: https://attack.mitre.org/techniques/T1200/ | AE86: 2026-10-09
A87: AV-NET-21 | B87: Internal network | C87: End-of-life / unsupported systems | D87: Supply chain | E87: Initial access | F87: High | G87: Besturingssystemen, databases of appliances zonder leveranciersondersteuning (bv. Windows Server 2012/2012 R2, Windows 10 na okt 2025, oude ESXi/NetScaler-firmware) draaien in productie zonder compenserende maatregelen. | H87: Onherstelbare, publiek bekende kwetsbaarheden; vaak directe exploitatie tot SYSTEM/root. | I87: Inventariseer versies via scans en CMDB en vergelijk met EOL-data; beoordeel isolatie en compenserende maatregelen. | J87: Migreren/vervangen, ESU waar tijdelijk nodig, strikte isolatie (geen internet, aparte zone), virtual patching, verwijderen uit het domein waar mogelijk. | K87: Vulnerability management met EOL-signalering; alarmeer op verkeer naar EOL-hosts vanaf werkplekken. | L87: A03:2025 | P87: T1210, T1068 | Q87: CWE-1104 | R87: Methodology and Resources | S87: Public exploits | T87: D7 | AB87: AV-NET-04, CVE-2017-0144, CVE-2019-0708 | AD87: https://endoflife.date/ | AE87: 2026-10-09
A88: AV-NET-22 | B88: Internal network | C88: Virtualization / hypervisor management exposure (vCenter, ESXi, Hyper-V, Proxmox) | D88: Configuration | E88: Privilege escalation | F88: High | G88: Hypervisor-beheerinterfaces zijn bereikbaar vanuit gebruikerssegmenten, gekoppeld aan AD (ESXi Admins-groep), ongepatcht of met lokale accounts zonder MFA; VM-escape en snapshot-diefstal zijn mogelijk. | H88: Compromittering van alle virtuele machines tegelijk (incl. DC's via VMDK-diefstal), ransomware op hypervisorniveau. | I88: Controleer netwerkblootstelling, versies, AD-koppeling/groepsnamen, SSH/shell-toegang en lockdown-mode van hypervisors en vCenter. | J88: Beheer alleen via beheerzone met MFA, patchen, lockdown mode, geen AD-groepsnaamgebaseerde admin zonder beveiliging, immutable backups van VM's. | K88: Alarmeer op logins op vCenter/ESXi vanaf niet-beheernetwerken en op massale snapshot-/export-acties. | P88: T1021, T1078, T1611 | Q88: CWE-284 | R88: Methodology and Resources | T88: D3 | AB88: CVE-2021-21972, CVE-2024-37085, CVE-2025-22224, CVE-2026-59310 | AD88: https://www.cisa.gov/news-events/cybersecurity-advisories/aa23-039a | AE88: 2026-10-09
A89: AV-NET-23 | B89: Internal network | C89: Backup infrastructure exposure (Veeam, Commvault, NAS-backups) | D89: Configuration | E89: Impact | F89: High | G89: Backupservers draaien in het domein met geprivilegieerde service-accounts, zijn breed bereikbaar, ongepatcht of hebben backups die door domeinaccounts verwijderd/versleuteld kunnen worden. | H89: Ransomware-actoren verwijderen of versleutelen backups en halen credentials uit de backupconsole; herstel wordt onmogelijk. | I89: Beoordeel netwerkblootstelling, versies, domeinlidmaatschap, rechten van backup-accounts en immutabiliteit van backups. | J89: Backupserver buiten het productiedomein of in aparte tier, immutable/offline kopieen (3-2-1-1-0), least-privilege service-accounts, MFA op console, patchen. | K89: Alarmeer op verwijdering van backup-jobs/repositories en op logins op de backupconsole buiten beheerwindows. | P89: T1490, T1078, T1552 | Q89: CWE-284 | R89: Methodology and Resources | T89: D7 | AB89: CVE-2024-40711, AV-NET-15 | AD89: https://www.veeam.com/kb4649 | AE89: 2026-10-09
A90: AV-EXT-01 | B90: External network | C90: External attack surface & OSINT enumeration | D90: Reconnaissance | E90: Reconnaissance | F90: Info | G90: In kaart brengen van domeinen, subdomeinen, IP-ranges, cloudassets, certificaten, medewerkers en technologie via passieve bronnen (CT-logs, DNS, Shodan/Censys, breach-data, social media). | H90: Bepaalt het aanvalsoppervlak en onbekende/vergeten assets (shadow IT). | I90: Voer passieve en lichte actieve enumeratie uit; vergelijk gevonden assets met de inventaris van de klant en rapporteer onbekende assets. | J90: Asset-inventaris en attack-surface-management (ASM), decommissioning-proces, beperking van publieke informatie. | K90: Beperkt; monitor CT-logs en ASM-tooling voor nieuwe assets. | N90: WSTG-INFO-01, WSTG-INFO-02 | P90: T1595, T1593, T1596, T1590 | R90: Methodology and Resources - Subdomains Enumeration | S90: Enumeration | T90: D4 | AB90: AV-NET-01, AV-WEB-28 | AD90: https://github.com/OWASP/amass | AE90: 2026-10-09
A91: AV-EXT-02 | B91: External network | C91: Exposed administrative / remote access services on the perimeter | D91: Configuration | E91: Initial access | F91: High | G91: RDP, SSH, SMB, databases, beheerinterfaces van firewalls/appliances, Kubernetes-API's of Docker-API's zijn direct vanaf internet bereikbaar. | H91: Brute force, credential stuffing en directe exploitatie van beheerinterfaces; ransomware-initial access. | I91: Portscan en servicefingerprinting op de externe ranges; toets authenticatie-eisen, lockout en versies (RoE). | J91: Beheer alleen via VPN/ZTNA met MFA, allowlisting van bron-IP's, verwijder onnodige services, WAF/reverse proxy voor webbeheer. | K91: Alarmeer op externe loginpogingen op beheerservices; ASM-scans. | L91: A02:2025 | P91: T1133, T1190, T1110 | Q91: CWE-284, CWE-1327 | R91: Methodology and Resources | S91: Enumeration | T91: D4 | AB91: AV-NET-17, CVE-2024-0012, CVE-2026-20079 | AD91: https://www.cisa.gov/resources-tools/services/cyber-hygiene-services | AE91: 2026-10-09
A92: AV-EXT-03 | B92: External network | C92: E-mail spoofing (missing/weak SPF, DKIM, DMARC) | D92: Configuration | E92: Initial access | F92: Medium | G92: SPF ontbreekt of is te ruim (+all, te veel includes), DKIM ontbreekt, DMARC staat op p=none of ontbreekt, waardoor e-mails namens het domein vervalst kunnen worden; ook subdomeinen zonder beleid en MTA-STS/TLS-RPT ontbreken. | H92: Geloofwaardige phishing en CEO-fraude namens de organisatie richting medewerkers, klanten en partners. | I92: Analyseer SPF/DKIM/DMARC/MTA-STS-records en test (met toestemming) of een vervalste mail de inbox bereikt. | J92: SPF met -all, DKIM op alle verzendende systemen, DMARC p=reject (gefaseerd), beleid voor subdomeinen, MTA-STS en TLS-RPT, inkomende DMARC-handhaving. | K92: DMARC-aggregaatrapporten monitoren; alarmeer op inkomende mail met eigen domein als afzender die DMARC faalt. | P92: T1566, T1672 | Q92: CWE-290, CWE-346 | R92: Phishing Methodology | T92: D4 | AB92: AV-SE-01, AV-SE-02 | AC92: NCSC-NL / Forum Standaardisatie: SPF, DKIM, DMARC, STARTTLS, DANE | AD92: https://internet.nl/ | AE92: 2026-10-09
A93: AV-EXT-04 | B93: External network | C93: DNS misconfiguration (zone transfer, dangling records, missing DNSSEC) | D93: Configuration | E93: Reconnaissance | F93: Low | G93: AXFR naar willekeurige clients toegestaan, verweesde records naar externe diensten of oude IP's, ontbrekende DNSSEC/CAA, interne hostnamen in publieke zones. | H93: Volledige inventaris van hosts voor aanvallers, subdomain takeover, DNS-spoofing van het domein. | I93: Test zone transfer op alle autoritatieve nameservers, enumereer records en controleer DNSSEC/CAA en dangling records. | J93: AXFR alleen naar secundaire servers, opschonen van records, DNSSEC en CAA, scheiding van interne en externe zones (split-horizon). | K93: Alarmeer op AXFR-verzoeken van onbekende bronnen; periodieke DNS-audit. | N93: WSTG-INFO-02, WSTG-CONF-10 | P93: T1590.002, T1584.001 | Q93: CWE-200, CWE-284 | R93: Methodology and Resources - Subdomains Enumeration | S93: Enumeration | T93: D4 | AB93: AV-WEB-28 | AD93: https://internet.nl/ | AE93: 2026-10-09
A94: AV-EXT-05 | B94: External network | C94: VPN / remote access gateway weaknesses | D94: Authentication | E94: Initial access | F94: High | G94: SSL-VPN's en remote-access-gateways (Fortinet, Citrix NetScaler, Ivanti, Palo Alto, Cisco ASA, SonicWall, Check Point) zonder MFA, met verouderde firmware met bekende exploits, blootgestelde beheerpoorten of zwakke lokale accounts. | H94: Directe toegang tot het interne netwerk met een enkel gelekt wachtwoord of via een publieke exploit; dit is de meest voorkomende ransomware-initial access. | I94: Fingerprint versie en build, vergelijk met KEV/leveranciersadviezen, test MFA-dekking (incl. legacy-realms), lockout en blootstelling van beheerinterfaces. | J94: MFA voor alle gebruikers, patchen binnen dagen bij KEV-vermeldingen, beheerinterface niet aan internet, certificaatgebaseerde clientauthenticatie, logging en integriteitscontroles van de appliance. | K94: Alarmeer op VPN-logins vanaf nieuwe landen/ASN's, meerdere gebruikers vanaf een IP en op configuratiewijzigingen van de appliance. | P94: T1133, T1078, T1190 | Q94: CWE-287, CWE-1104 | R94: Methodology and Resources | S94: Public exploits | T94: D4 | AB94: CVE-2018-13379, CVE-2023-4966, CVE-2024-21887, CVE-2024-3400, CVE-2025-20333, CVE-2025-5777 | AC94: Verwante CVE's zonder eigen rij: CVE-2026-19490 | AD94: https://www.cisa.gov/known-exploited-vulnerabilities-catalog | AE94: 2026-10-09
A95: AV-EXT-06 | B95: External network | C95: Leaked credentials & breach data exposure | D95: Credential access | E95: Initial access | F95: High | G95: Credentials van medewerkers komen voor in publieke datalekken, infostealer-logs of code-repositories; wachtwoordhergebruik tussen prive en zakelijk maakt ze bruikbaar op VPN, M365 of webmail. | H95: Geldige toegang zonder exploitatie; vaak gecombineerd met MFA-fatigue of ontbrekende MFA. | I95: Zoek (binnen RoE en wettelijke kaders) in breach-/stealer-databronnen naar het domein en valideer alleen met toestemming via password spraying of een enkele login. | J95: Credential-screening tegen breach-lijsten, MFA, wachtwoordmanager, monitoring van stealer-logs, incident-proces voor gelekte credentials. | K95: Alarmeer op logins met gelekte credentials (identity protection) en op impossible travel. | P95: T1589.001, T1586, T1078 | Q95: CWE-521, CWE-522 | R95: Account Takeover | S95: Password attacks | T95: D5 | AB95: AV-NET-06, AV-WEB-44, AV-CLD-09 | AD95: https://haveibeenpwned.com/ | AE95: 2026-10-09
A96: AV-EXT-07 | B96: External network | C96: Exposed test / staging / development environments | D96: Configuration | E96: Initial access | F96: Medium | G96: Acceptatie-, test- en ontwikkelomgevingen zijn publiek bereikbaar met productiedata, zwakkere beveiliging, debug-modi, default accounts of oude codeversies; vaak buiten monitoring. | H96: Datalek van productie-achtige data en een makkelijke springplank (gedeelde credentials, netwerkkoppeling) naar productie. | I96: Enumereer subdomeinen/hosts met test/dev/acc/uat-naamgeving, beoordeel beveiliging, data en koppelingen met productie. | J96: Geen productiedata in niet-productie, IP-allowlisting/VPN, dezelfde baseline en monitoring als productie, decommissioning. | K96: ASM-tooling op nieuwe hosts; logging van niet-productieomgevingen centraal. | L96: A02:2025 | N96: WSTG-CONF-05 | O96: V13 | P96: T1190, T1133 | Q96: CWE-284, CWE-1188 | R96: Methodology and Resources | S96: Enumeration | T96: D8 | AB96: AV-WEB-18, AV-WEB-48 | AD96: https://owasp.org/www-project-web-security-testing-guide/latest/4-Web_Application_Security_Testing/02-Configuration_and_Deployment_Management_Testing/05-Enumerate_Infrastructure_and_Application_Admin_Interfaces | AE96: 2026-10-09
A97: AV-AD-01 | B97: Active Directory | C97: Kerberoasting | D97: Credential access | E97: Credential access | F97: High | G97: Service-tickets voor SPN-accounts worden offline op zwak wachtwoord gekraakt. | H97: Compromittering van service-accounts, vaak met hoge rechten. | I97: Inventariseer SPN-accounts en beoordeel wachtwoordsterkte/beleid. | J97: (g)MSA's, sterke wachtwoorden (25+ tekens voor service-accounts), minimaliseer SPN's; schakel RC4 (Kerberos encryption types) uit zodat alleen AES-tickets worden uitgegeven. | K97: Alarmeer op ongebruikelijke service-ticketaanvragen. | P97: T1558.003 | R97: Active Directory Attack - Kerberoast | S97: Active Directory | T97: D5 | AB97: AV-AD-19, AV-AD-20 | AE97: 2026-10-09
A98: AV-AD-02 | B98: Active Directory | C98: AS-REP roasting | D98: Credential access | E98: Credential access | F98: High | G98: Accounts zonder pre-authenticatie leveren krakbaar materiaal op. | H98: Offline kraken van gebruikerswachtwoorden. | I98: Inventariseer accounts met pre-auth uitgeschakeld. | J98: Vereis Kerberos pre-authenticatie; sterke wachtwoorden. | K98: Alarmeer op AS-REP-aanvragen voor dergelijke accounts. | P98: T1558.004 | R98: Active Directory Attack - ASREPRoast | S98: Active Directory | T98: D5 | AB98: AV-AD-19 | AE98: 2026-10-09
A99: AV-AD-03 | B99: Active Directory | C99: OS credential dumping | D99: Credential access | E99: Credential access | F99: High | G99: Extractie van credentials uit geheugen of lokale stores op een host. | H99: Hergebruik van credentials voor verdere toegang. | I99: Beoordeel bescherming van credential-stores en LSASS (post-exploitatie, binnen scope). | J99: Credential Guard, LAPS, least privilege, EDR. | K99: EDR-detectie op geheugentoegang tot credential-processen. | P99: T1003 | R99: Active Directory Attack - Credential Dumping | S99: Active Directory | T99: D5 | AB99: AV-HOST-06, AV-AD-21, AV-HOST-04, CVE-2021-36934 | AE99: 2026-10-09
A100: AV-AD-04 | B100: Active Directory | C100: DCSync | D100: Credential access | E100: Credential access | F100: High | G100: Misbruik van replicatierechten om password-hashes op te vragen bij de DC. | H100: Verkrijgen van hashes tot en met domain-admin. | I100: Beoordeel wie replicatierechten (DS-Replication) bezit. | J100: Beperk replicatierechten; monitor delegaties. | K100: Alarmeer op replicatie vanaf niet-DC-hosts. | P100: T1003.006 | R100: Active Directory Attack - DCSync | S100: Active Directory | T100: D5 | AB100: AV-AD-08, AV-AD-17, AV-CLD-13, CVE-2020-1472 | AE100: 2026-10-09
...

Sheet Legenda
A1: Attack-vectors knowledge base - Legenda (versie 0.10.0, 2026-10-09)
A3: Kolom | B3: Betekenis | C3: Waarden / conventie
A4: ID | B4: Unieke sleutel van de rij. | C4: AV-<SCOPE>-<nn> voor attack vectors (WEB, API, NET, EXT, AD, CLD, MOB, WIFI, SE, PHY, HOST, AI); CVE-jjjj-nnnnn voor bekende kwetsbaarheden.
A5: Scope | B5: Testscope waarin de vector/kwetsbaarheid typisch wordt aangetroffen. | C5: Web application | API | Internal network | External network | Active Directory | Cloud | Mobile | Wireless | Social engineering | Physical | Endpoint | AI / LLM
A6: Vector | B6: Korte Engelse naam van de aanvalstechniek of kwetsbaarheid (rapporttitel). | C6: Vrije tekst; CVE-rijen: "<Product> - <type> (<bijnaam>)".
A7: Category | B7: Klasse van de bevinding. | C7: Bv. Authorization, Injection, Configuration, Credential access, Known vulnerability (alle CVE-rijen).
A8: Kill_chain_phase | B8: Fase (MITRE ATT&CK-tactiek) waarin de techniek doorgaans wordt ingezet. | C8: Reconnaissance | Initial access | Execution | Persistence | Privilege escalation | Defense evasion | Credential access | Discovery | Lateral movement | Collection | Command and control | Impact
A9: Severity_default | B9: Indicatieve standaardernst voor rapportage; pas aan op context en bewijs. | C9: Info | Low | Medium | High | Critical. Voor CVE-rijen gebaseerd op praktische pentest-impact; de formele CVSS-score staat in CVSS_score.
A10: Description / Impact / Test_approach / Remediation / Detection_note | B10: Rapporttekst (NL, zonder diacritics conform bestaande conventie). | C10: Test_approach beschrijft een niet-destructieve aanpak binnen de rules of engagement (RoE).
A11: OWASP_Top10_2025 | B11: Mapping op OWASP Top 10 2025. | C11: A01 Broken Access Control, A02 Security Misconfiguration, A03 Software Supply Chain Failures, A04 Cryptographic Failures, A05 Injection, A06 Insecure Design, A07 Authentication Failures, A08 Software or Data Integrity Failures, A09 Security Logging & Alerting Failures, A10 Mishandling of Exceptional Conditions. CVE-rijen krijgen A03:2025 (kwetsbare component) plus de onderliggende klasse.
A12: OWASP_API_2023 | B12: Mapping op OWASP API Security Top 10 2023. | C12: API1 t/m API10.
A13: WSTG | B13: OWASP Web Security Testing Guide test-ID (v4.2 / latest). | C13: Bv. WSTG-ATHZ-04 (IDOR), WSTG-INPV-05 (SQLi), WSTG-SESS-10 (JWT), WSTG-APIT-01 (GraphQL). Categorie-prefix blijft filterbaar.
A14: ASVS_5.0 | B14: Hoofdstuk van OWASP ASVS 5.0. | C14: V1 Encoding/Sanitization, V2 Validation/Business Logic, V3 Web Frontend, V4 API/Web Service, V5 File Handling, V6 Authentication, V7 Session, V8 Authorization, V9 Self-contained Tokens, V10 OAuth/OIDC, V11 Cryptography, V12 Secure Communication, V13 Configuration, V14 Data Protection, V15 Secure Coding/Architecture, V16 Logging/Error Handling, V17 WebRTC.
... A28: Last_updated | B28: Datum laatste review/wijziging van de rij. | C28: ISO-datum (jjjj-mm-dd).
A30: Bronnen en peildata
A31: CVE-records: CVEProject/cvelistV5 (CNA-beschrijvingen, CVSS, CISA-ADP incl. KEV-datum), stand 2026-10-04.
A32: CISA Known Exploited Vulnerabilities Catalog (via ADP-container in de CVE-records), stand 2026-10-04.
A33: OWASP Top 10 2025, OWASP API Security Top 10 2023, OWASP WSTG v4.2/latest, OWASP ASVS 5.0, OWASP Mobile Top 10 2024 / MASVS 2.x, OWASP Top 10 for LLM Applications 2025.
A34: MITRE ATT&CK Enterprise (v17/v18) en MITRE ATLAS.
A35: Leveranciersadviezen (MSRC, Fortinet PSIRT, Citrix/NetScaler, Ivanti, Palo Alto Networks, Cisco PSIRT, Broadcom/VMware, Atlassian, Oracle CPU, SAP, Adobe, GitLab, JetBrains, JFrog e.a.).
A36: Severity_default, Test_approach, Remediation en Detection_note zijn redactionele keuzes voor rapportage; CVSS/KEV/versies zijn uit de bronnen overgenomen.

Sheet Changelog
A1: Versie | B1: Datum | C1: Onderdeel | D1: Wijziging
A2: 0.10.0 | B2: 2026-10-09 | C2: Structuur | D2: 10 kolommen toegevoegd achter Evidence: CVSS_score, CVSS_vector, Affected_versions, Fixed_in, CISA_KEV, Exploit_public, Related_IDs, Other_mapping, References, Last_updated. Bestaande 21 kolommen, volgorde en kopnamen ongewijzigd.
A3: 0.10.0 | B3: 2026-10-09 | C3: Structuur | D3: Kopregel vet met vulling, bevroren eerste rij/kolom (ID), autofilter over de hele tabel; tabbladen Legenda, Changelog en Overzicht toegevoegd.
A4: 0.10.0 | B4: 2026-10-09 | C4: Attack vectors | D4: 108 nieuwe AV-rijen (totaal 195): Web +29, API +2, Internal network +14, External network (nieuw) +7, Active Directory +14, Cloud +11, Mobile +4, Wireless +4, Social engineering +5, Physical +4, Endpoint (nieuw) +7, AI / LLM (nieuw) +7.
A5: 0.10.0 | B5: 2026-10-09 | C5: Attack vectors | D5: Nieuwe scopes: External network (AV-EXT), Endpoint (AV-HOST) en AI / LLM (AV-AI) met mapping op OWASP LLM Top 10 2025 en MITRE ATLAS.
A6: 0.10.0 | B6: 2026-10-09 | C6: Bestaande rijen | D6: WSTG-kolom verfijnd van categorie (bv. WSTG-ATHZ) naar specifieke test-ID's (bv. WSTG-ATHZ-04); reflected/stored XSS verplaatst van WSTG-CLNT naar WSTG-INPV-01/02 conform WSTG.
A7: 0.10.0 | B7: 2026-10-09 | C7: Bestaande rijen | D7: MITRE ATT&CK aangevuld waar een verdedigbare mapping bestaat (o.a. SQLi/SSRF/XXE/SSTI -> T1190, file upload -> T1505.003, sessie -> T1539, JWT -> T1606, TLS -> T1557/T1040); AV-AD-08 (ACL abuse) gecorrigeerd naar T1098, T1484.001.
A8: 0.10.0 | B8: 2026-10-09 | C8: Bestaande rijen | D8: AV-AD-09 uitgebreid van ESC1-ESC8 naar ESC1-ESC16 (incl. ESC9/10 certificate mapping, ESC15 EKUwu, ESC16) met Certipy-verwijzing; AV-NET-02 uitgebreid met ADIDNS-wildcard-misbruik; AV-WEB-11 hernoemd naar "Path traversal / LFI / RFI"; AV-AD-01 remediation aangevuld met RC4-uitschakeling; AV-CLD-03 uitgebreid met snapshots/SAS-tokens; AV-WEB-18 CWE-1188 toegevoegd.
A9: 0.10.0 | B9: 2026-10-09 | C9: Bestaande rijen | D9: Related_IDs en Other_mapping (MASVS / OWASP Mobile Top 10 2024, CIS, Certipy) ingevuld; OWASP_API_2023 aangevuld voor AV-WEB-01/02/12 (IDOR, privesc, auth).
A10: 0.10.0 | B10: 2026-10-09 | C10: CVE-rijen | D10: 154 CVE-rijen (was 1). Rij CVE-2020-14008 vertaald naar NL, aangevuld (CVSS 7.2, build 14730, KEV-status, WSTG/CWE/MITRE) en categorie-typo "Known Vulnerabillity" gecorrigeerd naar "Known vulnerability".
A11: 0.10.0 | B11: 2026-10-09 | C11: CVE-rijen | D11: Selectiecriteria: in het wild misbruikt (CISA KEV) en/of structureel aangetroffen in pentests van NL-organisaties; per scope: Active Directory (11), Internal network (25), External network (47), Web application (38), Endpoint (10), Social engineering (5), Cloud (7), AI / LLM (11). 137 van de 154 CVE-rijen staan in de CISA KEV-catalogus. Dekking t/m KEV-toevoegingen van 2026-10-04 (o.a. CVE-2026-104286 FortiMail, CVE-2026-88771 NetScaler, CVE-2026-63030 WordPress, CVE-2026-33824 Windows IKEEXT).
A12: 0.10.0 | B12: 2026-10-09 | C12: CVE-rijen | D12: CVSS-score/-vector, KEV-datum en referenties automatisch overgenomen uit de officiele CVE-records (cvelistV5, CNA en CISA-ADP); temporal-metrics uit vectoren verwijderd. Uitzonderingen gedocumenteerd in Other_mapping (CVE-2020-1472 NVD 10.0 i.p.v. CNA 5.5; CVE-2020-14008 NVD 7.2; CVE-2013-4786 alleen CVSSv2).
... A14: 0.10.0 | B14: 2026-10-09 | C14: Aandachtspunten | D14: Controleer bij rapportage de actuele NVD-score en het leveranciersadvies; versienummers zijn samengevat. Severity_default is indicatief. Rijen met Last_updated 2026-10-09 zijn allemaal gereviewd in deze release.
A15: 0.9.1 | C15: Basis | D15: Oorspronkelijke knowledge base: 87 attack vectors (9 scopes) en 1 CVE-rij.

Sheet Overzicht
A1: Overzicht aantallen per scope en Severity_default (formules op tabblad attack-vectors-knowledge-base)
A3: Scope | B3: Info | C3: Low | D3: Medium | E3: High | F3: Critical | G3: Totaal | H3: waarvan CVE-rijen | I3: waarvan in KEV
A4: Web application | B4: =COUNTIFS('attack-vectors-knowledge-base'!$B:$B,$A4,'attack-vectors-knowledge-base'!$F:$F,B$3) -> 0 | C4: =COUNTIFS('attack-vectors-knowledge-base'!$B:$B,$A4,'attack-vectors-knowledge-base'!$F:$F,C$3) -> 8 | D4: =COUNTIFS('attack-vectors-knowledge-base'!$B:$B,$A4,'attack-vectors-knowledge-base'!$F:$F,D$3) -> 24 | E4: =COUNTIFS('attack-vectors-knowledge-base'!$B:$B,$A4,'attack-vectors-knowledge-base'!$F:$F,E$3) -> 22 | F4: =COUNTIFS('attack-vectors-knowledge-base'!$B:$B,$A4,'attack-vectors-knowledge-base'!$F:$F,F$3) -> 37 | G4: =SUM(B4:F4) -> 91 | H4: =COUNTIFS('attack-vectors-knowledge-base'!$B:$B,$A4,'attack-vectors-knowledge-base'!$D:$D,"Known vulnerability") -> 38 | I4: =COUNTIFS('attack-vectors-knowledge-base'!$B:$B,$A4,'attack-vectors-knowledge-base'!$Z:$Z,"Ja*") -> 36
A5: API | B5: =COUNTIFS('attack-vectors-knowledge-base'!$B:$B,$A5,'attack-vectors-knowledge-base'!$F:$F,B$3) -> 0 | C5: =COUNTIFS('attack-vectors-knowledge-base'!$B:$B,$A5,'attack-vectors-knowledge-base'!$F:$F,C$3) -> 0 | D5: =COUNTIFS('attack-vectors-knowledge-base'!$B:$B,$A5,'attack-vectors-knowledge-base'!$F:$F,D$3) -> 7 | E5: =COUNTIFS('attack-vectors-knowledge-base'!$B:$B,$A5,'attack-vectors-knowledge-base'!$F:$F,E$3) -> 5 | F5: =COUNTIFS('attack-vectors-knowledge-base'!$B:$B,$A5,'attack-vectors-knowledge-base'!$F:$F,F$3) -> 0 | G5: =SUM(B5:F5) -> 12 | H5: =COUNTIFS('attack-vectors-knowledge-base'!$B:$B,$A5,'attack-vectors-knowledge-base'!$D:$D,"Known vulnerability") -> 0 | I5: =COUNTIFS('attack-vectors-knowledge-base'!$B:$B,$A5,'attack-vectors-knowledge-base'!$Z:$Z,"Ja*") -> 0
A6: Internal network | B6: =COUNTIFS('attack-vectors-knowledge-base'!$B:$B,$A6,'attack-vectors-knowledge-base'!$F:$F,B$3) -> 1 | C6: =COUNTIFS('attack-vectors-knowledge-base'!$B:$B,$A6,'attack-vectors-knowledge-base'!$F:$F,C$3) -> 0 | D6: =COUNTIFS('attack-vectors-knowledge-base'!$B:$B,$A6,'attack-vectors-knowledge-base'!$F:$F,D$3) -> 9 | E6: =COUNTIFS('attack-vectors-knowledge-base'!$B:$B,$A6,'attack-vectors-knowledge-base'!$F:$F,E$3) -> 20 | F6: =COUNTIFS('attack-vectors-knowledge-base'!$B:$B,$A6,'attack-vectors-knowledge-base'!$F:$F,F$3) -> 18 | G6: =SUM(B6:F6) -> 48 | H6: =COUNTIFS('attack-vectors-knowledge-base'!$B:$B,$A6,'attack-vectors-knowledge-base'!$D:$D,"Known vulnerability") -> 25 | I6: =COUNTIFS('attack-vectors-knowledge-base'!$B:$B,$A6,'attack-vectors-knowledge-base'!$Z:$Z,"Ja*") -> 22
A7: External network | B7: =COUNTIFS('attack-vectors-knowledge-base'!$B:$B,$A7,'attack-vectors-knowledge-base'!$F:$F,B$3) -> 1 | C7: =COUNTIFS('attack-vectors-knowledge-base'!$B:$B,$A7,'attack-vectors-knowledge-base'!$F:$F,C$3) -> 1 | D7: =COUNTIFS('attack-vectors-knowledge-base'!$B:$B,$A7,'attack-vectors-knowledge-base'!$F:$F,D$3) -> 2 | E7: =COUNTIFS('attack-vectors-knowledge-base'!$B:$B,$A7,'attack-vectors-knowledge-base'!$F:$F,E$3) -> 6 | F7: =COUNTIFS('attack-vectors-knowledge-base'!$B:$B,$A7,'attack-vectors-knowledge-base'!$F:$F,F$3) -> 44 | G7: =SUM(B7:F7) -> 54 | H7: =COUNTIFS('attack-vectors-knowledge-base'!$B:$B,$A7,'attack-vectors-knowledge-base'!$D:$D,"Known vulnerability") -> 47 | I7: =COUNTIFS('attack-vectors-knowledge-base'!$B:$B,$A7,'attack-vectors-knowledge-base'!$Z:$Z,"Ja*") -> 47
A8: Active Directory | B8: =COUNTIFS('attack-vectors-knowledge-base'!$B:$B,$A8,'attack-vectors-knowledge-base'!$F:$F,B$3) -> 1 | C8: =COUNTIFS('attack-vectors-knowledge-base'!$B:$B,$A8,'attack-vectors-knowledge-base'!$F:$F,C$3) -> 0 | D8: =COUNTIFS('attack-vectors-knowledge-base'!$B:$B,$A8,'attack-vectors-knowledge-base'!$F:$F,D$3) -> 6 | E8: =COUNTIFS('attack-vectors-knowledge-base'!$B:$B,$A8,'attack-vectors-knowledge-base'!$F:$F,E$3) -> 27 | F8: =COUNTIFS('attack-vectors-knowledge-base'!$B:$B,$A8,'attack-vectors-knowledge-base'!$F:$F,F$3) -> 4 | G8: =SUM(B8:F8) -> 38 | H8: =COUNTIFS('attack-vectors-knowledge-base'!$B:$B,$A8,'attack-vectors-knowledge-base'!$D:$D,"Known vulnerability") -> 11 | I8: =COUNTIFS('attack-vectors-knowledge-base'!$B:$B,$A8,'attack-vectors-knowledge-base'!$Z:$Z,"Ja*") -> 8
A9: Cloud | B9: =COUNTIFS('attack-vectors-knowledge-base'!$B:$B,$A9,'attack-vectors-knowledge-base'!$F:$F,B$3) -> 1 | C9: =COUNTIFS('attack-vectors-knowledge-base'!$B:$B,$A9,'attack-vectors-knowledge-base'!$F:$F,C$3) -> 0 | D9: =COUNTIFS('attack-vectors-knowledge-base'!$B:$B,$A9,'attack-vectors-knowledge-base'!$F:$F,D$3) -> 3 | E9: =COUNTIFS('attack-vectors-knowledge-base'!$B:$B,$A9,'attack-vectors-knowledge-base'!$F:$F,E$3) -> 18 | F9: =COUNTIFS('attack-vectors-knowledge-base'!$B:$B,$A9,'attack-vectors-knowledge-base'!$F:$F,F$3) -> 4 | G9: =SUM(B9:F9) -> 26 | H9: =COUNTIFS('attack-vectors-knowledge-base'!$B:$B,$A9,'attack-vectors-knowledge-base'!$D:$D,"Known vulnerability") -> 7 | I9: =COUNTIFS('attack-vectors-knowledge-base'!$B:$B,$A9,'attack-vectors-knowledge-base'!$Z:$Z,"Ja*") -> 3
A10: Mobile | B10: =COUNTIFS('attack-vectors-knowledge-base'!$B:$B,$A10,'attack-vectors-knowledge-base'!$F:$F,B$3) -> 0 | C10: =COUNTIFS('attack-vectors-knowledge-base'!$B:$B,$A10,'attack-vectors-knowledge-base'!$F:$F,C$3) -> 1 | D10: =COUNTIFS('attack-vectors-knowledge-base'!$B:$B,$A10,'attack-vectors-knowledge-base'!$F:$F,D$3) -> 8 | E10: =COUNTIFS('attack-vectors-knowledge-base'!$B:$B,$A10,'attack-vectors-knowledge-base'!$F:$F,E$3) -> 2 | F10: =COUNTIFS('attack-vectors-knowledge-base'!$B:$B,$A10,'attack-vectors-knowledge-base'!$F:$F,F$3) -> 0 | G10: =SUM(B10:F10) -> 11 | H10: =COUNTIFS('attack-vectors-knowledge-base'!$B:$B,$A10,'attack-vectors-knowledge-base'!$D:$D,"Known vulnerability") -> 0 | I10: =COUNTIFS('attack-vectors-knowledge-base'!$B:$B,$A10,'attack-vectors-knowledge-base'!$Z:$Z,"Ja*") -> 0
A11: Wireless | B11: =COUNTIFS('attack-vectors-knowledge-base'!$B:$B,$A11,'attack-vectors-knowledge-base'!$F:$F,B$3) -> 0 | C11: =COUNTIFS('attack-vectors-knowledge-base'!$B:$B,$A11,'attack-vectors-knowledge-base'!$F:$F,C$3) -> 1 | D11: =COUNTIFS('attack-vectors-knowledge-base'!$B:$B,$A11,'attack-vectors-knowledge-base'!$F:$F,D$3) -> 2 | E11: =COUNTIFS('attack-vectors-knowledge-base'!$B:$B,$A11,'attack-vectors-knowledge-base'!$F:$F,E$3) -> 6 | F11: =COUNTIFS('attack-vectors-knowledge-base'!$B:$B,$A11,'attack-vectors-knowledge-base'!$F:$F,F$3) -> 0 | G11: =SUM(B11:F11) -> 9 | H11: =COUNTIFS('attack-vectors-knowledge-base'!$B:$B,$A11,'attack-vectors-knowledge-base'!$D:$D,"Known vulnerability") -> 0 | I11: =COUNTIFS('attack-vectors-knowledge-base'!$B:$B,$A11,'attack-vectors-knowledge-base'!$Z:$Z,"Ja*") -> 0
A12: Social engineering | B12: =COUNTIFS('attack-vectors-knowledge-base'!$B:$B,$A12,'attack-vectors-knowledge-base'!$F:$F,B$3) -> 0 | C12: =COUNTIFS('attack-vectors-knowledge-base'!$B:$B,$A12,'attack-vectors-knowledge-base'!$F:$F,C$3) -> 0 | D12: =COUNTIFS('attack-vectors-knowledge-base'!$B:$B,$A12,'attack-vectors-knowledge-base'!$F:$F,D$3) -> 4 | E12: =COUNTIFS('attack-vectors-knowledge-base'!$B:$B,$A12,'attack-vectors-knowledge-base'!$F:$F,E$3) -> 11 | F12: =COUNTIFS('attack-vectors-knowledge-base'!$B:$B,$A12,'attack-vectors-knowledge-base'!$F:$F,F$3) -> 1 | G12: =SUM(B12:F12) -> 16 | H12: =COUNTIFS('attack-vectors-knowledge-base'!$B:$B,$A12,'attack-vectors-knowledge-base'!$D:$D,"Known vulnerability") -> 5 | I12: =COUNTIFS('attack-vectors-knowledge-base'!$B:$B,$A12,'attack-vectors-knowledge-base'!$Z:$Z,"Ja*") -> 5
A13: Physical | B13: =COUNTIFS('attack-vectors-knowledge-base'!$B:$B,$A13,'attack-vectors-knowledge-base'!$F:$F,B$3) -> 0 | C13: =COUNTIFS('attack-vectors-knowledge-base'!$B:$B,$A13,'attack-vectors-knowledge-base'!$F:$F,C$3) -> 1 | D13: =COUNTIFS('attack-vectors-knowledge-base'!$B:$B,$A13,'attack-vectors-knowledge-base'!$F:$F,D$3) -> 7 | E13: =COUNTIFS('attack-vectors-knowledge-base'!$B:$B,$A13,'attack-vectors-knowledge-base'!$F:$F,E$3) -> 1 | F13: =COUNTIFS('attack-vectors-knowledge-base'!$B:$B,$A13,'attack-vectors-knowledge-base'!$F:$F,F$3) -> 0 | G13: =SUM(B13:F13) -> 9 | H13: =COUNTIFS('attack-vectors-knowledge-base'!$B:$B,$A13,'attack-vectors-knowledge-base'!$D:$D,"Known vulnerability") -> 0 | I13: =COUNTIFS('attack-vectors-knowledge-base'!$B:$B,$A13,'attack-vectors-knowledge-base'!$Z:$Z,"Ja*") -> 0
A14: Endpoint | B14: =COUNTIFS('attack-vectors-knowledge-base'!$B:$B,$A14,'attack-vectors-knowledge-base'!$F:$F,B$3) -> 0 | C14: =COUNTIFS('attack-vectors-knowledge-base'!$B:$B,$A14,'attack-vectors-knowledge-base'!$F:$F,C$3) -> 0 | D14: =COUNTIFS('attack-vectors-knowledge-base'!$B:$B,$A14,'attack-vectors-knowledge-base'!$F:$F,D$3) -> 0 | E14: =COUNTIFS('attack-vectors-knowledge-base'!$B:$B,$A14,'attack-vectors-knowledge-base'!$F:$F,E$3) -> 16 | F14: =COUNTIFS('attack-vectors-knowledge-base'!$B:$B,$A14,'attack-vectors-knowledge-base'!$F:$F,F$3) -> 1 | G14: =SUM(B14:F14) -> 17 | H14: =COUNTIFS('attack-vectors-knowledge-base'!$B:$B,$A14,'attack-vectors-knowledge-base'!$D:$D,"Known vulnerability") -> 10 | I14: =COUNTIFS('attack-vectors-knowledge-base'!$B:$B,$A14,'attack-vectors-knowledge-base'!$Z:$Z,"Ja*") -> 10
A15: AI / LLM | B15: =COUNTIFS('attack-vectors-knowledge-base'!$B:$B,$A15,'attack-vectors-knowledge-base'!$F:$F,B$3) -> 0 | C15: =COUNTIFS('attack-vectors-knowledge-base'!$B:$B,$A15,'attack-vectors-knowledge-base'!$F:$F,C$3) -> 0 | D15: =COUNTIFS('attack-vectors-knowledge-base'!$B:$B,$A15,'attack-vectors-knowledge-base'!$F:$F,D$3) -> 3 | E15: =COUNTIFS('attack-vectors-knowledge-base'!$B:$B,$A15,'attack-vectors-knowledge-base'!$F:$F,E$3) -> 6 | F15: =COUNTIFS('attack-vectors-knowledge-base'!$B:$B,$A15,'attack-vectors-knowledge-base'!$F:$F,F$3) -> 9 | G15: =SUM(B15:F15) -> 18 | H15: =COUNTIFS('attack-vectors-knowledge-base'!$B:$B,$A15,'attack-vectors-knowledge-base'!$D:$D,"Known vulnerability") -> 11 | I15: =COUNTIFS('attack-vectors-knowledge-base'!$B:$B,$A15,'attack-vectors-knowledge-base'!$Z:$Z,"Ja*") -> 6
A16: Totaal | B16: =SUM(B4:B15) -> 4 | C16: =SUM(C4:C15) -> 12 | D16: =SUM(D4:D15) -> 75 | E16: =SUM(E4:E15) -> 140 | F16: =SUM(F4:F15) -> 118 | G16: =SUM(G4:G15) -> 349 | H16: =SUM(H4:H15) -> 154 | I16: =SUM(I4:I15) -> 137
A18: Controle: aantal rijen met ID in hoofdtabel | B18: =COUNTA('attack-vectors-knowledge-base'!$A:$A)-1 -> 349
A19: Controle: aantal CVE-rijen (ID begint met CVE-) | B19: =SUMPRODUCT(--(LEFT('attack-vectors-knowledge-base'!$A$2:$A$2000,4)="CVE-")) -> 154
A20: Controle: aantal rijen in KEV | B20: =SUMPRODUCT(--(LEFT('attack-vectors-knowledge-base'!$Z$2:$Z$2000,2)="Ja")) -> 137
