Workbook

Sheet attack-vectors-knowledge-base
A1: ID | B1: Scope | C1: Vector | D1: Category | E1: Kill_chain_phase | F1: Severity_default | G1: Description | H1: Impact | I1: Test_approach | J1: Remediation | K1: Detection_note | L1: OWASP_Top10_2025 | M1: OWASP_API_2023 | N1: WSTG | O1: ASVS_5.0 | P1: MITRE_ATTACK | Q1: CWE | R1: PayloadsAllTheThings | S1: OSCP_plus | T1: CISSP_domain | U1: Evidence | V1: CVSS_score | W1: CVSS_vector | X1: Affected_versions | Y1: Fixed_in | Z1: CISA_KEV | AA1: Exploit_public | AB1: Related_IDs | AC1: Other_mapping | AD1: References | AE1: Last_updated
A2: AV-WEB-01 | B2: Web application | C2: Broken access control / IDOR | D2: Authorization | E2: Privilege escalation | F2: High | G2: Object references without a server-side authorization check allow access to other users' data. | H2: Unauthorized access to or manipulation of someone else's records. | I2: Swap object identifiers and roles and check whether authorization is enforced server-side (see WSTG-ATHZ). | J2: Enforce authorization centrally per object and per function; use indirect references. | K2: Log and alert on access to objects outside the user's scope. | L2: A01:2025 | M2: API1:2023 | N2: WSTG-ATHZ-04 | O2: V8 | P2: T1078 | Q2: CWE-639, CWE-284 | R2: Insecure Direct Object References | S2: Web attacks | T2: D5 | AB2: AV-API-01 | AD2: https://owasp.org/www-project-web-security-testing-guide/latest/4-Web_Application_Security_Testing/05-Authorization_Testing/04-Testing_for_Insecure_Direct_Object_References | AE2: 2026-10-09
A3: AV-WEB-02 | B3: Web application | C3: Vertical privilege escalation | D3: Authorization | E3: Privilege escalation | F3: High | G3: A lower-privileged user reaches functions or data intended for higher roles. | H3: Takeover of admin functionality or sensitive actions. | I3: Access admin endpoints with a user account and check role enforcement (WSTG-ATHZ). | J3: Deny-by-default, role check on every function, no reliance on hidden UI. | K3: Alert on admin actions by non-admin accounts. | L3: A01:2025 | M3: API5:2023 | N3: WSTG-ATHZ-02, WSTG-ATHZ-03 | O3: V8 | P3: T1068, T1078 | Q3: CWE-269 | R3: Privilege Escalation | S3: Web attacks | T3: D5 | AB3: AV-API-05, CVE-2025-29927, CVE-2023-22515 | AE3: 2026-10-09
A4: AV-WEB-03 | B4: Web application | C4: SQL injection | D4: Injection | E4: Execution | F4: High | G4: Untrusted input is interpreted as SQL, making queries manipulable. | H4: Reading, modifying or deleting database contents; sometimes code execution. | I4: Test input fields for injection via anomalous behavior and error messages; confirm with a review for parameterized queries (WSTG-INPV). | J4: Parameterized queries / prepared statements; least-privilege DB accounts. | K4: WAF and DB anomaly detection for unusual query patterns. | L4: A05:2025 | N4: WSTG-INPV-05 | O4: V1, V2 | P4: T1190 | Q4: CWE-89 | R4: SQL Injection | S4: Web attacks | T4: D8 | AB4: AV-WEB-36, CVE-2023-34362, CVE-2026-9082, CVE-2026-72898 | AE4: 2026-10-09
A5: AV-WEB-04 | B5: Web application | C5: Command injection | D5: Injection | E5: Execution | F5: Critical | G5: Input reaches an OS command interpreter and allows execution of system commands. | H5: Execution of commands on the host, potentially full compromise. | I5: Identify functions that invoke OS commands and check whether input is sanitized (WSTG-INPV). | J5: Avoid shell calls; use safe APIs and strict allowlists. | K5: Monitor for unexpected child processes of web processes. | L5: A05:2025 | N5: WSTG-INPV-12 | O5: V1 | P5: T1190, T1059 | Q5: CWE-78 | R5: Command Injection | S5: Web attacks | T5: D8 | AB5: AV-HOST-02, CVE-2024-4577, CVE-2014-6271, CVE-2024-3400 | AE5: 2026-10-09
A6: AV-WEB-05 | B6: Web application | C6: Reflected XSS | D6: Injection / client-side | E6: Execution | F6: Medium | G6: Unencoded input is reflected directly in the response and executed in the browser. | H6: Script execution in the victim's context; session theft, phishing. | I6: Check whether reflected input is encoded correctly for its context (WSTG-CLNT). | J6: Output encoding per context; Content Security Policy as an additional layer. | K6: Log CSP report endpoints and anomalous URL parameters. | L6: A05:2025 | N6: WSTG-INPV-01 | O6: V1, V3 | P6: T1059.007, T1539 | Q6: CWE-79 | R6: XSS Injection | S6: Web attacks | T6: D8 | AB6: AV-WEB-41, AV-WEB-42, AV-WEB-19 | AE6: 2026-10-09
A7: AV-WEB-06 | B7: Web application | C7: Stored XSS | D7: Injection / client-side | E7: Execution | F7: High | G7: Malicious input is stored and later displayed unencoded to other users. | H7: Wide reach; script runs for every visitor of the affected page. | I7: Submit marked input and check the encoding when it is displayed elsewhere (WSTG-CLNT). | J7: Output encoding and input sanitization; CSP. | K7: Monitor content integrity and CSP violations. | L7: A05:2025 | N7: WSTG-INPV-02 | O7: V1, V3 | P7: T1059.007, T1539 | Q7: CWE-79 | R7: XSS Injection | S7: Web attacks | T7: D8 | AB7: AV-WEB-41, AV-WEB-05 | AE7: 2026-10-09
A8: AV-WEB-07 | B8: Web application | C8: Server-side request forgery (SSRF) | D8: Access control | E8: Discovery | F8: High | G8: The server is induced to access internal or unintended destinations. | H8: Access to internal services, metadata endpoints and network reconnaissance. | I8: Check whether user-controlled URLs are validated server-side against an allowlist (WSTG-INPV). | J8: Allowlist for destinations; block internal ranges and metadata IPs. | K8: Egress filtering and alerting on internal calls from app servers. | L8: A01:2025 | N8: WSTG-INPV-19 | O8: V4 | P8: T1190 | Q8: CWE-918 | R8: Server Side Request Forgery | S8: Web attacks | T8: D8 | AB8: AV-API-07, AV-CLD-05, CVE-2021-26855, CVE-2026-64849 | AE8: 2026-10-09
A9: AV-WEB-08 | B9: Web application | C9: XML external entity (XXE) | D9: Injection | E9: Execution | F9: High | G9: An XML parser processes external entities and allows file or network access. | H9: Reading local files, SSRF and denial of service. | I9: Check whether XML parsers disable external entities and DTDs (WSTG-INPV). | J9: Disable DTD/external entity processing in the parser. | K9: Alert on outbound calls from XML-processing components. | L9: A05:2025 | N9: WSTG-INPV-07 | O9: V1 | P9: T1190 | Q9: CWE-611 | R9: XXE Injection | S9: Web attacks | T9: D8 | AB9: AV-WEB-31 | AE9: 2026-10-09
A10: AV-WEB-09 | B10: Web application | C10: Insecure deserialization | D10: Integrity | E10: Execution | F10: High | G10: Untrusted serialized data is processed without an integrity check. | H10: Object injection up to and including remote code execution. | I10: Identify deserialization points and check for integrity/type checks (WSTG-INPV). | J10: Avoid native deserialization of untrusted data; use signed formats. | K10: Monitor for deserialization errors and unexpected object types. | L10: A08:2025 | N10: WSTG-INPV (no specific test) | O10: V1 | P10: T1190 | Q10: CWE-502 | R10: Insecure Deserialization | S10: Web attacks | T10: D8 | AB10: CVE-2025-53770, CVE-2025-55182, CVE-2023-46604, CVE-2019-18935, CVE-2025-59287 | AE10: 2026-10-09
A11: AV-WEB-10 | B11: Web application | C11: Unrestricted file upload | D11: File handling | E11: Execution | F11: High | G11: Uploads are insufficiently validated for type, content and storage location. | H11: Placement of executable files; possible code execution. | I11: Check server-side validation of type/content and whether storage is outside the webroot (WSTG-BUSL/INPV). | J11: Validate content, rename files, store outside the webroot, block execution. | K11: Monitor upload directories for executable files. | L11: A05:2025 | N11: WSTG-BUSL-08, WSTG-BUSL-09 | O11: V5 | P11: T1190, T1505.003 | Q11: CWE-434 | R11: Upload Insecure Files | S11: Web attacks | T11: D8 | AB11: CVE-2025-31324, CVE-2020-14008, CVE-2021-21972 | AE11: 2026-10-09
A12: AV-WEB-11 | B12: Web application | C12: Path traversal / LFI / RFI | D12: Access control | E12: Discovery | F12: High | G12: Path manipulation gives access to files outside the intended directory. | H12: Reading sensitive files; sometimes inclusion and execution. | I12: Check whether file paths are normalized and restricted server-side (WSTG-ATHZ). | J12: Canonicalize paths, use allowlists, avoid user input in paths. | K12: Alert on traversal patterns in file requests. | L12: A01:2025 | N12: WSTG-ATHZ-01 | O12: V5 | P12: T1190, T1083 | Q12: CWE-22, CWE-98 | R12: Directory Traversal / File Inclusion | S12: Web attacks | T12: D8 | AB12: CVE-2021-41773, CVE-2021-43798, CVE-2018-13379, CVE-2019-19781 | AE12: 2026-10-09
A13: AV-WEB-12 | B13: Web application | C13: Authentication weaknesses | D13: Authentication | E13: Credential access | F13: High | G13: Weak login mechanisms allow brute force, credential stuffing or bypass. | H13: Account takeover and unauthorized access. | I13: Check lockout, rate limiting, MFA and reset flows (WSTG-ATHN). | J13: Strong MFA, rate limiting, secure reset flows, credential screening. | K13: Alert on login anomalies and spikes in failed logins. | L13: A07:2025 | M13: API2:2023 | N13: WSTG-ATHN-03, WSTG-ATHN-07, WSTG-ATHN-09 | O13: V6 | P13: T1110, T1078 | Q13: CWE-307, CWE-521 | R13: Account Takeover | S13: Web attacks | T13: D5 | AB13: AV-WEB-43, AV-WEB-44, AV-WEB-45, AV-WEB-46, AV-API-02 | AE13: 2026-10-09
A14: AV-WEB-13 | B14: Web application | C14: Session management flaws | D14: Session | E14: Credential access | F14: Medium | G14: Weak session tokens, fixation or missing invalidation undermine session security. | H14: Session hijacking and persistent unauthorized access. | I14: Check token entropy, rotation at login, and logout/timeout invalidation (WSTG-SESS). | J14: Secure cookie attributes, rotation after auth, correct invalidation. | K14: Detect concurrent use of sessions from multiple locations. | L14: A07:2025 | N14: WSTG-SESS-01, WSTG-SESS-03, WSTG-SESS-06, WSTG-SESS-07 | O14: V7 | P14: T1539, T1550.004 | Q14: CWE-384, CWE-613 | R14: Session Management | S14: Web attacks | T14: D5 | AB14: AV-WEB-47, AV-WEB-53, CVE-2023-4966 | AE14: 2026-10-09
A15: AV-WEB-14 | B15: Web application | C15: JWT / token weaknesses | D15: Session / tokens | E15: Credential access | F15: High | G15: Incorrect validation of self-contained tokens (e.g. alg confusion, weak keys). | H15: Forgery of identity and privileges. | I15: Check signature validation, algorithm allowlist and claim verification (WSTG-SESS). | J15: Validate signature and alg strictly; short lifetime; strong keys. | K15: Alert on tokens with an unexpected alg or issuer. | L15: A07:2025 | N15: WSTG-SESS-10 | O15: V9 | P15: T1606 | Q15: CWE-347 | R15: JSON Web Token | S15: Web attacks | T15: D5 | AB15: AV-WEB-30, CVE-2026-5430 | AE15: 2026-10-09
A16: AV-WEB-15 | B16: Web application | C16: Cross-site request forgery (CSRF) | D16: Client-side | E16: Execution | F16: Medium | G16: An authenticated user unknowingly performs a state-changing request. | H16: Unwanted actions on behalf of the victim. | I16: Check anti-CSRF tokens and SameSite cookie policy on state-changing endpoints (WSTG-SESS). | J16: Anti-CSRF tokens, SameSite cookies, re-authentication for sensitive actions. | K16: Detect state changes without the expected token/origin. | L16: A01:2025 | N16: WSTG-SESS-05 | O16: V3 | Q16: CWE-352 | R16: CSRF Injection | S16: Web attacks | T16: D8 | AB16: AV-WEB-33, AV-WEB-47 | AE16: 2026-10-09
A17: AV-WEB-16 | B17: Web application | C17: Server-side template injection (SSTI) | D17: Injection | E17: Execution | F17: High | G17: Input is evaluated by a template engine instead of being treated as data. | H17: Template evaluation up to and including code execution. | I17: Check whether user input stays outside the template context (WSTG-INPV). | J17: Treat input as data; use logic-less templates; sandbox. | K17: Monitor template errors and unexpected evaluations. | L17: A05:2025 | N17: WSTG-INPV-18 | O17: V1 | P17: T1190 | Q17: CWE-1336 | R17: Server Side Template Injection | S17: Web attacks | T17: D8 | AB17: AV-WEB-39, CVE-2023-22527, CVE-2026-75650 | AE17: 2026-10-09
A18: AV-WEB-17 | B18: Web application | C18: Open redirect | D18: Input validation | E18: Initial access | F18: Low | G18: Unvalidated redirect parameters send users to external destinations. | H18: Phishing and bypass of origin trust. | I18: Check whether redirect targets are validated against an allowlist (WSTG-CLNT). | J18: Allowlist of redirect targets; avoid user-controlled URLs. | K18: Log redirects to external domains. | L18: A01:2025 | N18: WSTG-CLNT-04 | O18: V2 | P18: T1566.002 | Q18: CWE-601 | R18: Open Redirect | S18: Web attacks | T18: D8 | AB18: AV-WEB-30 | AE18: 2026-10-09
A19: AV-WEB-18 | B19: Web application | C19: Security misconfiguration | D19: Configuration | E19: Reconnaissance | F19: Medium | G19: Default settings, unnecessary features or exposed management interfaces. | H19: Varies, from information leakage to direct compromise. | I19: Check hardening, default credentials and exposed interfaces (WSTG-CONF). | J19: Hardening baselines, remove defaults, minimize features. | K19: Config drift detection and periodic hardening scans. | L19: A02:2025 | N19: WSTG-CONF-02, WSTG-CONF-05 | O19: V13 | P19: T1592 | Q19: CWE-16, CWE-1188 | R19: Methodology and Resources | S19: Enumeration | T19: D3 | AB19: AV-WEB-48, AV-WEB-49, AV-EXT-07 | AE19: 2026-10-09
A20: AV-WEB-19 | B20: Web application | C20: Missing security headers | D20: Configuration | E20: Reconnaissance | F20: Low | G20: Missing headers (CSP, HSTS, X-Frame-Options) weaken browser defenses. | H20: Greater likelihood of XSS, clickjacking and downgrade. | I20: Check the presence and correctness of security headers (WSTG-CONF). | J20: Set CSP, HSTS, X-Content-Type-Options and frame-ancestors. | K20: Periodic header scans in CI. | L20: A02:2025 | N20: WSTG-CONF-07, WSTG-CONF-12 | O20: V3 | Q20: CWE-693 | R20: Methodology and Resources | S20: Enumeration | T20: D3 | AB20: AV-WEB-27, AV-WEB-47 | AE20: 2026-10-09
A21: AV-WEB-20 | B21: Web application | C21: Cryptographic failures / weak TLS | D21: Cryptography | E21: Credential access | F21: Medium | G21: Weak algorithms, outdated TLS or poor key management. | H21: Exposure or manipulation of sensitive data in transit or at rest. | I21: Check TLS config, algorithm choice and key management (WSTG-CRYP). | J21: Modern TLS, strong suites, correct key management and crypto agility. | K21: Monitor for outdated protocol versions and cipher downgrades. | L21: A04:2025 | N21: WSTG-CRYP-01, WSTG-CRYP-04 | O21: V11, V12 | P21: T1557, T1040 | Q21: CWE-327 | R21: Methodology and Resources | S21: Enumeration | T21: D3 | AB21: AV-NET-18, CVE-2014-0160 | AE21: 2026-10-09
A22: AV-WEB-21 | B22: Web application | C22: Sensitive data exposure | D22: Data protection | E22: Collection | F22: Medium | G22: Sensitive data is insufficiently protected or unnecessarily exposed. | H22: Data breach and privacy violation. | I22: Check data classification, encryption and minimization in responses (WSTG-ATHZ/CONF). | J22: Classify data, encrypt at rest/in transit, minimize fields. | K22: DLP and monitoring for unusual data egress. | L22: A04:2025 | N22: WSTG-CRYP-03, WSTG-INFO-05 | O22: V14 | P22: T1005, T1213 | Q22: CWE-200 | R22: Methodology and Resources | S22: Enumeration | T22: D2 | AB22: AV-WEB-48, AV-WEB-53 | AE22: 2026-10-09
A23: AV-WEB-22 | B23: Web application | C23: Business logic flaws | D23: Business logic | E23: Execution | F23: Medium | G23: Legitimate functionality is exploited in unintended ways (e.g. workflow bypass, race conditions). | H23: Fraud, bypass of limits and integrity damage. | I23: Model the intended workflows and test deviating sequences and concurrency (WSTG-BUSL). | J23: Server-side enforcement of workflow, atomic operations, limits. | K23: Alert on impossible or overly fast workflow transitions. | L23: A06:2025 | N23: WSTG-BUSL-01, WSTG-BUSL-06 | O23: V2 | Q23: CWE-840 | R23: Methodology and Resources | S23: Web attacks | T23: D8 | AB23: AV-WEB-34, AV-API-06 | AE23: 2026-10-09
A24: AV-WEB-23 | B24: Web application | C24: Vulnerable & outdated components | D24: Supply chain | E24: Initial access | F24: High | G24: Outdated libraries or frameworks with known vulnerabilities. | H24: Exploitation of known CVEs in dependencies. | I24: Inventory dependencies and compare versions against known advisories (WSTG-CONF). | J24: SBOM, dependency scanning, timely patching. | K24: Continuous SCA and version monitoring in the pipeline. | L24: A03:2025 | N24: WSTG-INFO-02, WSTG-INFO-08 | O24: V15 | P24: T1190 | Q24: CWE-1104 | R24: Methodology and Resources | S24: Enumeration | T24: D8 | AB24: CVE-2021-44228, CVE-2022-22965, CVE-2017-5638, AV-CLD-19, AV-NET-21 | AE24: 2026-10-09
A25: AV-WEB-24 | B25: Web application | C25: Improper error handling | D25: Error handling | E25: Reconnaissance | F25: Low | G25: Verbose errors leak details or the application fails open instead of closed. | H25: Information leakage and bypass of controls on exceptions. | I25: Force error conditions and assess leakage and fail-open behavior (WSTG-ERRH). | J25: Generic error pages, fail-closed design, structured logging. | K25: Monitor for stack traces in responses. | L25: A10:2025 | N25: WSTG-ERRH-01, WSTG-ERRH-02 | O25: V16 | Q25: CWE-209 | R25: Methodology and Resources | S25: Web attacks | T25: D8 | AB25: AV-WEB-48 | AE25: 2026-10-09
A26: AV-WEB-25 | B26: Web application | C26: HTTP request smuggling / desync | D26: Injection | E26: Execution | F26: High | G26: Front-end (proxy/load balancer) and back-end interpret Content-Length/Transfer-Encoding (or HTTP/2 downgrade) differently, allowing an attacker to smuggle a second request into the connection. | H26: Bypass of front-end security controls, hijacking of other users' requests, cache poisoning and sometimes account takeover. | I26: Test CL.TE, TE.CL and H2.CL desync with timing-based probes on the front-end; confirm only with non-destructive payloads and per the RoE (WSTG-INPV-15). | J26: Use end-to-end HTTP/2 or normalize ambiguous requests on the front-end; reject requests with both CL and TE; close back-end connections after every request; patch proxy/web server. | K26: Alert on 400/timeout spikes and on requests with conflicting CL/TE headers at the edge. | L26: A06:2025 | N26: WSTG-INPV-15 | O26: V4, V13 | P26: T1190 | Q26: CWE-444 | R26: Request Smuggling | S26: Web attacks | T26: D8 | AD26: https://portswigger.net/web-security/request-smuggling | AE26: 2026-10-09
A27: AV-WEB-26 | B27: Web application | C27: CORS misconfiguration | D27: Configuration | E27: Collection | F27: Medium | G27: Access-Control-Allow-Origin reflects arbitrary or null origins (often combined with Allow-Credentials: true), allowing a malicious site to read authenticated responses. | H27: Cross-origin theft of sensitive data and CSRF-like actions on behalf of the victim. | I27: Send requests with deviating Origin headers (arbitrary, null, subdomain variants) and check ACAO/ACAC in the response (WSTG-CLNT-07). | J27: Strict allowlist of origins; never reflect the Origin header with credentials; no wildcard on authenticated endpoints. | K27: Log and review Origin headers on authenticated endpoints; periodic header scan in CI. | L27: A01:2025 | M27: API8:2023 | N27: WSTG-CLNT-07 | O27: V3 | Q27: CWE-942 | R27: CORS Misconfiguration | S27: Web attacks | T27: D8 | AD27: https://portswigger.net/web-security/cors | AE27: 2026-10-09
A28: AV-WEB-27 | B28: Web application | C28: Clickjacking / UI redressing | D28: Client-side | E28: Execution | F28: Low | G28: Pages with state-changing functionality can be loaded in an (invisible) frame on an attacker's domain due to missing frame-ancestors/X-Frame-Options. | H28: User unintentionally performs actions (e.g. changing settings, confirming transactions). | I28: Check CSP frame-ancestors and X-Frame-Options on sensitive pages and create a framing PoC (WSTG-CLNT-09). | J28: Content-Security-Policy: frame-ancestors 'none' or an allowlist; X-Frame-Options as fallback; re-authentication for sensitive actions. | K28: Header scan in CI; CSP violation reporting. | L28: A02:2025 | N28: WSTG-CLNT-09 | O28: V3 | Q28: CWE-1021 | R28: Clickjacking | S28: Web attacks | T28: D8 | AB28: AV-WEB-19 | AD28: https://cheatsheetseries.owasp.org/cheatsheets/Clickjacking_Defense_Cheat_Sheet.html | AE28: 2026-10-09
A29: AV-WEB-28 | B29: Web application | C29: Subdomain takeover (dangling DNS) | D29: Configuration | E29: Initial access | F29: Medium | G29: A CNAME/A record points to a no-longer-claimed external service (cloud storage, SaaS, CDN), allowing an attacker to claim the destination and serve content under the trusted domain. | H29: Phishing under the organization's own domain, cookie theft for parent-domain cookies, bypass of CSP/CORS trust. | I29: Enumerate subdomains and check DNS records for references to unclaimed services (fingerprints per provider) (WSTG-CONF-10). | J29: Remove orphaned DNS records during decommissioning; inventory DNS periodically; claim resources before DNS is created. | K29: Periodic DNS inventory and monitoring for CNAMEs to external services without an active resource. | L29: A02:2025 | N29: WSTG-CONF-10 | O29: V13 | P29: T1584.001 | Q29: CWE-284 | R29: Methodology and Resources - Subdomains Enumeration | S29: Enumeration | T29: D4 | AB29: AV-EXT-04 | AD29: https://github.com/EdOverflow/can-i-take-over-xyz | AE29: 2026-10-09
A30: AV-WEB-29 | B30: Web application | C30: Host header injection / password reset poisoning | D30: Injection | E30: Credential access | F30: Medium | G30: The application uses the Host or X-Forwarded-Host header to build absolute URLs (e.g. in password reset emails), allowing an attacker to inject links to their own domain. | H30: Theft of reset tokens and account takeover; cache poisoning and SSRF-like routing. | I30: Manipulate Host/X-Forwarded-Host and check whether generated links, redirects or cache keys adopt the value (WSTG-INPV-17). | J30: Use a configured canonical hostname; validate Host against an allowlist; ignore X-Forwarded-Host unless from a trusted proxy. | K30: Alert on requests with unknown Host values at the edge. | L30: A05:2025 | N30: WSTG-INPV-17 | O30: V2, V4 | P30: T1566.002 | Q30: CWE-644, CWE-20 | R30: Methodology and Resources | S30: Web attacks | T30: D8 | AB30: AV-WEB-45 | AD30: https://portswigger.net/web-security/host-header | AE30: 2026-10-09
A31: AV-WEB-30 | B31: Web application | C31: OAuth 2.0 / OIDC misconfiguration | D31: Authentication | E31: Credential access | F31: High | G31: Weak redirect_uri validation, missing state/PKCE, implicit flow or overly broad scopes enable theft of authorization codes or access tokens. | H31: Account takeover via token theft or login CSRF; access to APIs on behalf of the victim. | I31: Test redirect_uri variants (path/subdomain/open redirect), absence of state/nonce/PKCE, token leakage via Referer and scope escalation (WSTG-ATHZ-05). | J31: Exact redirect_uri matching, authorization code flow with PKCE, mandatory state/nonce, short token lifetime, scope minimization. | K31: Alert on authorization requests with a deviating redirect_uri or unusual client/scopes. | L31: A07:2025 | M31: API2:2023 | N31: WSTG-ATHZ-05 | O31: V10 | P31: T1528, T1550.001 | Q31: CWE-601, CWE-287 | R31: OAuth Misconfiguration | S31: Web attacks | T31: D5 | AB31: AV-WEB-17, AV-CLD-10 | AD31: https://portswigger.net/web-security/oauth | AE31: 2026-10-09
A32: AV-WEB-31 | B32: Web application | C32: SAML / SSO implementation flaws | D32: Authentication | E32: Credential access | F32: High | G32: Incorrect validation of SAML responses (signature wrapping, missing/weak signature check, XXE in assertions, missing audience/recipient check) allows identity forgery. | H32: Impersonation of arbitrary users including administrators at the service provider. | I32: Manipulate SAML responses (remove/replace signature, XSW, attribute modification, replay) and check whether the SP rejects the assertion. | J32: Use a maintained SAML library, validate the signature on the assertion and response, check audience/recipient/NotOnOrAfter, disable DTD processing. | K32: Alert on SAML responses with signature errors or a deviating issuer/audience. | L32: A07:2025 | N32: WSTG-ATHN-04 | O32: V6, V9 | P32: T1606.002 | Q32: CWE-347, CWE-287 | R32: SAML Injection | S32: Web attacks | T32: D5 | AB32: CVE-2022-47966 | AD32: https://cheatsheetseries.owasp.org/cheatsheets/SAML_Security_Cheat_Sheet.html | AE32: 2026-10-09
A33: AV-WEB-32 | B33: Web application | C33: GraphQL-specific weaknesses | D33: Configuration | E33: Discovery | F33: Medium | G33: Introspection in production, missing authorization per resolver, batching/aliasing without limits and deep queries enable information leakage, brute force and DoS. | H33: Exposure of schema and data, bypass of rate limiting, resource exhaustion. | I33: Check introspection, per-field authorization, query depth/complexity limits and batching abuse (WSTG-APIT-01). | J33: Introspection off in production, authorization in the resolver layer, depth/complexity/cost limits, limit batching and aliasing. | K33: Monitor for introspection queries and unusually complex/large queries. | L33: A01:2025 | M33: API4:2023, API8:2023 | N33: WSTG-APIT-01 | O33: V4 | Q33: CWE-200, CWE-770 | R33: GraphQL Injection | S33: Web attacks | T33: D8 | AB33: AV-API-04 | AD33: https://cheatsheetseries.owasp.org/cheatsheets/GraphQL_Cheat_Sheet.html | AE33: 2026-10-09
A34: AV-WEB-33 | B34: Web application | C34: WebSocket weaknesses (CSWSH, missing auth) | D34: Session | E34: Execution | F34: Medium | G34: WebSocket handshakes without Origin validation or without (re-)authentication allow cross-site WebSocket hijacking and unauthorized messages; messages are often not validated. | H34: Reading and sending messages on behalf of the victim; injection via unprotected message processing. | I34: Test the handshake with a foreign Origin and without a session cookie; fuzz message content for injection (WSTG-CLNT-10). | J34: Validate Origin, use tokens in the handshake, apply the same authorization and input validation as on HTTP endpoints, use wss://. | K34: Log handshakes with an unknown Origin; monitor message volume per session. | L34: A01:2025 | N34: WSTG-CLNT-10 | O34: V3, V4 | Q34: CWE-1385, CWE-346 | R34: Web Sockets | S34: Web attacks | T34: D8 | AB34: AV-WEB-15 | AD34: https://portswigger.net/web-security/websockets | AE34: 2026-10-09
A35: AV-WEB-34 | B35: Web application | C35: Race conditions / TOCTOU | D35: Business logic | E35: Execution | F35: Medium | G35: Concurrent requests on non-atomic operations (vouchers, balance, limits, OTP attempts, registration) allow limits to be exceeded or checks to be bypassed. | H35: Financial fraud, double payout, bypass of rate limits and one-time actions. | I35: Send parallel requests (single-packet/last-byte-sync) to limit-bound functions and compare the final state with the expected limit (WSTG-BUSL-05). | J35: Atomic database operations/locks, idempotency keys, server-side state machine, unique constraints. | K35: Alert on multiple successful transactions within milliseconds for the same entity. | L35: A06:2025 | M35: API6:2023 | N35: WSTG-BUSL-05 | O35: V2 | Q35: CWE-362, CWE-367 | R35: Race Condition | S35: Web attacks | T35: D8 | AB35: AV-WEB-22 | AD35: https://portswigger.net/web-security/race-conditions | AE35: 2026-10-09
A36: AV-WEB-35 | B36: Web application | C36: Web cache poisoning / cache deception | D36: Configuration | E36: Execution | F36: Medium | G36: Unkeyed input (headers, parameters, path normalization) influences cached responses, or sensitive personal responses are cached under a static-looking path. | H36: Spread of XSS/redirects to all visitors, or exposure of personal data via the cache. | I36: Identify cache behavior (headers, keys) and test unkeyed inputs and path confusion (/account/x.css) for cacheability. | J36: Cache only explicitly static content, normalize path/parameters consistently on CDN and origin, set Cache-Control: no-store on personal responses. | K36: Monitor cache hit ratios and anomalous cache keys; alert on cached responses with Set-Cookie. | L36: A06:2025 | N36: WSTG-CONF-13 | O36: V3, V13 | Q36: CWE-444, CWE-524 | R36: Web Cache Deception | S36: Web attacks | T36: D8 | AB36: AV-WEB-25 | AD36: https://portswigger.net/web-security/web-cache-poisoning | AE36: 2026-10-09
A37: AV-WEB-36 | B37: Web application | C37: NoSQL injection | D37: Injection | E37: Execution | F37: High | G37: Input is included unfiltered in NoSQL queries (MongoDB operators such as $ne/$regex/$where, JSON objects). | H37: Authentication bypass, reading of collections, sometimes server-side JavaScript execution. | I37: Inject operator objects and JSON type changes into parameters/bodies and observe behavioral deviations (WSTG-INPV-05). | J37: Strict schema/type validation, forbid operator keys in input, use parameterized query builders, disable server-side JS. | K37: Alert on query operators in request bodies and on anomalous query patterns in the database. | L37: A05:2025 | N37: WSTG-INPV-05 | O37: V1 | P37: T1190 | Q37: CWE-943 | R37: NoSQL Injection | S37: Web attacks | T37: D8 | AB37: AV-WEB-03 | AD37: https://cheatsheetseries.owasp.org/cheatsheets/Injection_Prevention_Cheat_Sheet.html | AE37: 2026-10-09
A38: AV-WEB-37 | B38: Web application | C38: LDAP / XPath injection | D38: Injection | E38: Execution | F38: High | G38: Input is included without escaping in LDAP filters or XPath expressions (e.g. login forms against AD or XML datastores). | H38: Authentication bypass, enumeration of directory objects and reading of XML data. | I38: Inject filter metacharacters (*, (, ), |, &) and XPath booleans and check for deviating results (WSTG-INPV-06, WSTG-INPV-09). | J38: Escape per context with a library, use allowlists for input, bind with least-privilege service accounts. | K38: Alert on LDAP queries with unusual filters from the application. | L38: A05:2025 | N38: WSTG-INPV-06, WSTG-INPV-09 | O38: V1 | P38: T1190 | Q38: CWE-90, CWE-643 | R38: LDAP Injection | S38: Web attacks | T38: D8 | AD38: https://cheatsheetseries.owasp.org/cheatsheets/LDAP_Injection_Prevention_Cheat_Sheet.html | AE38: 2026-10-09
A39: AV-WEB-38 | B39: Web application | C39: CRLF / HTTP header / e-mail header injection | D39: Injection | E39: Execution | F39: Medium | G39: Line breaks in input are not filtered when building HTTP headers, log lines or email headers (SMTP). | H39: Response splitting, cookie injection, log pollution, spam/phishing via the organization's own mail server. | I39: Inject %0d%0a into parameters that end up in headers, redirects or mail fields and check the output (WSTG-INPV-15, WSTG-INPV-10). | J39: Strip or encode CR/LF, use framework APIs for headers and mail, validate email fields strictly. | K39: Monitor for unexpected extra headers or anomalous mail volumes from the application. | L39: A05:2025 | N39: WSTG-INPV-15, WSTG-INPV-10 | O39: V1 | Q39: CWE-113, CWE-93 | R39: CRLF Injection | S39: Web attacks | T39: D8 | AD39: https://owasp.org/www-community/vulnerabilities/CRLF_Injection | AE39: 2026-10-09
A40: AV-WEB-39 | B40: Web application | C40: Code injection (eval) / expression language injection | D40: Injection | E40: Execution | F40: Critical | G40: Input is evaluated by an interpreter or expression language (eval(), OGNL, SpEL, EL, Jinja expressions outside templates). | H40: Direct code execution on the server; full compromise. | I40: Inject arithmetic and language-specific expressions into suspicious parameters and check whether they are evaluated (WSTG-INPV-11). | J40: Avoid dynamic evaluation of input; use safe parsers; sandbox and least privilege. | K40: Monitor for unexpected child processes and for expression syntax in requests. | L40: A05:2025 | N40: WSTG-INPV-11 | O40: V1 | P40: T1190, T1059 | Q40: CWE-94, CWE-917 | R40: Methodology and Resources | S40: Web attacks | T40: D8 | AB40: AV-WEB-16, CVE-2022-26134, CVE-2017-5638 | AD40: https://owasp.org/www-community/attacks/Code_Injection | AE40: 2026-10-09
A41: AV-WEB-40 | B41: Web application | C41: Prototype pollution | D41: Injection | E41: Execution | F41: Medium | G41: Unsafe merge/clone of user input in JavaScript (client- or server-side) allows setting __proto__/constructor properties that affect all objects. | H41: Client-side XSS via gadgets, server-side logic bypass up to and including RCE in Node.js. | I41: Inject __proto__[x]=y via query/JSON and check whether properties appear on empty objects; look for gadgets (WSTG-CLNT-01). | J41: Use Object.create(null)/Map, freeze prototypes, validate keys, update vulnerable libraries. | K41: SCA for known vulnerable libraries; alert on __proto__/constructor in request bodies. | L41: A05:2025 | N41: WSTG-CLNT-01 | O41: V1, V15 | Q41: CWE-1321 | R41: Prototype Pollution | S41: Web attacks | T41: D8 | AB41: AV-WEB-23 | AD41: https://portswigger.net/web-security/prototype-pollution | AE41: 2026-10-09
A42: AV-WEB-41 | B42: Web application | C42: DOM-based XSS | D42: Injection / client-side | E42: Execution | F42: Medium | G42: Client-side JavaScript writes untrusted sources (location, postMessage, storage) to the DOM via dangerous sinks (innerHTML, eval, document.write). | H42: Script execution in the victim's browser without server-side reflection; often invisible to a WAF. | I42: Analyze sources and sinks in the client-side code (DOM Invader/manually) and confirm with a PoC payload (WSTG-CLNT-01). | J42: Use safe DOM APIs (textContent), sanitize with DOMPurify, Trusted Types and a strict CSP. | K42: CSP violation reporting; client-side telemetry on errors. | L42: A05:2025 | N42: WSTG-CLNT-01 | O42: V1, V3 | P42: T1059.007 | Q42: CWE-79 | R42: XSS Injection | S42: Web attacks | T42: D8 | AB42: AV-WEB-05, AV-WEB-06 | AD42: https://cheatsheetseries.owasp.org/cheatsheets/DOM_based_XSS_Prevention_Cheat_Sheet.html | AE42: 2026-10-09
A43: AV-WEB-42 | B43: Web application | C43: HTML injection / content spoofing | D43: Injection / client-side | E43: Execution | F43: Low | G43: Input is rendered as HTML without enabling script execution (e.g. due to CSP or filtering), but does allow forged content, forms and links. | H43: Phishing within the trusted site, defacement, theft of input via injected forms. | I43: Inject benign HTML elements (h1, a, form) and check the rendering (WSTG-CLNT-03). | J43: Context-correct output encoding; sanitize HTML with an allowlist when rich text is needed. | K43: Content integrity monitoring on user-generated pages. | L43: A05:2025 | N43: WSTG-CLNT-03 | O43: V1 | Q43: CWE-80 | R43: XSS Injection | S43: Web attacks | T43: D8 | AB43: AV-WEB-05 | AD43: https://owasp.org/www-project-web-security-testing-guide/latest/4-Web_Application_Security_Testing/11-Client-side_Testing/03-Testing_for_HTML_Injection | AE43: 2026-10-09
A44: AV-WEB-43 | B44: Web application | C44: Username / account enumeration | D44: Authentication | E44: Reconnaissance | F44: Low | G44: Login, registration or reset functions respond differently (message, status code, timing) for existing and non-existing accounts. | H44: Compilation of valid user lists for password spraying and phishing. | I44: Compare responses and response times for known and unknown usernames on all auth-related endpoints (WSTG-IDNT-04). | J44: Generic error messages, constant response times, rate limiting and CAPTCHA on enumeration-sensitive functions. | K44: Alert on many different usernames from a single source within a short time. | L44: A07:2025 | M44: API2:2023 | N44: WSTG-IDNT-04 | O44: V6 | P44: T1589.002, T1087 | Q44: CWE-204, CWE-203 | R44: Account Takeover | S44: Enumeration | T44: D5 | AB44: AV-NET-06, AV-WEB-12 | AD44: https://owasp.org/www-project-web-security-testing-guide/latest/4-Web_Application_Security_Testing/03-Identity_Management_Testing/04-Testing_for_Account_Enumeration_and_Guessable_User_Account | AE44: 2026-10-09
A45: AV-WEB-44 | B45: Web application | C45: Weak password policy | D45: Authentication | E45: Credential access | F45: Medium | G45: Short or simple passwords are accepted, no screening against leaked passwords, no restriction on reuse. | H45: Successful brute force, spraying and credential stuffing. | I45: Try weak passwords at registration/change and check length, complexity and breach checks (WSTG-ATHN-07). | J45: Minimum 12-14 characters, screening against breach lists (NIST SP 800-63B), no forced periodic rotation without cause, MFA. | K45: Periodic audit of password hashes (offline, with permission) and monitoring of spraying. | L45: A07:2025 | N45: WSTG-ATHN-07 | O45: V6 | P45: T1110 | Q45: CWE-521 | R45: Account Takeover | S45: Password attacks | T45: D5 | AB45: AV-AD-19, AV-WEB-12 | AC45: NIST SP 800-63B | AD45: https://cheatsheetseries.owasp.org/cheatsheets/Authentication_Cheat_Sheet.html | AE45: 2026-10-09
A46: AV-WEB-45 | B46: Web application | C46: Insecure password reset / recovery flow | D46: Authentication | E46: Credential access | F46: High | G46: Reset tokens are predictable, not bound to the user, non-expiring, leak via the Referer/Host header or are not invalidated after use; security questions are guessable. | H46: Account takeover without knowledge of the current password. | I46: Analyze token entropy and lifetime, reuse, binding to the account, Host header poisoning and the logic of the flow (WSTG-ATHN-09). | J46: Cryptographically random, short-lived one-time tokens bound to the account; invalidation after use; notification; no security questions. | K46: Alert on many reset requests per account or source. | L46: A07:2025 | N46: WSTG-ATHN-09 | O46: V6 | P46: T1098 | Q46: CWE-640 | R46: Account Takeover | S46: Web attacks | T46: D5 | AB46: AV-WEB-29, CVE-2023-7028 | AD46: https://cheatsheetseries.owasp.org/cheatsheets/Forgot_Password_Cheat_Sheet.html | AE46: 2026-10-09
A47: AV-WEB-46 | B47: Web application | C47: MFA bypass / weak MFA implementation | D47: Authentication | E47: Credential access | F47: High | G47: OTP codes can be guessed (no rate limiting), the MFA step can be skipped (directly to post-auth endpoints), response manipulation results in approval, or MFA is missing on alternative channels (API, legacy). | H47: Bypass of the second factor and account takeover with only a password. | I47: Test brute force on OTP, step skipping, response tampering, reusable codes and MFA coverage of all login channels (WSTG-ATHN-11). | J47: Server-side state machine for the auth flow, rate limiting and lockout on OTP, one-time codes, MFA on all channels, phishing-resistant MFA (FIDO2) where possible. | K47: Alert on many OTP attempts and on sessions that do not complete the MFA step. | L47: A07:2025 | M47: API2:2023 | N47: WSTG-ATHN-11 | O47: V6 | P47: T1621, T1111 | Q47: CWE-287, CWE-307 | R47: Account Takeover | S47: Web attacks | T47: D5 | AB47: AV-SE-06, AV-SE-07, AV-CLD-09 | AD47: https://cheatsheetseries.owasp.org/cheatsheets/Multifactor_Authentication_Cheat_Sheet.html | AE47: 2026-10-09
A48: AV-WEB-47 | B48: Web application | C48: Insecure cookie attributes | D48: Session | E48: Credential access | F48: Low | G48: Session cookies lack Secure, HttpOnly or SameSite, have an overly broad Domain/Path or too long a lifetime. | H48: Greater impact of XSS and network interception; CSRF risk; session theft. | I48: Inspect Set-Cookie headers of all session and auth cookies for attributes and scope (WSTG-SESS-02). | J48: Secure; HttpOnly; SameSite=Lax/Strict; __Host- prefix; minimal lifetime and scope. | K48: Header scan in CI. | L48: A02:2025 | N48: WSTG-SESS-02 | O48: V7 | P48: T1539 | Q48: CWE-1004, CWE-614, CWE-1275 | R48: Session Management | S48: Web attacks | T48: D5 | AB48: AV-WEB-13 | AD48: https://cheatsheetseries.owasp.org/cheatsheets/Session_Management_Cheat_Sheet.html | AE48: 2026-10-09
A49: AV-WEB-48 | B49: Web application | C49: Information disclosure (source maps, backups, .git, directory listing, banners) | D49: Configuration | E49: Reconnaissance | F49: Low | G49: Exposed .git/.svn directories, backup and config files, source maps, directory listing, Swagger/actuator endpoints and detailed version banners leak implementation details or secrets. | H49: Accelerated exploitation, leakage of credentials/API keys, source code analysis by attackers. | I49: Fuzz for known paths (.git/HEAD, .env, *.bak, /actuator, /swagger), check listing and banners (WSTG-INFO-02, WSTG-CONF-04, WSTG-CONF-05). | J49: Remove/block development artifacts and backups from the webroot, disable listing, minimize banners, protect management endpoints. | K49: Alert on requests for .git/.env/backup patterns; periodic content discovery scan. | L49: A02:2025 | M49: API9:2023 | N49: WSTG-INFO-02, WSTG-CONF-04, WSTG-CONF-05 | O49: V13, V14 | P49: T1592, T1552.001 | Q49: CWE-538, CWE-548, CWE-200 | R49: Insecure Source Code Management | S49: Enumeration | T49: D8 | AB49: AV-WEB-18, AV-WEB-24 | AD49: https://owasp.org/www-project-web-security-testing-guide/latest/4-Web_Application_Security_Testing/02-Configuration_and_Deployment_Management_Testing/04-Review_Old_Backup_and_Unreferenced_Files_for_Sensitive_Information | AE49: 2026-10-09
A50: AV-WEB-49 | B50: Web application | C50: Dangerous HTTP methods / verb tampering | D50: Configuration | E50: Execution | F50: Medium | G50: PUT/DELETE/TRACE/WebDAV are enabled or authorization is only enforced on specific methods, so that a different method bypasses the check. | H50: Uploading/deleting files, authorization bypass, cross-site tracing. | I50: Enumerate allowed methods (OPTIONS) and repeat authorized requests with alternative methods/overrides (WSTG-CONF-06, WSTG-INPV-03). | J50: Restrict methods to what is needed, enforce authorization independently of the method, disable TRACE/WebDAV, block X-HTTP-Method-Override. | K50: Alert on unusual methods to application endpoints. | L50: A02:2025 | N50: WSTG-CONF-06, WSTG-INPV-03 | O50: V13 | P50: T1190 | Q50: CWE-650, CWE-749 | R50: Methodology and Resources | S50: Web attacks | T50: D8 | AB50: AV-WEB-02, CVE-2025-24813 | AD50: https://owasp.org/www-project-web-security-testing-guide/latest/4-Web_Application_Security_Testing/02-Configuration_and_Deployment_Management_Testing/06-Test_HTTP_Methods | AE50: 2026-10-09
A51: AV-WEB-50 | B51: Web application | C51: Insufficient logging & alerting (application) | D51: Detection | E51: Defense evasion | F51: Medium | G51: Security-relevant events (logins, failed authorization, input validation errors, admin actions) are not logged, logged incompletely or logged without context and there are no alerts. | H51: Attacks and abuse remain unnoticed; forensic investigation is limited. | I51: Perform recognizable actions during the test (failed logins, IDOR attempts, injection) and verify with the client whether these are visible in logging and alerting. | J51: Log auth, authorization and validation events in a structured way with correlation IDs, centralize in a SIEM, define alerts and retention periods; no sensitive data in logs. | K51: Measure coverage through purple-team-style verification of test actions in the SIEM. | L51: A09:2025 | N51: WSTG-CONF (no specific test) | O51: V16 | P51: T1562.008 | Q51: CWE-778, CWE-223 | R51: Methodology and Resources | T51: D7 | AB51: AV-CLD-08 | AD51: https://cheatsheetseries.owasp.org/cheatsheets/Logging_Cheat_Sheet.html | AE51: 2026-10-09
A52: AV-WEB-51 | B52: Web application | C52: Missing integrity controls (SRI, unsigned updates, third-party scripts) | D52: Integrity | E52: Initial access | F52: Medium | G52: External scripts/CSS are loaded without Subresource Integrity, auto-update or plugin mechanisms do not verify signatures, and CI/CD artifacts are not signed. | H52: Supply chain compromise via CDN/third party (e.g. Magecart-like skimming) or via manipulated updates. | I52: Inventory external resources and check SRI hashes, CSP and signature verification of update/plugin mechanisms. | J52: SRI and strict CSP for external resources, self-hosting of critical scripts, signed updates/artifacts and verification at installation. | K52: Monitor changes in third-party scripts; CSP reporting on unknown script sources. | L52: A08:2025, A03:2025 | N52: WSTG-CLNT-06 | O52: V3, V15 | P52: T1195.001, T1195.002 | Q52: CWE-353, CWE-494, CWE-829 | R52: Methodology and Resources | T52: D8 | AB52: AV-WEB-23, AV-CLD-19 | AD52: https://cheatsheetseries.owasp.org/cheatsheets/Third_Party_Javascript_Management_Cheat_Sheet.html | AE52: 2026-10-09
A53: AV-WEB-52 | B53: Web application | C53: postMessage / JSONP / cross-origin messaging weaknesses | D53: Client-side | E53: Collection | F53: Medium | G53: window.postMessage listeners do not validate the origin or process data insecurely; JSONP endpoints or cross-site script inclusion leak data to third parties. | H53: Cross-origin leakage of tokens/data and DOM XSS via message processing. | I53: Inventory message listeners and JSONP endpoints in the client code and test origin validation and sink usage (WSTG-CLNT-11, WSTG-CLNT-13). | J53: Validate event.origin against an allowlist, treat message data as untrusted, replace JSONP with CORS with an allowlist. | K53: Client-side telemetry; code review in CI for insecure listeners. | L53: A01:2025 | N53: WSTG-CLNT-11, WSTG-CLNT-13 | O53: V3 | Q53: CWE-346, CWE-79 | R53: XSS Injection | S53: Web attacks | T53: D8 | AB53: AV-WEB-26, AV-WEB-41 | AD53: https://portswigger.net/web-security/dom-based/controlling-the-web-message-source | AE53: 2026-10-09
A54: AV-WEB-53 | B54: Web application | C54: Sensitive data in client-side storage | D54: Data protection | E54: Credential access | F54: Medium | G54: Access/refresh tokens, PII or secrets are stored in localStorage/sessionStorage/IndexedDB, so that any XSS can read them and they remain persistently on the device. | H54: Token theft and account takeover in case of XSS or local access. | I54: Inspect browser storage after logging in and assess the sensitivity and lifetime of stored values (WSTG-CLNT-12). | J54: Store session tokens in HttpOnly cookies (with SameSite), minimize client-side storage, short token lifetime and refresh rotation. | K54: Not detectable server-side; audit during code review. | L54: A04:2025 | N54: WSTG-CLNT-12 | O54: V7, V14 | P54: T1539, T1528 | Q54: CWE-922, CWE-312 | R54: Methodology and Resources | S54: Web attacks | T54: D2 | AB54: AV-WEB-14, AV-WEB-47 | AD54: https://cheatsheetseries.owasp.org/cheatsheets/HTML5_Security_Cheat_Sheet.html | AE54: 2026-10-09
A55: AV-API-01 | B55: API | C55: Broken object level authorization (BOLA) | D55: Authorization | E55: Privilege escalation | F55: High | G55: Endpoints with object IDs without an authorization check give access to other users' objects. | H55: Unauthorized access to data of other users. | I55: Swap object IDs between accounts and check server-side authorization (WSTG-ATHZ). | J55: Authorization check on every object per request; unpredictable IDs. | K55: Alert on access to object IDs outside the scope of the token. | L55: A01:2025 | M55: API1:2023 | N55: WSTG-ATHZ-04 | O55: V8 | P55: T1078 | Q55: CWE-639 | R55: Insecure Direct Object References | S55: Web attacks | T55: D5 | AB55: AV-WEB-01 | AE55: 2026-10-09
A56: AV-API-02 | B56: API | C56: Broken authentication | D56: Authentication | E56: Credential access | F56: High | G56: Weak or incorrectly implemented authentication on API endpoints. | H56: Token compromise and impersonation. | I56: Check token issuance, validation and endpoint coverage (WSTG-ATHN). | J56: Strong authentication, correct token validation, MFA where appropriate. | K56: Monitor for authentication anomalies and token abuse. | L56: A07:2025 | M56: API2:2023 | N56: WSTG-ATHN-04, WSTG-ATHN-10 | O56: V6 | P56: T1078 | Q56: CWE-287 | R56: Account Takeover | S56: Web attacks | T56: D5 | AB56: AV-WEB-12, AV-WEB-14, AV-API-12 | AE56: 2026-10-09
A57: AV-API-03 | B57: API | C57: Broken object property level authorization | D57: Authorization | E57: Collection | F57: Medium | G57: Insufficient authorization at property level (excessive data exposure / mass assignment). | H57: Reading or overwriting of disallowed fields. | I57: Check whether response and request fields are restricted per role (WSTG-ATHZ). | J57: Explicit allowlist of fields for reading and writing. | K57: Monitor for write actions to sensitive properties. | L57: A01:2025 | M57: API3:2023 | N57: WSTG-INPV-20 | O57: V8 | Q57: CWE-915 | R57: Mass Assignment | S57: Web attacks | T57: D5 | AB57: AV-API-11 | AE57: 2026-10-09
A58: AV-API-04 | B58: API | C58: Unrestricted resource consumption | D58: Availability | E58: Impact | F58: Medium | G58: Missing limits on requests or resources. | H58: Denial of service and increased costs. | I58: Check rate limiting, pagination and resource quotas (WSTG-BUSL). | J58: Rate limiting, quotas, payload and timeout limits. | K58: Alert on consumption spikes per client/token. | L58: A06:2025 | M58: API4:2023 | N58: WSTG-BUSL-05 | O58: V2 | P58: T1499 | Q58: CWE-770 | R58: Methodology and Resources | S58: Web attacks | T58: D8 | AB58: AV-WEB-32, AV-AI-06 | AE58: 2026-10-09
A59: AV-API-05 | B59: API | C59: Broken function level authorization | D59: Authorization | E59: Privilege escalation | F59: High | G59: Functions without a role check are reachable by lower roles. | H59: Access to administrative or privileged functions. | I59: Access functions with different roles and check enforcement (WSTG-ATHZ). | J59: Deny-by-default per function; central authorization layer. | K59: Alert on privileged function calls by low roles. | L59: A01:2025 | M59: API5:2023 | N59: WSTG-ATHZ-02, WSTG-ATHZ-03 | O59: V8 | Q59: CWE-285 | R59: Privilege Escalation | S59: Web attacks | T59: D5 | AB59: AV-WEB-02 | AE59: 2026-10-09
A60: AV-API-06 | B60: API | C60: Unrestricted access to sensitive business flows | D60: Business logic | E60: Impact | F60: Medium | G60: Sensitive business flows without abuse protection (e.g. bulk purchasing, spam). | H60: Automated abuse causing business damage. | I60: Identify sensitive flows and test anti-automation measures (WSTG-BUSL). | J60: Detect automation, add friction, limit flows. | K60: Behavioral analysis of flow usage. | L60: A06:2025 | M60: API6:2023 | N60: WSTG-BUSL-07 | O60: V2 | Q60: CWE-840 | R60: Methodology and Resources | S60: Web attacks | T60: D8 | AB60: AV-WEB-22, AV-WEB-34 | AE60: 2026-10-09
A61: AV-API-07 | B61: API | C61: Server-side request forgery (API) | D61: Access control | E61: Discovery | F61: High | G61: API fetches unintended destinations based on user input. | H61: Internal network access and metadata theft. | I61: Check server-side validation of user-controlled URLs (WSTG-INPV). | J61: Allowlist destinations; block internal ranges. | K61: Egress filtering and alerting on internal calls. | L61: A01:2025 | M61: API7:2023 | N61: WSTG-INPV-19 | O61: V4 | P61: T1190 | Q61: CWE-918 | R61: Server Side Request Forgery | S61: Web attacks | T61: D8 | AB61: AV-WEB-07, AV-CLD-05 | AE61: 2026-10-09
A62: AV-API-08 | B62: API | C62: Security misconfiguration (API) | D62: Configuration | E62: Reconnaissance | F62: Medium | G62: Insecure defaults, CORS errors or missing hardening at API level. | H62: Varied exposure and access. | I62: Check CORS, methods, headers and error handling (WSTG-CONF). | J62: Hardening baseline, strict CORS policy, minimize methods. | K62: Config scans and CORS monitoring. | L62: A02:2025 | M62: API8:2023 | N62: WSTG-CONF-02, WSTG-CLNT-07 | O62: V13 | Q62: CWE-16 | R62: Methodology and Resources | S62: Enumeration | T62: D3 | AB62: AV-WEB-26, AV-WEB-18 | AE62: 2026-10-09
A63: AV-API-09 | B63: API | C63: Improper inventory management | D63: Configuration | E63: Reconnaissance | F63: Medium | G63: Unknown, outdated or undocumented API versions and endpoints. | H63: Attack surface via shadow/legacy endpoints. | I63: Inventory versions, hosts and endpoints and compare with documentation (WSTG-CONF). | J63: Up-to-date API inventory, deprecation policy, retirement. | K63: Monitor traffic to non-inventoried endpoints. | L63: A02:2025 | M63: API9:2023 | N63: WSTG-INFO-04, WSTG-CONF-05 | O63: V13 | Q63: CWE-1059 | R63: Methodology and Resources | S63: Enumeration | T63: D8 | AB63: AV-EXT-01, AV-EXT-07 | AE63: 2026-10-09
A64: AV-API-10 | B64: API | C64: Unsafe consumption of APIs | D64: Integrity | E64: Execution | F64: Medium | G64: Data from third-party APIs is processed with too much trust. | H64: Compromise via upstream services. | I64: Check validation and isolation of external API responses (WSTG-INPV). | J64: Validate external data, use timeouts and isolation. | K64: Monitor anomalous behavior of integrations. | L64: A08:2025 | M64: API10:2023 | N64: WSTG-INPV (no specific test) | O64: V4 | P64: T1195 | Q64: CWE-1104 | R64: Methodology and Resources | S64: Web attacks | T64: D8 | AB64: AV-CLD-19 | AE64: 2026-10-09
A65: AV-API-11 | B65: API | C65: Missing input schema validation (type juggling, JSON injection, HPP) | D65: Input validation | E65: Execution | F65: Medium | G65: The API does not validate request bodies against a strict schema: unexpected types (array instead of string), extra fields, duplicate parameters or nested JSON are accepted and passed on to back-end logic. | H65: Logic bypass (e.g. price/role), injection into downstream systems, crashes (DoS). | I65: Change types, add unexpected fields, duplicate parameters and compare server-side behavior with the OpenAPI specification (WSTG-INPV-04). | J65: Strict schema validation (OpenAPI/JSON Schema) with additionalProperties: false, canonicalization of parameters, strongly typed deserialization. | K65: Alert on schema validation errors and anomalous request structures. | L65: A05:2025 | M65: API3:2023, API8:2023 | N65: WSTG-INPV-04 | O65: V2, V4 | Q65: CWE-20, CWE-235 | R65: HTTP Parameter Pollution | S65: Web attacks | T65: D8 | AB65: AV-API-03 | AD65: https://cheatsheetseries.owasp.org/cheatsheets/REST_Security_Cheat_Sheet.html | AE65: 2026-10-09
A66: AV-API-12 | B66: API | C66: Insufficient authentication on internal / machine-to-machine APIs | D66: Authentication | E66: Lateral movement | F66: High | G66: Internal or service-to-service APIs rely on network location, static shared API keys or missing mTLS, so that any host in the segment (or a leaked key) has full access. | H66: Lateral movement and data access from a compromised component or via a leaked key. | I66: Access internal APIs from a different host/pod without credentials or with leaked keys; check key rotation, scoping and mTLS. | J66: mTLS or short-lived workload identities (SPIFFE/OIDC), per-client scopes, key rotation, network policy as an additional layer. | K66: Alert on API calls from unexpected workloads/IPs and on use of expired keys. | L66: A07:2025 | M66: API2:2023 | N66: WSTG-ATHN-10 | O66: V4, V6 | P66: T1078, T1552 | Q66: CWE-306, CWE-798 | R66: API Key Leaks | T66: D5 | AB66: AV-CLD-02, AV-NET-15 | AD66: https://cheatsheetseries.owasp.org/cheatsheets/Microservices_Security_Cheat_Sheet.html | AE66: 2026-10-09
A67: AV-NET-01 | B67: Internal network | C67: Network enumeration & host discovery | D67: Reconnaissance | E67: Reconnaissance | F67: Info | G67: Discovery of hosts, ports and services within the scope. | H67: Maps out the attack surface. | I67: Perform scoped host and service discovery in accordance with the rules of engagement. | J67: Network segmentation and minimization of exposed services. | K67: IDS/NDR detection of scan patterns. | P67: T1046, T1595, T1018 | R67: Network Discovery | S67: Enumeration | T67: D4 | AB67: AV-EXT-01, AV-AD-22 | AE67: 2026-10-09
A68: AV-NET-02 | B68: Internal network | C68: LLMNR/NBT-NS/mDNS poisoning & ADIDNS wildcard abuse | D68: Adversary-in-the-middle | E68: Credential access | F68: High | G68: Abuse of fallback name resolution (LLMNR, NBT-NS, mDNS) to redirect traffic and capture NetNTLM hashes; if those protocols are disabled, an authenticated user can often still create a wildcard record in AD-integrated DNS with the same effect. | H68: Interception of authentication material. | I68: Determine whether legacy name resolution protocols are active in the segment. | J68: Disable LLMNR/NBT-NS/mDNS via GPO; segment; enforce secure resolution; block creation of wildcard DNS records (ADIDNS) by regular users and enforce SMB/LDAP signing so that relay does not succeed. | K68: Alert on unexpected responder activity. | P68: T1557.001 | R68: Active Directory Attack | S68: Active Directory | T68: D4 | AB68: AV-NET-03, AV-NET-10, AV-AD-18, AV-NET-08, CVE-2025-24054 | AE68: 2026-10-09
A69: AV-NET-03 | B69: Internal network | C69: NTLM relay | D69: Adversary-in-the-middle | E69: Lateral movement | F69: High | G69: Forwarding intercepted authentication to hosts without signing. | H69: Authentication as the victim on other systems. | I69: Check whether SMB/LDAP signing is enforced on target systems. | J69: Enforce signing, disable legacy, segment. | K69: Detect authentications with an anomalous source/chain. | P69: T1557 | R69: Active Directory Attack | S69: Active Directory | T69: D4 | AB69: AV-NET-08, AV-AD-14, AV-AD-17, AV-NET-10, CVE-2019-1040, CVE-2025-33073, CVE-2024-21410 | AE69: 2026-10-09
A70: AV-NET-04 | B70: Internal network | C70: Service/version exploitation (unpatched) | D70: Exploitation | E70: Initial access | F70: High | G70: Known vulnerabilities in unpatched network services. | H70: Access to or control of the host. | I70: Identify versions and compare with known advisories within scope. | J70: Patch management, minimize exposed services. | K70: Vulnerability scanning and exploit signature detection. | L70: A03:2025 | P70: T1190, T1210 | Q70: CWE-1104 | R70: Methodology and Resources | S70: Enumeration | T70: D4 | AB70: AV-NET-21, CVE-2017-0144, CVE-2019-0708, CVE-2020-0796, CVE-2025-59287, CVE-2026-33824 | AE70: 2026-10-09
A71: AV-NET-05 | B71: Internal network | C71: Default / weak credentials | D71: Credential access | E71: Initial access | F71: High | G71: Vendor defaults or weak passwords on services and devices. | H71: Direct access to systems. | I71: Check for default and weak credentials within scope. | J71: Remove defaults, strong password policy, MFA. | K71: Alert on logins with default accounts. | P71: T1078, T1110 | Q71: CWE-521 | R71: Methodology and Resources | S71: Enumeration | T71: D5 | AB71: AV-NET-12, AV-NET-14, AV-NET-19, AV-WEB-44 | AE71: 2026-10-09
A72: AV-NET-06 | B72: Internal network | C72: Password spraying | D72: Credential access | E72: Credential access | F72: High | G72: A small number of commonly used passwords against many accounts. | H72: Account compromise without triggering lockout. | I72: Check lockout, throttling and detection policy (within the RoE). | J72: MFA, smart lockout policy, detection of spray patterns. | K72: Alert on many accounts with a few failed attempts. | P72: T1110.003 | Q72: CWE-307 | R72: Password Spraying | S72: Active Directory | T72: D5 | AB72: AV-WEB-43, AV-AD-19, AV-EXT-06, AV-CLD-09 | AE72: 2026-10-09
A73: AV-NET-07 | B73: Internal network | C73: Cleartext protocol interception | D73: Sniffing | E73: Credential access | F73: Medium | G73: Unencrypted protocols allow eavesdropping on credentials. | H73: Interception of sensitive data. | I73: Inventory unencrypted traffic within scope. | J73: Enforce encryption; remove legacy protocols. | K73: NDR detection of cleartext credential traffic. | L73: A04:2025 | O73: V12 | P73: T1040 | Q73: CWE-319 | R73: Network Sniffing | S73: Enumeration | T73: D4 | AB73: AV-NET-11, AV-NET-18, AV-WEB-20 | AE73: 2026-10-09
A74: AV-NET-08 | B74: Internal network | C74: SMB signing disabled | D74: Configuration | E74: Lateral movement | F74: Medium | G74: Missing SMB signing enables relay and MitM attacks. | H74: Facilitates NTLM relay and traffic manipulation. | I74: Check whether SMB signing is required on hosts within scope. | J74: Require SMB signing domain-wide. | K74: Inventory hosts without mandatory signing. | L74: A02:2025 | P74: T1557 | Q74: CWE-16 | R74: Active Directory Attack | S74: Active Directory | T74: D4 | AB74: AV-NET-03, AV-AD-14, AV-AD-17, CVE-2025-33073 | AE74: 2026-10-09
A75: AV-NET-09 | B75: Internal network | C75: SNMP misconfiguration | D75: Configuration | E75: Discovery | F75: Medium | G75: Weak community strings or exposed SNMP information. | H75: Information leakage and sometimes configuration changes. | I75: Check for default community strings and exposure (within scope). | J75: SNMPv3 with authentication, restrict access. | K75: Monitor SNMP traffic from unexpected sources. | L75: A02:2025 | P75: T1602 | Q75: CWE-16 | R75: Methodology and Resources | S75: Enumeration | T75: D4 | AB75: AV-NET-12, CVE-2025-20352 | AE75: 2026-10-09
A76: AV-NET-10 | B76: Internal network | C76: IPv6 / DHCPv6 spoofing (mitm6) & WPAD abuse | D76: Adversary-in-the-middle | E76: Credential access | F76: High | G76: Windows hosts request DHCPv6 by default; an attacker on the segment advertises itself as the DNS server and captures authentication via WPAD/DNS spoofing that can be relayed to LDAP(S)/SMB. | H76: NTLM relay to LDAP (creating a computer account, RBCD) up to and including domain compromise. | I76: Determine whether IPv6 is active but unmanaged and whether clients use DHCPv6/WPAD; perform only passive or explicitly approved active tests (RoE). | J76: Manage IPv6 (RA Guard, DHCPv6 Guard) or deliberately disable it on clients, disable WPAD, enforce LDAP signing/channel binding and SMB signing. | K76: Alert on unexpected DHCPv6/RA sources and WPAD requests to unknown hosts. | P76: T1557.003, T1557.001 | Q76: CWE-290 | R76: Active Directory Attack - mitm6 | S76: Active Directory | T76: D4 | AB76: AV-NET-02, AV-NET-03, AV-AD-17 | AD76: https://blog.fox-it.com/2018/01/11/mitm6-compromising-ipv4-networks-via-ipv6/ | AE76: 2026-10-09
A77: AV-NET-11 | B77: Internal network | C77: ARP spoofing / layer-2 attacks | D77: Adversary-in-the-middle | E77: Credential access | F77: Medium | G77: Missing Dynamic ARP Inspection, DHCP snooping and port security allow ARP cache poisoning, DHCP spoofing and VLAN hopping on access switches. | H77: Interception and manipulation of traffic within the segment; downgrade to cleartext. | I77: Assess switch configuration (DAI, DHCP snooping, port security, native VLAN) and perform only limited, approved PoCs. | J77: DAI, DHCP snooping, port security, 802.1X, no unused ports in production VLANs, encryption of sensitive traffic. | K77: Alert on ARP anomalies (duplicate MAC/IP bindings) via NDR/switch logging. | P77: T1557.002 | Q77: CWE-290 | R77: Network Sniffing | S77: Enumeration | T77: D4 | AB77: AV-NET-07, AV-NET-20 | AD77: https://attack.mitre.org/techniques/T1557/002/ | AE77: 2026-10-09
A78: AV-NET-12 | B78: Internal network | C78: Exposed management interfaces (IPMI/BMC, iLO, iDRAC, web admin) | D78: Configuration | E78: Privilege escalation | F78: High | G78: Out-of-band management interfaces and web consoles of servers, switches, storage and hypervisors are reachable from user VLANs, often with default credentials, outdated firmware or IPMI 2.0 (RAKP hash leakage, cipher 0). | H78: Full control of hardware (console, virtual media, power) bypassing the OS; persistent access. | I78: Inventory management interfaces per segment, check reachability from non-management zones, default credentials, IPMI version/cipher suites and firmware version. | J78: Isolate management in a separate OOB VLAN with jump hosts and MFA, remove defaults, disable IPMI-over-LAN where possible, firmware updates. | K78: Alert on logins to management interfaces from non-management networks. | P78: T1021, T1078.001, T1110 | Q78: CWE-1188, CWE-284 | R78: Insecure Management Interface | S78: Enumeration | T78: D4 | AB78: CVE-2013-4786, AV-NET-05, AV-NET-15 | AD78: https://www.rapid7.com/blog/post/2013/07/02/a-penetration-testers-guide-to-ipmi/ | AE78: 2026-10-09
A79: AV-NET-13 | B79: Internal network | C79: Insecure network shares (anonymous / overly permissive SMB & NFS) | D79: Access control | E79: Collection | F79: High | G79: File shares are readable (or writable) by Everyone/Authenticated Users or anonymous users; NFS exports without root_squash or with no_root_squash; shares contain configs, scripts, backups and passwords. | H79: Data breach, credential discovery (often the fastest route to domain admin), placement of malicious files (LNK/SCF for hash capture). | I79: Enumerate shares and exports as an anonymous and as a low-privileged user, scan file contents for credentials and sensitive data (within scope). | J79: Least-privilege share and NTFS permissions, remove anonymous access, root_squash and host restrictions on NFS, clean up credentials in files, DLP/classification. | K79: Alert on large-scale share enumeration and mass file reads by a single user. | P79: T1135, T1039, T1552.001 | Q79: CWE-732, CWE-284 | R79: Methodology and Resources - Network Discovery | S79: Enumeration | T79: D2 | AB79: AV-AD-26, AV-HOST-04 | AD79: https://attack.mitre.org/techniques/T1135/ | AE79: 2026-10-09
A80: AV-NET-14 | B80: Internal network | C80: Exposed databases & unauthenticated services (Redis, MongoDB, Elasticsearch, MSSQL) | D80: Configuration | E80: Initial access | F80: High | G80: Databases, caches and message brokers listen on all interfaces without authentication or with weak/default credentials (e.g. sa, postgres, redis without requirepass, Elasticsearch without security). | H80: Data breach and often code execution on the host (xp_cmdshell, Redis module/config write, MongoDB scripting). | I80: Scan for database services, test anonymous access and default credentials, assess version and network exposure. | J80: Bind to localhost/management interfaces, mandatory authentication and TLS, firewall per source, least-privilege accounts, patch policy. | K80: Alert on connections to databases from non-application hosts. | L80: A02:2025 | P80: T1190, T1078.001, T1213 | Q80: CWE-306, CWE-1188 | R80: Methodology and Resources | S80: Enumeration | T80: D4 | AB80: CVE-2025-49844, CVE-2025-14847, AV-NET-05 | AD80: https://attack.mitre.org/techniques/T1190/ | AE80: 2026-10-09
A81: AV-NET-15 | B81: Internal network | C81: Insufficient network segmentation (flat network) | D81: Architecture | E81: Lateral movement | F81: High | G81: Workstations, servers, OT/IoT, management and guests share (routable) segments without filtering, so that a compromised endpoint directly reaches critical systems. | H81: Rapid lateral movement and ransomware spread; the blast radius of a single incident is the entire network. | I81: Test reachability of critical systems (DCs, databases, backup, OT, management) from representative segments; assess firewall rules and VLAN design. | J81: Zoning (users, servers, management, OT, DMZ, guests) with default-deny between zones, microsegmentation for critical assets, host firewalls. | K81: NDR/flow monitoring of east-west traffic between zones; alert on SMB/RDP between workstations. | P81: T1021, T1570, T1210 | Q81: CWE-923 | R81: Network Pivoting Techniques | S81: Tunneling | T81: D4 | AB81: AV-NET-12, AV-NET-17, AV-WIFI-07 | AC81: CIS Controls v8: 12.2 | AD81: https://www.cisecurity.org/controls/v8 | AE81: 2026-10-09
A82: AV-NET-16 | B82: Internal network | C82: Insufficient egress filtering (C2 / exfiltration possible) | D82: Architecture | E82: Command and control | F82: Medium | G82: Outbound traffic from workstations and servers is not restricted to necessary destinations/protocols (direct internet, DNS to external resolvers, unrestricted 443), so that C2 channels and data exfiltration go unnoticed. | H82: Unrestricted command-and-control and exfiltration; DNS/ICMP tunneling possible. | I82: Test from representative segments which ports/protocols to the internet are open (incl. DNS tunneling and direct IP connections) and whether a proxy is mandatory. | J82: Default-deny egress with proxy/allowlisting, enforce internal DNS resolvers, TLS inspection where appropriate, no direct internet access for servers. | K82: Alert on long/regular connections to unknown destinations, DNS anomalies and large outbound volumes. | P82: T1071, T1572, T1090, T1048 | Q82: CWE-923 | R82: Network Pivoting Techniques | S82: Tunneling | T82: D4 | AB82: AV-NET-15 | AD82: https://attack.mitre.org/techniques/T1572/ | AE82: 2026-10-09
A83: AV-NET-17 | B83: Internal network | C83: Exposed remote access services (RDP/VNC/SSH) with weak configuration | D83: Configuration | E83: Lateral movement | F83: Medium | G83: RDP without NLA, VNC without or with a weak password, SSH with password authentication/root login, and remote access tools (AnyDesk, TeamViewer, ScreenConnect) widely available within the network. | H83: Brute force and credential reuse for lateral movement; shadow IT remote access as a persistence channel. | I83: Inventory remote access services per segment, check NLA, encryption, authentication methods and lockout. | J83: NLA and MFA on RDP, SSH with keys and without root login, VNC only via tunnel, allowlisting of remote access tools, jump hosts. | K83: Alert on RDP/SSH logins between workstations and on installation of unknown remote access software. | P83: T1021.001, T1021.004, T1219, T1110 | Q83: CWE-287, CWE-306 | R83: Methodology and Resources | S83: Password attacks | T83: D4 | AB83: CVE-2019-0708, CVE-2024-1709, AV-NET-05 | AD83: https://attack.mitre.org/techniques/T1021/001/ | AE83: 2026-10-09
A84: AV-NET-18 | B84: Internal network | C84: Legacy protocols enabled (SMBv1, Telnet/FTP, TLS 1.0/1.1, SSLv3) | D84: Configuration | E84: Initial access | F84: Medium | G84: Outdated protocols and versions are still active on servers, printers and appliances, with known vulnerabilities (EternalBlue on SMBv1), cleartext authentication or weak cryptography. | H84: Exploitation of known vulnerabilities, interception of credentials, downgrade attacks. | I84: Scan for SMBv1, Telnet, FTP, old TLS versions and cipher suites; link to known CVEs within scope. | J84: Disable SMBv1 (GPO), replace Telnet/FTP with SSH/SFTP, TLS 1.2+ with modern suites, replace or isolate devices that do not support this. | K84: Periodic protocol scans; alert on SMBv1 negotiation and cleartext logins in NDR. | L84: A02:2025, A04:2025 | P84: T1210, T1040 | Q84: CWE-1104, CWE-327, CWE-319 | R84: Methodology and Resources | S84: Enumeration | T84: D4 | AB84: CVE-2017-0144, AV-NET-07, AV-AD-18 | AD84: https://learn.microsoft.com/en-us/windows-server/storage/file-server/troubleshoot/detect-enable-and-disable-smbv1-v2-v3 | AE84: 2026-10-09
A85: AV-NET-19 | B85: Internal network | C85: Printer / MFP abuse (LDAP pass-back, stored credentials, PJL) | D85: Configuration | E85: Credential access | F85: Medium | G85: Multifunction printers with a default admin password contain LDAP/SMB scan-to-folder credentials; by changing the LDAP address (pass-back), those credentials are sent in cleartext to the attacker; PJL/PostScript gives access to the file system and stored scans. | H85: Obtaining (often privileged) domain credentials and sensitive documents. | I85: Inventory printers, check default credentials and the presence of stored LDAP/SMB accounts; perform pass-back only within the RoE. | J85: Unique admin passwords, least-privilege scan accounts (no domain admin), LDAPS with certificate validation, printers in a separate VLAN, firmware updates. | K85: Alert on LDAP binds from printer accounts to non-DC hosts. | P85: T1557, T1552, T1078.001 | Q85: CWE-1188, CWE-522 | R85: Methodology and Resources | S85: Enumeration | T85: D4 | AB85: AV-NET-05, AV-NET-12 | AD85: http://hacking-printers.net/wiki/index.php/Main_Page | AE85: 2026-10-09
A86: AV-NET-20 | B86: Internal network | C86: No network access control (802.1X / NAC) on wired or wireless | D86: Configuration | E86: Initial access | F86: Medium | G86: Every physically connected or wirelessly connected device receives an address in a production VLAN; no 802.1X, MAB-only with MAC spoofing possible, or NAC only in monitoring mode. | H86: Rogue devices (drop boxes, implants) and brought-in laptops immediately get access to the internal network. | I86: Connect an unknown device to access ports (meeting rooms, printers, VoIP) and determine the access obtained; test MAC spoofing of allowed devices (RoE). | J86: 802.1X with certificates (EAP-TLS), MAB only with profiling and a restricted VLAN, port lockdown of unused ports, VoIP/printer VLANs separated. | K86: NAC alerts on new MAC addresses and profiling mismatch. | P86: T1200, T1557 | Q86: CWE-306 | R86: Methodology and Resources | T86: D4 | AB86: AV-PHY-03, AV-PHY-08, AV-WIFI-05 | AD86: https://attack.mitre.org/techniques/T1200/ | AE86: 2026-10-09
A87: AV-NET-21 | B87: Internal network | C87: End-of-life / unsupported systems | D87: Supply chain | E87: Initial access | F87: High | G87: Operating systems, databases or appliances without vendor support (e.g. Windows Server 2012/2012 R2, Windows 10 after Oct 2025, old ESXi/NetScaler firmware) run in production without compensating controls. | H87: Unpatchable, publicly known vulnerabilities; often direct exploitation to SYSTEM/root. | I87: Inventory versions via scans and CMDB and compare with EOL dates; assess isolation and compensating controls. | J87: Migrate/replace, ESU where temporarily needed, strict isolation (no internet, separate zone), virtual patching, remove from the domain where possible. | K87: Vulnerability management with EOL flagging; alert on traffic to EOL hosts from workstations. | L87: A03:2025 | P87: T1210, T1068 | Q87: CWE-1104 | R87: Methodology and Resources | S87: Public exploits | T87: D7 | AB87: AV-NET-04, CVE-2017-0144, CVE-2019-0708 | AD87: https://endoflife.date/ | AE87: 2026-10-09
A88: AV-NET-22 | B88: Internal network | C88: Virtualization / hypervisor management exposure (vCenter, ESXi, Hyper-V, Proxmox) | D88: Configuration | E88: Privilege escalation | F88: High | G88: Hypervisor management interfaces are reachable from user segments, linked to AD (ESXi Admins group), unpatched or with local accounts without MFA; VM escape and snapshot theft are possible. | H88: Compromise of all virtual machines at once (incl. DCs via VMDK theft), ransomware at the hypervisor level. | I88: Check network exposure, versions, AD integration/group names, SSH/shell access and lockdown mode of hypervisors and vCenter. | J88: Management only via a management zone with MFA, patching, lockdown mode, no AD group-name-based admin without protection, immutable backups of VMs. | K88: Alert on logins to vCenter/ESXi from non-management networks and on mass snapshot/export actions. | P88: T1021, T1078, T1611 | Q88: CWE-284 | R88: Methodology and Resources | T88: D3 | AB88: CVE-2021-21972, CVE-2024-37085, CVE-2025-22224, CVE-2026-59310 | AD88: https://www.cisa.gov/news-events/cybersecurity-advisories/aa23-039a | AE88: 2026-10-09
A89: AV-NET-23 | B89: Internal network | C89: Backup infrastructure exposure (Veeam, Commvault, NAS-backups) | D89: Configuration | E89: Impact | F89: High | G89: Backup servers run in the domain with privileged service accounts, are widely reachable, unpatched or have backups that can be deleted/encrypted by domain accounts. | H89: Ransomware actors delete or encrypt backups and extract credentials from the backup console; recovery becomes impossible. | I89: Assess network exposure, versions, domain membership, privileges of backup accounts and immutability of backups. | J89: Backup server outside the production domain or in a separate tier, immutable/offline copies (3-2-1-1-0), least-privilege service accounts, MFA on the console, patching. | K89: Alert on deletion of backup jobs/repositories and on logins to the backup console outside maintenance windows. | P89: T1490, T1078, T1552 | Q89: CWE-284 | R89: Methodology and Resources | T89: D7 | AB89: CVE-2024-40711, AV-NET-15 | AD89: https://www.veeam.com/kb4649 | AE89: 2026-10-09
A90: AV-EXT-01 | B90: External network | C90: External attack surface & OSINT enumeration | D90: Reconnaissance | E90: Reconnaissance | F90: Info | G90: Mapping of domains, subdomains, IP ranges, cloud assets, certificates, employees and technology via passive sources (CT logs, DNS, Shodan/Censys, breach data, social media). | H90: Determines the attack surface and unknown/forgotten assets (shadow IT). | I90: Perform passive and light active enumeration; compare discovered assets with the client's inventory and report unknown assets. | J90: Asset inventory and attack surface management (ASM), decommissioning process, limiting public information. | K90: Limited; monitor CT logs and ASM tooling for new assets. | N90: WSTG-INFO-01, WSTG-INFO-02 | P90: T1595, T1593, T1596, T1590 | R90: Methodology and Resources - Subdomains Enumeration | S90: Enumeration | T90: D4 | AB90: AV-NET-01, AV-WEB-28 | AD90: https://github.com/OWASP/amass | AE90: 2026-10-09
A91: AV-EXT-02 | B91: External network | C91: Exposed administrative / remote access services on the perimeter | D91: Configuration | E91: Initial access | F91: High | G91: RDP, SSH, SMB, databases, management interfaces of firewalls/appliances, Kubernetes APIs or Docker APIs are directly reachable from the internet. | H91: Brute force, credential stuffing and direct exploitation of management interfaces; ransomware initial access. | I91: Port scan and service fingerprinting on the external ranges; test authentication requirements, lockout and versions (RoE). | J91: Management only via VPN/ZTNA with MFA, allowlisting of source IPs, remove unnecessary services, WAF/reverse proxy for web management. | K91: Alert on external login attempts on management services; ASM scans. | L91: A02:2025 | P91: T1133, T1190, T1110 | Q91: CWE-284, CWE-1327 | R91: Methodology and Resources | S91: Enumeration | T91: D4 | AB91: AV-NET-17, CVE-2024-0012, CVE-2026-20079 | AD91: https://www.cisa.gov/resources-tools/services/cyber-hygiene-services | AE91: 2026-10-09
A92: AV-EXT-03 | B92: External network | C92: E-mail spoofing (missing/weak SPF, DKIM, DMARC) | D92: Configuration | E92: Initial access | F92: Medium | G92: SPF is missing or too permissive (+all, too many includes), DKIM is missing, DMARC is set to p=none or is missing, which allows emails to be forged on behalf of the domain; also subdomains without a policy and MTA-STS/TLS-RPT are missing. | H92: Credible phishing and CEO fraud on behalf of the organization aimed at employees, customers and partners. | I92: Analyze SPF/DKIM/DMARC/MTA-STS records and test (with permission) whether a forged email reaches the inbox. | J92: SPF with -all, DKIM on all sending systems, DMARC p=reject (phased), policy for subdomains, MTA-STS and TLS-RPT, inbound DMARC enforcement. | K92: Monitor DMARC aggregate reports; alert on inbound mail with the organization's own domain as sender that fails DMARC. | P92: T1566, T1672 | Q92: CWE-290, CWE-346 | R92: Phishing Methodology | T92: D4 | AB92: AV-SE-01, AV-SE-02 | AC92: NCSC-NL / Forum Standaardisatie: SPF, DKIM, DMARC, STARTTLS, DANE | AD92: https://internet.nl/ | AE92: 2026-10-09
A93: AV-EXT-04 | B93: External network | C93: DNS misconfiguration (zone transfer, dangling records, missing DNSSEC) | D93: Configuration | E93: Reconnaissance | F93: Low | G93: AXFR allowed to arbitrary clients, orphaned records pointing to external services or old IPs, missing DNSSEC/CAA, internal hostnames in public zones. | H93: Complete inventory of hosts for attackers, subdomain takeover, DNS spoofing of the domain. | I93: Test zone transfer on all authoritative nameservers, enumerate records and check DNSSEC/CAA and dangling records. | J93: AXFR only to secondary servers, cleanup of records, DNSSEC and CAA, separation of internal and external zones (split-horizon). | K93: Alert on AXFR requests from unknown sources; periodic DNS audit. | N93: WSTG-INFO-02, WSTG-CONF-10 | P93: T1590.002, T1584.001 | Q93: CWE-200, CWE-284 | R93: Methodology and Resources - Subdomains Enumeration | S93: Enumeration | T93: D4 | AB93: AV-WEB-28 | AD93: https://internet.nl/ | AE93: 2026-10-09
A94: AV-EXT-05 | B94: External network | C94: VPN / remote access gateway weaknesses | D94: Authentication | E94: Initial access | F94: High | G94: SSL VPNs and remote access gateways (Fortinet, Citrix NetScaler, Ivanti, Palo Alto, Cisco ASA, SonicWall, Check Point) without MFA, with outdated firmware with known exploits, exposed management ports or weak local accounts. | H94: Direct access to the internal network with a single leaked password or via a public exploit; this is the most common ransomware initial access. | I94: Fingerprint version and build, compare with KEV/vendor advisories, test MFA coverage (incl. legacy realms), lockout and exposure of management interfaces. | J94: MFA for all users, patching within days for KEV listings, management interface not exposed to the internet, certificate-based client authentication, logging and integrity checks of the appliance. | K94: Alert on VPN logins from new countries/ASNs, multiple users from a single IP and on configuration changes of the appliance. | P94: T1133, T1078, T1190 | Q94: CWE-287, CWE-1104 | R94: Methodology and Resources | S94: Public exploits | T94: D4 | AB94: CVE-2018-13379, CVE-2023-4966, CVE-2024-21887, CVE-2024-3400, CVE-2025-20333, CVE-2025-5777 | AC94: Related CVEs without their own row: CVE-2026-19490 | AD94: https://www.cisa.gov/known-exploited-vulnerabilities-catalog | AE94: 2026-10-09
A95: AV-EXT-06 | B95: External network | C95: Leaked credentials & breach data exposure | D95: Credential access | E95: Initial access | F95: High | G95: Employee credentials appear in public data breaches, infostealer logs or code repositories; password reuse between personal and business accounts makes them usable on VPN, M365 or webmail. | H95: Valid access without exploitation; often combined with MFA fatigue or missing MFA. | I95: Search (within the RoE and legal frameworks) breach/stealer data sources for the domain and validate only with permission via password spraying or a single login. | J95: Credential screening against breach lists, MFA, password manager, monitoring of stealer logs, incident process for leaked credentials. | K95: Alert on logins with leaked credentials (identity protection) and on impossible travel. | P95: T1589.001, T1586, T1078 | Q95: CWE-521, CWE-522 | R95: Account Takeover | S95: Password attacks | T95: D5 | AB95: AV-NET-06, AV-WEB-44, AV-CLD-09 | AD95: https://haveibeenpwned.com/ | AE95: 2026-10-09
A96: AV-EXT-07 | B96: External network | C96: Exposed test / staging / development environments | D96: Configuration | E96: Initial access | F96: Medium | G96: Staging, test and development environments are publicly reachable with production data, weaker security, debug modes, default accounts or old code versions; often outside monitoring. | H96: Data leak of production-like data and an easy stepping stone (shared credentials, network link) to production. | I96: Enumerate subdomains/hosts with test/dev/acc/uat naming, assess security, data and links with production. | J96: No production data in non-production, IP allowlisting/VPN, the same baseline and monitoring as production, decommissioning. | K96: ASM tooling for new hosts; central logging of non-production environments. | L96: A02:2025 | N96: WSTG-CONF-05 | O96: V13 | P96: T1190, T1133 | Q96: CWE-284, CWE-1188 | R96: Methodology and Resources | S96: Enumeration | T96: D8 | AB96: AV-WEB-18, AV-WEB-48 | AD96: https://owasp.org/www-project-web-security-testing-guide/latest/4-Web_Application_Security_Testing/02-Configuration_and_Deployment_Management_Testing/05-Enumerate_Infrastructure_and_Application_Admin_Interfaces | AE96: 2026-10-09
A97: AV-AD-01 | B97: Active Directory | C97: Kerberoasting | D97: Credential access | E97: Credential access | F97: High | G97: Service tickets for SPN accounts are cracked offline against weak passwords. | H97: Compromise of service accounts, often with high privileges. | I97: Inventory SPN accounts and assess password strength/policy. | J97: (g)MSAs, strong passwords (25+ characters for service accounts), minimize SPNs; disable RC4 (Kerberos encryption types) so that only AES tickets are issued. | K97: Alert on unusual service ticket requests. | P97: T1558.003 | R97: Active Directory Attack - Kerberoast | S97: Active Directory | T97: D5 | AB97: AV-AD-19, AV-AD-20 | AE97: 2026-10-09
A98: AV-AD-02 | B98: Active Directory | C98: AS-REP roasting | D98: Credential access | E98: Credential access | F98: High | G98: Accounts without pre-authentication yield crackable material. | H98: Offline cracking of user passwords. | I98: Inventory accounts with pre-auth disabled. | J98: Require Kerberos pre-authentication; strong passwords. | K98: Alert on AS-REP requests for such accounts. | P98: T1558.004 | R98: Active Directory Attack - ASREPRoast | S98: Active Directory | T98: D5 | AB98: AV-AD-19 | AE98: 2026-10-09
A99: AV-AD-03 | B99: Active Directory | C99: OS credential dumping | D99: Credential access | E99: Credential access | F99: High | G99: Extraction of credentials from memory or local stores on a host. | H99: Reuse of credentials for further access. | I99: Assess protection of credential stores and LSASS (post-exploitation, within scope). | J99: Credential Guard, LAPS, least privilege, EDR. | K99: EDR detection of memory access to credential processes. | P99: T1003 | R99: Active Directory Attack - Credential Dumping | S99: Active Directory | T99: D5 | AB99: AV-HOST-06, AV-AD-21, AV-HOST-04, CVE-2021-36934 | AE99: 2026-10-09
A100: AV-AD-04 | B100: Active Directory | C100: DCSync | D100: Credential access | E100: Credential access | F100: High | G100: Abuse of replication privileges to request password hashes from the DC. | H100: Obtaining hashes up to and including domain admin. | I100: Assess who holds replication privileges (DS-Replication). | J100: Restrict replication privileges; monitor delegations. | K100: Alert on replication from non-DC hosts. | P100: T1003.006 | R100: Active Directory Attack - DCSync | S100: Active Directory | T100: D5 | AB100: AV-AD-08, AV-AD-17, AV-CLD-13, CVE-2020-1472 | AE100: 2026-10-09
...

Sheet Legend
A1: Attack-vectors knowledge base - Legend (version 0.10.0, 2026-10-09)
A3: Column | B3: Meaning | C3: Values / convention
A4: ID | B4: Unique key of the row. | C4: AV-<SCOPE>-<nn> for attack vectors (WEB, API, NET, EXT, AD, CLD, MOB, WIFI, SE, PHY, HOST, AI); CVE-yyyy-nnnnn for known vulnerabilities.
A5: Scope | B5: Test scope in which the vector/vulnerability is typically encountered. | C5: Web application | API | Internal network | External network | Active Directory | Cloud | Mobile | Wireless | Social engineering | Physical | Endpoint | AI / LLM
A6: Vector | B6: Short English name of the attack technique or vulnerability (report title). | C6: Free text; CVE rows: "<Product> - <type> (<nickname>)".
A7: Category | B7: Class of the finding. | C7: E.g. Authorization, Injection, Configuration, Credential access, Known vulnerability (all CVE rows).
A8: Kill_chain_phase | B8: Phase (MITRE ATT&CK tactic) in which the technique is typically used. | C8: Reconnaissance | Initial access | Execution | Persistence | Privilege escalation | Defense evasion | Credential access | Discovery | Lateral movement | Collection | Command and control | Impact
A9: Severity_default | B9: Indicative default severity for reporting; adjust to context and evidence. | C9: Info | Low | Medium | High | Critical. For CVE rows based on practical pentest impact; the formal CVSS score is in CVSS_score.
A10: Description / Impact / Test_approach / Remediation / Detection_note | B10: Report text (EN; translated from the Dutch original, which by convention was written without diacritics). | C10: Test_approach describes a non-destructive approach within the rules of engagement (RoE).
A11: OWASP_Top10_2025 | B11: Mapping to OWASP Top 10 2025. | C11: A01 Broken Access Control, A02 Security Misconfiguration, A03 Software Supply Chain Failures, A04 Cryptographic Failures, A05 Injection, A06 Insecure Design, A07 Authentication Failures, A08 Software or Data Integrity Failures, A09 Security Logging & Alerting Failures, A10 Mishandling of Exceptional Conditions. CVE rows receive A03:2025 (vulnerable component) plus the underlying class.
A12: OWASP_API_2023 | B12: Mapping to OWASP API Security Top 10 2023. | C12: API1 through API10.
A13: WSTG | B13: OWASP Web Security Testing Guide test ID (v4.2 / latest). | C13: E.g. WSTG-ATHZ-04 (IDOR), WSTG-INPV-05 (SQLi), WSTG-SESS-10 (JWT), WSTG-APIT-01 (GraphQL). The category prefix remains filterable.
A14: ASVS_5.0 | B14: Chapter of OWASP ASVS 5.0. | C14: V1 Encoding/Sanitization, V2 Validation/Business Logic, V3 Web Frontend, V4 API/Web Service, V5 File Handling, V6 Authentication, V7 Session, V8 Authorization, V9 Self-contained Tokens, V10 OAuth/OIDC, V11 Cryptography, V12 Secure Communication, V13 Configuration, V14 Data Protection, V15 Secure Coding/Architecture, V16 Logging/Error Handling, V17 WebRTC.
... A28: Last_updated | B28: Date of last review/change of the row. | C28: ISO date (yyyy-mm-dd).
A30: Sources and reference dates
A31: CVE records: CVEProject/cvelistV5 (CNA descriptions, CVSS, CISA-ADP incl. KEV date), as of 2026-10-04.
A32: CISA Known Exploited Vulnerabilities Catalog (via the ADP container in the CVE records), as of 2026-10-04.
A33: OWASP Top 10 2025, OWASP API Security Top 10 2023, OWASP WSTG v4.2/latest, OWASP ASVS 5.0, OWASP Mobile Top 10 2024 / MASVS 2.x, OWASP Top 10 for LLM Applications 2025.
A34: MITRE ATT&CK Enterprise (v17/v18) and MITRE ATLAS.
A35: Vendor advisories (MSRC, Fortinet PSIRT, Citrix/NetScaler, Ivanti, Palo Alto Networks, Cisco PSIRT, Broadcom/VMware, Atlassian, Oracle CPU, SAP, Adobe, GitLab, JetBrains, JFrog and others).
A36: Severity_default, Test_approach, Remediation and Detection_note are editorial choices for reporting; CVSS/KEV/versions are taken from the sources.

Sheet Changelog
A1: Version | B1: Date | C1: Component | D1: Change
A2: 0.10.0 | B2: 2026-10-09 | C2: Structure | D2: 10 columns added after Evidence: CVSS_score, CVSS_vector, Affected_versions, Fixed_in, CISA_KEV, Exploit_public, Related_IDs, Other_mapping, References, Last_updated. Existing 21 columns, order and header names unchanged.
A3: 0.10.0 | B3: 2026-10-09 | C3: Structure | D3: Header row bold with fill, frozen first row/column (ID), autofilter across the entire table; Legend, Changelog and Overview tabs added.
A4: 0.10.0 | B4: 2026-10-09 | C4: Attack vectors | D4: 108 new AV rows (total 195): Web +29, API +2, Internal network +14, External network (new) +7, Active Directory +14, Cloud +11, Mobile +4, Wireless +4, Social engineering +5, Physical +4, Endpoint (new) +7, AI / LLM (new) +7.
A5: 0.10.0 | B5: 2026-10-09 | C5: Attack vectors | D5: New scopes: External network (AV-EXT), Endpoint (AV-HOST) and AI / LLM (AV-AI) with mapping to OWASP LLM Top 10 2025 and MITRE ATLAS.
A6: 0.10.0 | B6: 2026-10-09 | C6: Existing rows | D6: WSTG column refined from category (e.g. WSTG-ATHZ) to specific test IDs (e.g. WSTG-ATHZ-04); reflected/stored XSS moved from WSTG-CLNT to WSTG-INPV-01/02 in line with WSTG.
A7: 0.10.0 | B7: 2026-10-09 | C7: Existing rows | D7: MITRE ATT&CK supplemented where a defensible mapping exists (including SQLi/SSRF/XXE/SSTI -> T1190, file upload -> T1505.003, session -> T1539, JWT -> T1606, TLS -> T1557/T1040); AV-AD-08 (ACL abuse) corrected to T1098, T1484.001.
A8: 0.10.0 | B8: 2026-10-09 | C8: Existing rows | D8: AV-AD-09 extended from ESC1-ESC8 to ESC1-ESC16 (incl. ESC9/10 certificate mapping, ESC15 EKUwu, ESC16) with Certipy reference; AV-NET-02 extended with ADIDNS wildcard abuse; AV-WEB-11 renamed to "Path traversal / LFI / RFI"; AV-AD-01 remediation supplemented with RC4 disabling; AV-CLD-03 extended with snapshots/SAS tokens; AV-WEB-18 CWE-1188 added.
A9: 0.10.0 | B9: 2026-10-09 | C9: Existing rows | D9: Related_IDs and Other_mapping (MASVS / OWASP Mobile Top 10 2024, CIS, Certipy) filled in; OWASP_API_2023 supplemented for AV-WEB-01/02/12 (IDOR, privesc, auth).
A10: 0.10.0 | B10: 2026-10-09 | C10: CVE rows | D10: 154 CVE rows (was 1). Row CVE-2020-14008 translated into Dutch, supplemented (CVSS 7.2, build 14730, KEV status, WSTG/CWE/MITRE) and category typo "Known Vulnerabillity" corrected to "Known vulnerability".
A11: 0.10.0 | B11: 2026-10-09 | C11: CVE rows | D11: Selection criteria: exploited in the wild (CISA KEV) and/or structurally encountered in pentests of Dutch organizations; per scope: Active Directory (11), Internal network (25), External network (47), Web application (38), Endpoint (10), Social engineering (5), Cloud (7), AI / LLM (11). 137 of the 154 CVE rows are in the CISA KEV catalog. Coverage through KEV additions of 2026-10-04 (including CVE-2026-104286 FortiMail, CVE-2026-88771 NetScaler, CVE-2026-63030 WordPress, CVE-2026-33824 Windows IKEEXT).
A12: 0.10.0 | B12: 2026-10-09 | C12: CVE rows | D12: CVSS score/vector, KEV date and references automatically taken from the official CVE records (cvelistV5, CNA and CISA-ADP); temporal metrics removed from vectors. Exceptions documented in Other_mapping (CVE-2020-1472 NVD 10.0 instead of CNA 5.5; CVE-2020-14008 NVD 7.2; CVE-2013-4786 CVSSv2 only).
... A14: 0.10.0 | B14: 2026-10-09 | C14: Points of attention | D14: When reporting, check the current NVD score and the vendor advisory; version numbers are summarized. Severity_default is indicative. All rows with Last_updated 2026-10-09 were reviewed in this release.
A15: 0.9.1 | C15: Baseline | D15: Original knowledge base: 87 attack vectors (9 scopes) and 1 CVE row.
A16: 0.10.0-EN | B16: 2026-10-11 | C16: Translation | D16: Full English translation of all tabs (attack-vectors-knowledge-base, Legend, Changelog, Overview) from the Dutch 0.10.0 original. IDs, mappings, versions, CVSS, KEV dates, references and formulas unchanged; CISA_KEV values "Ja/Nee" are now "Yes/No" (Overview formulas adjusted accordingly); tabs "Legenda" and "Overzicht" renamed to "Legend" and "Overview".

Sheet Overview
A1: Overview of counts per scope and Severity_default (formulas on the attack-vectors-knowledge-base tab)
A3: Scope | B3: Info | C3: Low | D3: Medium | E3: High | F3: Critical | G3: Total | H3: of which CVE rows | I3: of which in KEV
A4: Web application | B4: =COUNTIFS('attack-vectors-knowledge-base'!$B:$B,$A4,'attack-vectors-knowledge-base'!$F:$F,B$3) -> 0 | C4: =COUNTIFS('attack-vectors-knowledge-base'!$B:$B,$A4,'attack-vectors-knowledge-base'!$F:$F,C$3) -> 8 | D4: =COUNTIFS('attack-vectors-knowledge-base'!$B:$B,$A4,'attack-vectors-knowledge-base'!$F:$F,D$3) -> 24 | E4: =COUNTIFS('attack-vectors-knowledge-base'!$B:$B,$A4,'attack-vectors-knowledge-base'!$F:$F,E$3) -> 22 | F4: =COUNTIFS('attack-vectors-knowledge-base'!$B:$B,$A4,'attack-vectors-knowledge-base'!$F:$F,F$3) -> 37 | G4: =SUM(B4:F4) -> 91 | H4: =COUNTIFS('attack-vectors-knowledge-base'!$B:$B,$A4,'attack-vectors-knowledge-base'!$D:$D,"Known vulnerability") -> 38 | I4: =COUNTIFS('attack-vectors-knowledge-base'!$B:$B,$A4,'attack-vectors-knowledge-base'!$Z:$Z,"Yes*") -> 36
A5: API | B5: =COUNTIFS('attack-vectors-knowledge-base'!$B:$B,$A5,'attack-vectors-knowledge-base'!$F:$F,B$3) -> 0 | C5: =COUNTIFS('attack-vectors-knowledge-base'!$B:$B,$A5,'attack-vectors-knowledge-base'!$F:$F,C$3) -> 0 | D5: =COUNTIFS('attack-vectors-knowledge-base'!$B:$B,$A5,'attack-vectors-knowledge-base'!$F:$F,D$3) -> 7 | E5: =COUNTIFS('attack-vectors-knowledge-base'!$B:$B,$A5,'attack-vectors-knowledge-base'!$F:$F,E$3) -> 5 | F5: =COUNTIFS('attack-vectors-knowledge-base'!$B:$B,$A5,'attack-vectors-knowledge-base'!$F:$F,F$3) -> 0 | G5: =SUM(B5:F5) -> 12 | H5: =COUNTIFS('attack-vectors-knowledge-base'!$B:$B,$A5,'attack-vectors-knowledge-base'!$D:$D,"Known vulnerability") -> 0 | I5: =COUNTIFS('attack-vectors-knowledge-base'!$B:$B,$A5,'attack-vectors-knowledge-base'!$Z:$Z,"Yes*") -> 0
A6: Internal network | B6: =COUNTIFS('attack-vectors-knowledge-base'!$B:$B,$A6,'attack-vectors-knowledge-base'!$F:$F,B$3) -> 1 | C6: =COUNTIFS('attack-vectors-knowledge-base'!$B:$B,$A6,'attack-vectors-knowledge-base'!$F:$F,C$3) -> 0 | D6: =COUNTIFS('attack-vectors-knowledge-base'!$B:$B,$A6,'attack-vectors-knowledge-base'!$F:$F,D$3) -> 9 | E6: =COUNTIFS('attack-vectors-knowledge-base'!$B:$B,$A6,'attack-vectors-knowledge-base'!$F:$F,E$3) -> 20 | F6: =COUNTIFS('attack-vectors-knowledge-base'!$B:$B,$A6,'attack-vectors-knowledge-base'!$F:$F,F$3) -> 18 | G6: =SUM(B6:F6) -> 48 | H6: =COUNTIFS('attack-vectors-knowledge-base'!$B:$B,$A6,'attack-vectors-knowledge-base'!$D:$D,"Known vulnerability") -> 25 | I6: =COUNTIFS('attack-vectors-knowledge-base'!$B:$B,$A6,'attack-vectors-knowledge-base'!$Z:$Z,"Yes*") -> 22
A7: External network | B7: =COUNTIFS('attack-vectors-knowledge-base'!$B:$B,$A7,'attack-vectors-knowledge-base'!$F:$F,B$3) -> 1 | C7: =COUNTIFS('attack-vectors-knowledge-base'!$B:$B,$A7,'attack-vectors-knowledge-base'!$F:$F,C$3) -> 1 | D7: =COUNTIFS('attack-vectors-knowledge-base'!$B:$B,$A7,'attack-vectors-knowledge-base'!$F:$F,D$3) -> 2 | E7: =COUNTIFS('attack-vectors-knowledge-base'!$B:$B,$A7,'attack-vectors-knowledge-base'!$F:$F,E$3) -> 6 | F7: =COUNTIFS('attack-vectors-knowledge-base'!$B:$B,$A7,'attack-vectors-knowledge-base'!$F:$F,F$3) -> 44 | G7: =SUM(B7:F7) -> 54 | H7: =COUNTIFS('attack-vectors-knowledge-base'!$B:$B,$A7,'attack-vectors-knowledge-base'!$D:$D,"Known vulnerability") -> 47 | I7: =COUNTIFS('attack-vectors-knowledge-base'!$B:$B,$A7,'attack-vectors-knowledge-base'!$Z:$Z,"Yes*") -> 47
A8: Active Directory | B8: =COUNTIFS('attack-vectors-knowledge-base'!$B:$B,$A8,'attack-vectors-knowledge-base'!$F:$F,B$3) -> 1 | C8: =COUNTIFS('attack-vectors-knowledge-base'!$B:$B,$A8,'attack-vectors-knowledge-base'!$F:$F,C$3) -> 0 | D8: =COUNTIFS('attack-vectors-knowledge-base'!$B:$B,$A8,'attack-vectors-knowledge-base'!$F:$F,D$3) -> 6 | E8: =COUNTIFS('attack-vectors-knowledge-base'!$B:$B,$A8,'attack-vectors-knowledge-base'!$F:$F,E$3) -> 27 | F8: =COUNTIFS('attack-vectors-knowledge-base'!$B:$B,$A8,'attack-vectors-knowledge-base'!$F:$F,F$3) -> 4 | G8: =SUM(B8:F8) -> 38 | H8: =COUNTIFS('attack-vectors-knowledge-base'!$B:$B,$A8,'attack-vectors-knowledge-base'!$D:$D,"Known vulnerability") -> 11 | I8: =COUNTIFS('attack-vectors-knowledge-base'!$B:$B,$A8,'attack-vectors-knowledge-base'!$Z:$Z,"Yes*") -> 8
A9: Cloud | B9: =COUNTIFS('attack-vectors-knowledge-base'!$B:$B,$A9,'attack-vectors-knowledge-base'!$F:$F,B$3) -> 1 | C9: =COUNTIFS('attack-vectors-knowledge-base'!$B:$B,$A9,'attack-vectors-knowledge-base'!$F:$F,C$3) -> 0 | D9: =COUNTIFS('attack-vectors-knowledge-base'!$B:$B,$A9,'attack-vectors-knowledge-base'!$F:$F,D$3) -> 3 | E9: =COUNTIFS('attack-vectors-knowledge-base'!$B:$B,$A9,'attack-vectors-knowledge-base'!$F:$F,E$3) -> 18 | F9: =COUNTIFS('attack-vectors-knowledge-base'!$B:$B,$A9,'attack-vectors-knowledge-base'!$F:$F,F$3) -> 4 | G9: =SUM(B9:F9) -> 26 | H9: =COUNTIFS('attack-vectors-knowledge-base'!$B:$B,$A9,'attack-vectors-knowledge-base'!$D:$D,"Known vulnerability") -> 7 | I9: =COUNTIFS('attack-vectors-knowledge-base'!$B:$B,$A9,'attack-vectors-knowledge-base'!$Z:$Z,"Yes*") -> 3
A10: Mobile | B10: =COUNTIFS('attack-vectors-knowledge-base'!$B:$B,$A10,'attack-vectors-knowledge-base'!$F:$F,B$3) -> 0 | C10: =COUNTIFS('attack-vectors-knowledge-base'!$B:$B,$A10,'attack-vectors-knowledge-base'!$F:$F,C$3) -> 1 | D10: =COUNTIFS('attack-vectors-knowledge-base'!$B:$B,$A10,'attack-vectors-knowledge-base'!$F:$F,D$3) -> 8 | E10: =COUNTIFS('attack-vectors-knowledge-base'!$B:$B,$A10,'attack-vectors-knowledge-base'!$F:$F,E$3) -> 2 | F10: =COUNTIFS('attack-vectors-knowledge-base'!$B:$B,$A10,'attack-vectors-knowledge-base'!$F:$F,F$3) -> 0 | G10: =SUM(B10:F10) -> 11 | H10: =COUNTIFS('attack-vectors-knowledge-base'!$B:$B,$A10,'attack-vectors-knowledge-base'!$D:$D,"Known vulnerability") -> 0 | I10: =COUNTIFS('attack-vectors-knowledge-base'!$B:$B,$A10,'attack-vectors-knowledge-base'!$Z:$Z,"Yes*") -> 0
A11: Wireless | B11: =COUNTIFS('attack-vectors-knowledge-base'!$B:$B,$A11,'attack-vectors-knowledge-base'!$F:$F,B$3) -> 0 | C11: =COUNTIFS('attack-vectors-knowledge-base'!$B:$B,$A11,'attack-vectors-knowledge-base'!$F:$F,C$3) -> 1 | D11: =COUNTIFS('attack-vectors-knowledge-base'!$B:$B,$A11,'attack-vectors-knowledge-base'!$F:$F,D$3) -> 2 | E11: =COUNTIFS('attack-vectors-knowledge-base'!$B:$B,$A11,'attack-vectors-knowledge-base'!$F:$F,E$3) -> 6 | F11: =COUNTIFS('attack-vectors-knowledge-base'!$B:$B,$A11,'attack-vectors-knowledge-base'!$F:$F,F$3) -> 0 | G11: =SUM(B11:F11) -> 9 | H11: =COUNTIFS('attack-vectors-knowledge-base'!$B:$B,$A11,'attack-vectors-knowledge-base'!$D:$D,"Known vulnerability") -> 0 | I11: =COUNTIFS('attack-vectors-knowledge-base'!$B:$B,$A11,'attack-vectors-knowledge-base'!$Z:$Z,"Yes*") -> 0
A12: Social engineering | B12: =COUNTIFS('attack-vectors-knowledge-base'!$B:$B,$A12,'attack-vectors-knowledge-base'!$F:$F,B$3) -> 0 | C12: =COUNTIFS('attack-vectors-knowledge-base'!$B:$B,$A12,'attack-vectors-knowledge-base'!$F:$F,C$3) -> 0 | D12: =COUNTIFS('attack-vectors-knowledge-base'!$B:$B,$A12,'attack-vectors-knowledge-base'!$F:$F,D$3) -> 4 | E12: =COUNTIFS('attack-vectors-knowledge-base'!$B:$B,$A12,'attack-vectors-knowledge-base'!$F:$F,E$3) -> 11 | F12: =COUNTIFS('attack-vectors-knowledge-base'!$B:$B,$A12,'attack-vectors-knowledge-base'!$F:$F,F$3) -> 1 | G12: =SUM(B12:F12) -> 16 | H12: =COUNTIFS('attack-vectors-knowledge-base'!$B:$B,$A12,'attack-vectors-knowledge-base'!$D:$D,"Known vulnerability") -> 5 | I12: =COUNTIFS('attack-vectors-knowledge-base'!$B:$B,$A12,'attack-vectors-knowledge-base'!$Z:$Z,"Yes*") -> 5
A13: Physical | B13: =COUNTIFS('attack-vectors-knowledge-base'!$B:$B,$A13,'attack-vectors-knowledge-base'!$F:$F,B$3) -> 0 | C13: =COUNTIFS('attack-vectors-knowledge-base'!$B:$B,$A13,'attack-vectors-knowledge-base'!$F:$F,C$3) -> 1 | D13: =COUNTIFS('attack-vectors-knowledge-base'!$B:$B,$A13,'attack-vectors-knowledge-base'!$F:$F,D$3) -> 7 | E13: =COUNTIFS('attack-vectors-knowledge-base'!$B:$B,$A13,'attack-vectors-knowledge-base'!$F:$F,E$3) -> 1 | F13: =COUNTIFS('attack-vectors-knowledge-base'!$B:$B,$A13,'attack-vectors-knowledge-base'!$F:$F,F$3) -> 0 | G13: =SUM(B13:F13) -> 9 | H13: =COUNTIFS('attack-vectors-knowledge-base'!$B:$B,$A13,'attack-vectors-knowledge-base'!$D:$D,"Known vulnerability") -> 0 | I13: =COUNTIFS('attack-vectors-knowledge-base'!$B:$B,$A13,'attack-vectors-knowledge-base'!$Z:$Z,"Yes*") -> 0
A14: Endpoint | B14: =COUNTIFS('attack-vectors-knowledge-base'!$B:$B,$A14,'attack-vectors-knowledge-base'!$F:$F,B$3) -> 0 | C14: =COUNTIFS('attack-vectors-knowledge-base'!$B:$B,$A14,'attack-vectors-knowledge-base'!$F:$F,C$3) -> 0 | D14: =COUNTIFS('attack-vectors-knowledge-base'!$B:$B,$A14,'attack-vectors-knowledge-base'!$F:$F,D$3) -> 0 | E14: =COUNTIFS('attack-vectors-knowledge-base'!$B:$B,$A14,'attack-vectors-knowledge-base'!$F:$F,E$3) -> 16 | F14: =COUNTIFS('attack-vectors-knowledge-base'!$B:$B,$A14,'attack-vectors-knowledge-base'!$F:$F,F$3) -> 1 | G14: =SUM(B14:F14) -> 17 | H14: =COUNTIFS('attack-vectors-knowledge-base'!$B:$B,$A14,'attack-vectors-knowledge-base'!$D:$D,"Known vulnerability") -> 10 | I14: =COUNTIFS('attack-vectors-knowledge-base'!$B:$B,$A14,'attack-vectors-knowledge-base'!$Z:$Z,"Yes*") -> 10
A15: AI / LLM | B15: =COUNTIFS('attack-vectors-knowledge-base'!$B:$B,$A15,'attack-vectors-knowledge-base'!$F:$F,B$3) -> 0 | C15: =COUNTIFS('attack-vectors-knowledge-base'!$B:$B,$A15,'attack-vectors-knowledge-base'!$F:$F,C$3) -> 0 | D15: =COUNTIFS('attack-vectors-knowledge-base'!$B:$B,$A15,'attack-vectors-knowledge-base'!$F:$F,D$3) -> 3 | E15: =COUNTIFS('attack-vectors-knowledge-base'!$B:$B,$A15,'attack-vectors-knowledge-base'!$F:$F,E$3) -> 6 | F15: =COUNTIFS('attack-vectors-knowledge-base'!$B:$B,$A15,'attack-vectors-knowledge-base'!$F:$F,F$3) -> 9 | G15: =SUM(B15:F15) -> 18 | H15: =COUNTIFS('attack-vectors-knowledge-base'!$B:$B,$A15,'attack-vectors-knowledge-base'!$D:$D,"Known vulnerability") -> 11 | I15: =COUNTIFS('attack-vectors-knowledge-base'!$B:$B,$A15,'attack-vectors-knowledge-base'!$Z:$Z,"Yes*") -> 6
A16: Total | B16: =SUM(B4:B15) -> 4 | C16: =SUM(C4:C15) -> 12 | D16: =SUM(D4:D15) -> 75 | E16: =SUM(E4:E15) -> 140 | F16: =SUM(F4:F15) -> 118 | G16: =SUM(G4:G15) -> 349 | H16: =SUM(H4:H15) -> 154 | I16: =SUM(I4:I15) -> 137
A18: Check: number of rows with ID in main table | B18: =COUNTA('attack-vectors-knowledge-base'!$A:$A)-1 -> 349
A19: Check: number of CVE rows (ID starts with CVE-) | B19: =SUMPRODUCT(--(LEFT('attack-vectors-knowledge-base'!$A$2:$A$2000,4)="CVE-")) -> 154
A20: Check: number of rows in KEV | B20: =SUMPRODUCT(--(LEFT('attack-vectors-knowledge-base'!$Z$2:$Z$2000,3)="Yes")) -> 137
